[
    {
        "input": "【Background】\n【角色定义】你是一名消费者,你需要充分了解两个商家提供的生活项目并进行比较, 根据关键要素抽取规则和项目匹配规则来判断两个项目是否相同或匹配，并且以结构化数据的形式把两个项目结果展示出来。\n【Requirements】\n\n\n项目单的信息包括：商品标题、项目单详情、有效期、营业时间、适用人数、购买限制等。关键要素包括：服务名称、适用部位、服务方式、服务时长、适用人群、适用日期/时段、非服务类商品。（注意：如果有枚举值需要归类到枚举值，如果该内容在枚举值之外则默认为null；严格按照优先级，获取信息后不再考虑剩余。\"\n    \"1.服务名称，同一项目单可能包含多个项目，需要全部列举（注意：出现好评礼、会员礼所附赠的项目不计入服务名称。例如：“好评一次深层洁净60分钟”，则服务名称为“null”。优先级：商品标题 > 服务功效 > 服务流程/步骤\n     枚举值：\n     1.1深层洁净(收缩毛孔)\n     1.2补水保湿(皮肤清洁、毛孔洗澡)\n     1.3祛痘\n     1.4美白嫩肤\n     1.5淡斑祛斑\n     1.6紧致提拉\n     1.7修复护理\n     1.8脱毛\n     1.9眼部护理\n     1.10肩颈按摩\n     1.11SPA\n     1.12头疗\n     1.13养生调理\n     1.14瘦身纤体\n     1.15美胸美臀\n\n    2.适用部位：和服务名称对应。优先级：商品标题 > 服务功效 > 服务流程/步骤\n     枚举值：\n     2.1深层洁净/补水保湿/祛痘/美白嫩肤/淡斑祛斑/紧致提拉/修复护理：2.1.1面部,2.1.2部分面部,2.1.3背部 \n     2.2脱毛：2.2.1口唇,2.2.2腋下,2.2.3面部,2.2.4手臂,2.2.5腿部,2.2.6私密/比基尼\n     2.3眼部护理：2.3.1眼部 \n     2.4肩颈按摩：2.4.1肩颈,2.4.2肩颈+背 \n     2.5SPA：2.5.1全身,2.5.2肩颈+腰背,2.5.3肩颈+背部+腿部,2.5.4肩颈+腰腹+腿,2.5.5头+肩+颈+背,2.5.6背部 \n     2.6头疗：2.6.1头部\n     2.7养生调理：2.7.1全身(未指明部位),2.7.2局部(非全身，或者指明某个部位) \n     2.8瘦身纤体：2.8.1全身,2.8.2局部塑形 \n     2.9美胸美臀：2.9.1胸部,2.9.2臀部\n    \n    3.服务方式：和服务名称对应。优先级：项目单详情>商品标题\n     枚举值：（注意：1.未提到以下内容的，输出null;2.如果出现2种或者2种以上结果需要都输出）\n     3.1深层洁净：3.1.1)仪器(超微小气泡/大气泡/臭氧泡泡/魔法活氧泡泡) 3.1.2)海菲秀 3.1.3)泥膜/面膜 3.1.4)白牌产品 \n    3.2补水保湿：3.2.1)B5精华 3.2.2)修丽可 3.2.3)日式pola 3.2.4)日式晓姿 3.2.5)赫莲娜HR 3.2.6)伊芙珑evelom 3.2.7)海蓝之谜LA MER 3.2.8)瑞妍cellcosment 3.2.9)莱珀妮 LA PRAIRIE 3.2.10)迪奥DIOR 3.2.11)圣罗兰YSL 3.2.12)诚美DGR 3.2.13)法尔曼VALMONT 3.2.14)菲洛嘉FILORGA 3.2.15)白牌产品\n     3.3祛痘：3.3.1)手工针清/皮铲/护理 3.3.2)点阵激光 3.3.3)红蓝光/PDT光能/烤光 3.3.4)刷酸/果酸 3.3.5)草本 \n     3.4美白嫩肤：3.4.1)焕肤类 3.4.2)氨甲环酸 3.4.3)大牌产品(菲洛嘉) 3.4.4)普牌产品(欧诗漫) 3.4.5)白牌产品 \n     3.5紧致提拉：3.5.1)手法按摩类 3.5.2)抗糖祛黄/生物酶疗 3.5.3)木乃伊紧致 3.5.4)大牌产品(赫莲娜/日式POLA) 3.5.5)白牌产品 \n     3.6修复护理：3.6.1)酵素/乳糖酸/骨胶原/活性酶 3.6.2)大牌产品(赫莲娜/伊芙珑/海蓝之谜/瑞妍/莱珀妮/迪奥/圣罗兰诚美DGR/法尔曼/菲洛嘉) 3.6.3)白牌产品\n     3.7肩颈按摩：3.7.1)使用精油 3.7.2)不使用精油 3.7.3)热石精油 3.7.4)水疗\n     3.8全身SPA：3.8.1)使用精油 3.8.2)不使用精油 3.8.3)热石精油 3.8.4)水疗\n     3.9头疗：3.9.1)使用精油 3.9.2)不使用精油 \n     3.10养生调理：3.10.1)灸类 3.10.2)刮痧 3.10.3)罐类 3.10.4)蒸/浴类 3.10.5)经络/净排类 3.10.6)产后修复类\n     3.11瘦身纤体：3.11.1)针灸/拔罐/经络 3.11.2)刮痧 3.11.3)仪器 3.11.4)调理粉/精油\n     3.12.美胸美臀：3.12.1)使用精油 3.12.2)不使用精油\n\n    4.服务时长，总服务时长(服务项目的服务时长总和)。优先级：商品标题>项目单详情\n    需要映射到枚举值：(0-30]、(30-40]、(40-60]、(60-80]、(80-90]、(90-100]、(100-120]、(120-∞]（输出答案时需要输出具体的枚举值内容）\n\n    5.适用人群，包括性别、年龄、用户类型（出现“XX节”属于营销词，不能作为性别的判断，eg.女神节专属、母亲节，不能判断性别为女性） 优先级：购买限制>商品标题>项目单详情\n     枚举值：（注意：此项优先级：用户类型>性别>年龄，只需输出一个类别）\n     5.1用户类型：5.1.1新客价格（第一次使用该项目的用户）\n     5.2性别：5.2.1男性，5.2.2女性\n     5.3年龄：5.3.1儿童（0-12周岁）,5.3.2成人（18岁以上）\n     5.4不限通用(每人限购1份，不限年龄，性别)\n\n    6.适用日期/时段（注意：全天可用等于商家营业时间可用；闲时指的是周一到周五的下午4点前）  优先级：项目单详情>商品标题>购买须知\n    注意1：项目单详情中信息多处不符一致时，则取最小时段进行对比，eg1.A单适用日期：2025年7月1日-2025年9月1日，周一-周五10:00-19:00可用；B单适用日期2025.7.1-2025.10.1周一到周日10:00-22:00，则AB两单适用日期/时段不一致。eg2.2025年8月1日-2025年8月30日，周一-周五10:00-19:00可用；B单适用日期2025.7.1-2025.10.1周一-周天10:00-19:00可用，则AB两单适用日期/时段一致（不考虑年月日时格式）\n    注意2：适用日期/时段：从营业时间得到信息，仅看“周一-周日”、“xx月xx日-xx月xx日”、“xx:xx-xx:xx”、“xx点-xx点”等类似字眼，无需关注特殊节假日；时段：由“开始时间”和“结束时间”组成，输出具体的时间，例如“10:00-22:00” \n\n    7.非服务类商品：指的是除服务名称以外的内容，eg.“深层洁净60分钟+（含/送/赠）XX面膜2盒”，”非服务商品为“XX面膜，2盒”。如果是仅面膜、产品，零食、皮肤检测等非美容美体产品不算非服务产品，此时输出null。\n\n    8.白牌产品：指的是小厂商生产的没有牌子的商品，白牌是相对品牌而言的。\n\n\n    项目单匹配规则：根据抽取出来的要素和以下规则判断是否为同一项目单“注意：如果无法识别出来则默认为null”\n     1.服务名称：需完全一致，否则认为两个项目单不一致(不考虑顺序)。\n     2.适用部位：需完全一致，否则认为两个项目单不一致(不考虑顺序)。\n     3.服务方式：任意一方有值另一方空值，不可以视为一致。需要两侧都有值进行判断是否一致。\n     4.服务时长：如果任意一方有值另一方空值，可以视为一致。但当双方都有值时，双方时长一致才算一致。\n     5.适用人群：性别、年龄、用户类型要完全一样才算一致，如果任意一方空值则默认为“不限通用”，随后再对比出结果。\n     6.适用日期/时段：\n      1)当只有适用日期（年月日）时，日期精确到年月日相同则认为一致，eg.A单适用日期：2025年7月1日-2025年10月1日；B单适用日期2025.7.1-2025.10.1，则AB两单适用日期一致。（不考虑年月日格式）\n      2)当任意一方“适用日期”为空值，则取适用时段或者运营时间进行比较，AB两单之间起始及终止时间相差为1小时以内，可视为一致，超过1小时则为不一致。\n     7.非服务类商品：\n      1)纯非服务类商品，无需参与匹配。\n      2)若出现服务名称+非服务产品，针对服务内容按照规则匹配；非服务类商品需精准匹配，内容具体到名称+规格或者单位或者品牌。eg.“深层洁净60分钟+（含/送/赠）XX面膜2盒”，”非服务商品为“2盒XX面膜”\n    判断步骤：\n     1. 根据输入的项目单信息和规则抽取相应的要素，以及输出对应的枚举值内容\n     2. 根据抽取要素、枚举值内容和匹配规则来判断两个项目单是否匹配\n     \n     \n\n【Input】 \n1.项目单A：古瑶神烙舒缓放松肩颈套餐（60分钟）3次，限制：每人限购1张，须知：需提前预约，周一至周日全天可用，单次尽可核销一份。有效时间：购买后90天以内有效，规则提醒：不再与其他优惠同享，适用人数：每张优惠券最多1人使用。退款规则：支持随时退、过期退。若次数未使用，可随时退全部实付金额，如发生核销后再申请退款，剩余所有未核销次数将一起退款，本商品为阶梯定价品，退款金额如下计算：累积使用1次，单次价格：36.30元，预计可退金额：62.70元；累积使用2次，单次价格：31.35元，预计可退金额：31.35元；累积使用3次，单次价格：31.35元，预计可退金额：0元 适用门店（4）：古瑶神烙龙江店、古瑶神烙勒流店、古瑶神烙容桂店、古瑶神烙大良店。项目单B:女性专享补水亮肤脸部套餐，限制：每人限购1张，须知：需提前预约，周一至周日全天可用，单次尽可核销一份。有效时间：购买后90天以内有效，规则提醒：不再与其他优惠同享，适用人数：每张优惠券最多1人使用。服务部位：头部，服务流程：净化清洁全脸部5分钟，面部精华开穴全脸部10分钟，面部烙脸全脸部10分钟，面部精华提升全面部5分钟，敷补水面膜全脸部10分钟。服务设施：茶点水果饮料（附赠小吃）适用门店（4）：古瑶神烙龙江店、古瑶神烙勒流店、古瑶神烙容桂店、古瑶神烙大良店。\n\n\n\n【Output Requirement】\n 你的输出必须满足以下JSON_SCHEMA{'$schema': 'http://json-schema.org/draft-07/schema#', 'type': 'object', 'properties': {'项目单A': {'type': 'object', 'properties': {'1.服务名称': {'type': 'array', 'items': {'type': 'string', 'enum': ['1.1', '1.2', '1.3', '1.4', '1.5', '1.6', '1.7', '1.8', '1.9', '1.10', '1.11', '1.12', '1.13', '1.14', '1.15', 'null']}}, '2.适用部位': {'type': 'array', 'items': {'type': 'string', 'enum': ['2.1.1', '2.1.2', '2.1.3', '2.2.1', '2.2.2', '2.2.3', '2.2.4', '2.2.5', '2.2.6', '2.3.1', '2.4.1', '2.4.2', '2.5.1', '2.5.2', '2.5.3', '2.5.4', '2.5.5', '2.5.6', '2.6.1', '2.7.1', '2.7.2', '2.8.1', '2.8.2', '2.9.1', '2.9.2', 'null']}}, '3.服务方式': {'type': 'array', 'items': {'type': 'string', 'enum': ['3.1.1', '3.1.2', '3.1.3', '3.1.4', '3.2.1', '3.2.2', '3.2.3', '3.2.4', '3.2.5', '3.2.6', '3.2.7', '3.2.8', '3.2.9', '3.2.10', '3.2.11', '3.2.12', '3.2.13', '3.2.14', '3.2.15', '3.3.1', '3.3.2', '3.3.3', '3.3.4', '3.3.5', '3.4.1', '3.4.2', '3.4.3', '3.4.4', '3.4.5', '3.5.1', '3.5.2', '3.5.3', '3.5.4', '3.5.5', '3.6.1', '3.6.2', '3.6.3', '3.7.1', '3.7.2', '3.7.3', '3.7.4', '3.8.1', '3.8.2', '3.8.3', '3.8.4', '3.9.1', '3.9.2', '3.10.1', '3.10.2', '3.10.3', '3.10.4', '3.10.5', '3.10.6', '3.11.1', '3.11.2', '3.11.3', '3.11.4', '3.12.1', '3.12.2', 'null']}}, '4.服务时长': {'type': 'string', 'enum': ['(0-30]', '(30-40]', '(40-60]', '(60-80]', '(80-90]', '(90-100]', '(100-120]', '(120-∞]', 'null']}, '5.适用人群': {'type': 'string', 'enum': ['5.1.1', '5.2.1', '5.2.2', '5.3.1', '5.3.2', '5.4', 'null']}, '6.适用日期/时段': {'type': 'string'}, '7.非服务类商品': {'type': 'string'}}, 'required': ['1.服务名称', '2.适用部位', '3.服务方式', '4.服务时长', '5.适用人群', '6.适用日期/时段', '7.非服务类商品'], 'additionalProperties': False}, '项目单B': {'type': 'object', 'properties': {'1.服务名称': {'type': 'array', 'items': {'type': 'string', 'enum': ['1.1', '1.2', '1.3', '1.4', '1.5', '1.6', '1.7', '1.8', '1.9', '1.10', '1.11', '1.12', '1.13', '1.14', '1.15', 'null']}}, '2.适用部位': {'type': 'array', 'items': {'type': 'string', 'enum': ['2.1.1', '2.1.2', '2.1.3', '2.2.1', '2.2.2', '2.2.3', '2.2.4', '2.2.5', '2.2.6', '2.3.1', '2.4.1', '2.4.2', '2.5.1', '2.5.2', '2.5.3', '2.5.4', '2.5.5', '2.5.6', '2.6.1', '2.7.1', '2.7.2', '2.8.1', '2.8.2', '2.9.1', '2.9.2', 'null']}}, '3.服务方式': {'type': 'array', 'items': {'type': 'string', 'enum': ['3.1.1', '3.1.2', '3.1.3', '3.1.4', '3.2.1', '3.2.2', '3.2.3', '3.2.4', '3.2.5', '3.2.6', '3.2.7', '3.2.8', '3.2.9', '3.2.10', '3.2.11', '3.2.12', '3.2.13', '3.2.14', '3.2.15', '3.3.1', '3.3.2', '3.3.3', '3.3.4', '3.3.5', '3.4.1', '3.4.2', '3.4.3', '3.4.4', '3.4.5', '3.5.1', '3.5.2', '3.5.3', '3.5.4', '3.5.5', '3.6.1', '3.6.2', '3.6.3', '3.7.1', '3.7.2', '3.7.3', '3.7.4', '3.8.1', '3.8.2', '3.8.3', '3.8.4', '3.9.1', '3.9.2', '3.10.1', '3.10.2', '3.10.3', '3.10.4', '3.10.5', '3.10.6', '3.11.1', '3.11.2', '3.11.3', '3.11.4', '3.12.1', '3.12.2', 'null']}}, '4.服务时长': {'type': 'string', 'enum': ['(0-30]', '(30-40]', '(40-60]', '(60-80]', '(80-90]', '(90-100]', '(100-120]', '(120-∞]', 'null']}, '5.适用人群': {'type': 'string', 'enum': ['5.1.1', '5.2.1', '5.2.2', '5.3.1', '5.3.2', '5.4', 'null']}, '6.适用日期/时段': {'type': 'string'}, '7.非服务类商品': {'type': 'string'}}, 'required': ['1.服务名称', '2.适用部位', '3.服务方式', '4.服务时长', '5.适用人群', '6.适用日期/时段', '7.非服务类商品'], 'additionalProperties': False}, '匹配结果': {'type': 'string', 'enum': ['是', '否']}}, 'required': ['项目单A', '项目单B', '匹配结果'], 'additionalProperties': False}",
        "target": {
            "项目单A": {
                "1.服务名称": [
                    "1.10"
                ],
                "2.适用部位": [
                    "2.4.1"
                ],
                "3.服务方式": [
                    "null"
                ],
                "4.服务时长": "(40-60]",
                "5.适用人群": "5.4",
                "6.适用日期/时段": "周一至周日全天可用",
                "7.非服务类商品": "null"
            },
            "项目单B": {
                "1.服务名称": [
                    "1.2"
                ],
                "2.适用部位": [
                    "2.1.1"
                ],
                "3.服务方式": [
                    "3.2.15"
                ],
                "4.服务时长": "(30-40]",
                "5.适用人群": "5.2.2",
                "6.适用日期/时段": "周一至周日全天可用",
                "7.非服务类商品": "null"
            },
            "匹配结果": "否"
        },
        "json_schema": {
            "$schema": "http://json-schema.org/draft-07/schema#",
            "type": "object",
            "properties": {
                "项目单A": {
                    "type": "object",
                    "properties": {
                        "1.服务名称": {
                            "type": "array",
                            "items": {
                                "type": "string",
                                "enum": [
                                    "1.1",
                                    "1.2",
                                    "1.3",
                                    "1.4",
                                    "1.5",
                                    "1.6",
                                    "1.7",
                                    "1.8",
                                    "1.9",
                                    "1.10",
                                    "1.11",
                                    "1.12",
                                    "1.13",
                                    "1.14",
                                    "1.15",
                                    "null"
                                ]
                            }
                        },
                        "2.适用部位": {
                            "type": "array",
                            "items": {
                                "type": "string",
                                "enum": [
                                    "2.1.1",
                                    "2.1.2",
                                    "2.1.3",
                                    "2.2.1",
                                    "2.2.2",
                                    "2.2.3",
                                    "2.2.4",
                                    "2.2.5",
                                    "2.2.6",
                                    "2.3.1",
                                    "2.4.1",
                                    "2.4.2",
                                    "2.5.1",
                                    "2.5.2",
                                    "2.5.3",
                                    "2.5.4",
                                    "2.5.5",
                                    "2.5.6",
                                    "2.6.1",
                                    "2.7.1",
                                    "2.7.2",
                                    "2.8.1",
                                    "2.8.2",
                                    "2.9.1",
                                    "2.9.2",
                                    "null"
                                ]
                            }
                        },
                        "3.服务方式": {
                            "type": "array",
                            "items": {
                                "type": "string",
                                "enum": [
                                    "3.1.1",
                                    "3.1.2",
                                    "3.1.3",
                                    "3.1.4",
                                    "3.2.1",
                                    "3.2.2",
                                    "3.2.3",
                                    "3.2.4",
                                    "3.2.5",
                                    "3.2.6",
                                    "3.2.7",
                                    "3.2.8",
                                    "3.2.9",
                                    "3.2.10",
                                    "3.2.11",
                                    "3.2.12",
                                    "3.2.13",
                                    "3.2.14",
                                    "3.2.15",
                                    "3.3.1",
                                    "3.3.2",
                                    "3.3.3",
                                    "3.3.4",
                                    "3.3.5",
                                    "3.4.1",
                                    "3.4.2",
                                    "3.4.3",
                                    "3.4.4",
                                    "3.4.5",
                                    "3.5.1",
                                    "3.5.2",
                                    "3.5.3",
                                    "3.5.4",
                                    "3.5.5",
                                    "3.6.1",
                                    "3.6.2",
                                    "3.6.3",
                                    "3.7.1",
                                    "3.7.2",
                                    "3.7.3",
                                    "3.7.4",
                                    "3.8.1",
                                    "3.8.2",
                                    "3.8.3",
                                    "3.8.4",
                                    "3.9.1",
                                    "3.9.2",
                                    "3.10.1",
                                    "3.10.2",
                                    "3.10.3",
                                    "3.10.4",
                                    "3.10.5",
                                    "3.10.6",
                                    "3.11.1",
                                    "3.11.2",
                                    "3.11.3",
                                    "3.11.4",
                                    "3.12.1",
                                    "3.12.2",
                                    "null"
                                ]
                            }
                        },
                        "4.服务时长": {
                            "type": "string",
                            "enum": [
                                "(0-30]",
                                "(30-40]",
                                "(40-60]",
                                "(60-80]",
                                "(80-90]",
                                "(90-100]",
                                "(100-120]",
                                "(120-∞]",
                                "null"
                            ]
                        },
                        "5.适用人群": {
                            "type": "string",
                            "enum": [
                                "5.1.1",
                                "5.2.1",
                                "5.2.2",
                                "5.3.1",
                                "5.3.2",
                                "5.4",
                                "null"
                            ]
                        },
                        "6.适用日期/时段": {
                            "type": "string"
                        },
                        "7.非服务类商品": {
                            "type": "string"
                        }
                    },
                    "required": [
                        "1.服务名称",
                        "2.适用部位",
                        "3.服务方式",
                        "4.服务时长",
                        "5.适用人群",
                        "6.适用日期/时段",
                        "7.非服务类商品"
                    ],
                    "additionalProperties": false
                },
                "项目单B": {
                    "type": "object",
                    "properties": {
                        "1.服务名称": {
                            "type": "array",
                            "items": {
                                "type": "string",
                                "enum": [
                                    "1.1",
                                    "1.2",
                                    "1.3",
                                    "1.4",
                                    "1.5",
                                    "1.6",
                                    "1.7",
                                    "1.8",
                                    "1.9",
                                    "1.10",
                                    "1.11",
                                    "1.12",
                                    "1.13",
                                    "1.14",
                                    "1.15",
                                    "null"
                                ]
                            }
                        },
                        "2.适用部位": {
                            "type": "array",
                            "items": {
                                "type": "string",
                                "enum": [
                                    "2.1.1",
                                    "2.1.2",
                                    "2.1.3",
                                    "2.2.1",
                                    "2.2.2",
                                    "2.2.3",
                                    "2.2.4",
                                    "2.2.5",
                                    "2.2.6",
                                    "2.3.1",
                                    "2.4.1",
                                    "2.4.2",
                                    "2.5.1",
                                    "2.5.2",
                                    "2.5.3",
                                    "2.5.4",
                                    "2.5.5",
                                    "2.5.6",
                                    "2.6.1",
                                    "2.7.1",
                                    "2.7.2",
                                    "2.8.1",
                                    "2.8.2",
                                    "2.9.1",
                                    "2.9.2",
                                    "null"
                                ]
                            }
                        },
                        "3.服务方式": {
                            "type": "array",
                            "items": {
                                "type": "string",
                                "enum": [
                                    "3.1.1",
                                    "3.1.2",
                                    "3.1.3",
                                    "3.1.4",
                                    "3.2.1",
                                    "3.2.2",
                                    "3.2.3",
                                    "3.2.4",
                                    "3.2.5",
                                    "3.2.6",
                                    "3.2.7",
                                    "3.2.8",
                                    "3.2.9",
                                    "3.2.10",
                                    "3.2.11",
                                    "3.2.12",
                                    "3.2.13",
                                    "3.2.14",
                                    "3.2.15",
                                    "3.3.1",
                                    "3.3.2",
                                    "3.3.3",
                                    "3.3.4",
                                    "3.3.5",
                                    "3.4.1",
                                    "3.4.2",
                                    "3.4.3",
                                    "3.4.4",
                                    "3.4.5",
                                    "3.5.1",
                                    "3.5.2",
                                    "3.5.3",
                                    "3.5.4",
                                    "3.5.5",
                                    "3.6.1",
                                    "3.6.2",
                                    "3.6.3",
                                    "3.7.1",
                                    "3.7.2",
                                    "3.7.3",
                                    "3.7.4",
                                    "3.8.1",
                                    "3.8.2",
                                    "3.8.3",
                                    "3.8.4",
                                    "3.9.1",
                                    "3.9.2",
                                    "3.10.1",
                                    "3.10.2",
                                    "3.10.3",
                                    "3.10.4",
                                    "3.10.5",
                                    "3.10.6",
                                    "3.11.1",
                                    "3.11.2",
                                    "3.11.3",
                                    "3.11.4",
                                    "3.12.1",
                                    "3.12.2",
                                    "null"
                                ]
                            }
                        },
                        "4.服务时长": {
                            "type": "string",
                            "enum": [
                                "(0-30]",
                                "(30-40]",
                                "(40-60]",
                                "(60-80]",
                                "(80-90]",
                                "(90-100]",
                                "(100-120]",
                                "(120-∞]",
                                "null"
                            ]
                        },
                        "5.适用人群": {
                            "type": "string",
                            "enum": [
                                "5.1.1",
                                "5.2.1",
                                "5.2.2",
                                "5.3.1",
                                "5.3.2",
                                "5.4",
                                "null"
                            ]
                        },
                        "6.适用日期/时段": {
                            "type": "string"
                        },
                        "7.非服务类商品": {
                            "type": "string"
                        }
                    },
                    "required": [
                        "1.服务名称",
                        "2.适用部位",
                        "3.服务方式",
                        "4.服务时长",
                        "5.适用人群",
                        "6.适用日期/时段",
                        "7.非服务类商品"
                    ],
                    "additionalProperties": false
                },
                "匹配结果": {
                    "type": "string",
                    "enum": [
                        "是",
                        "否"
                    ]
                }
            },
            "required": [
                "项目单A",
                "项目单B",
                "匹配结果"
            ],
            "additionalProperties": false
        },
        "no_required_eval_acc_keys": [
            "6.适用日期/时段"
        ],
        "model_response": "```json\n{\n    \"项目单A\": {\n        \"1.服务名称\": [\n            \"1.10\"\n        ],\n        \"2.适用部位\": [\n            \"2.4.1\"\n        ],\n        \"3.服务方式\": [\n            \"null\"\n        ],\n        \"4.服务时长\": \"(60-80]\",\n        \"5.适用人群\": \"5.4\",\n        \"6.适用日期/时段\": \"全天可用\",\n        \"7.非服务类商品\": \"null\"\n    },\n    \"项目单B\": {\n        \"1.服务名称\": [\n            \"1.2\",\n            \"1.4\"\n        ],\n        \"2.适用部位\": [\n            \"2.1.1\"\n        ],\n        \"3.服务方式\": [\n            \"3.2.15\"\n        ],\n        \"4.服务时长\": \"(30-40]\",\n        \"5.适用人群\": \"5.2.2\",\n        \"6.适用日期/时段\": \"全天可用\",\n        \"7.非服务类商品\": \"null\"\n    },\n    \"匹配结果\": \"否\"\n}\n```"
    },
    {
        "input": "【Background】\n【角色定义】你是一名消费者,你需要充分了解两个商家提供的生活项目并进行比较, 根据关键要素抽取规则和项目匹配规则来判断两个项目是否相同或匹配，并且以结构化数据的形式把两个项目结果展示出来。\n【Requirements】\n\n\n项目单的信息包括：商品标题、项目单详情、有效期、营业时间、适用人数、购买限制等。关键要素包括：服务名称、适用部位、服务方式、服务时长、适用人群、适用日期/时段、非服务类商品。（注意：如果有枚举值需要归类到枚举值，如果该内容在枚举值之外则默认为null；严格按照优先级，获取信息后不再考虑剩余。\"\n    \"1.服务名称，同一项目单可能包含多个项目，需要全部列举（注意：出现好评礼、会员礼所附赠的项目不计入服务名称。例如：“好评一次深层洁净60分钟”，则服务名称为“null”。优先级：商品标题 > 服务功效 > 服务流程/步骤\n     枚举值：\n     1.1深层洁净(收缩毛孔)\n     1.2补水保湿(皮肤清洁、毛孔洗澡)\n     1.3祛痘\n     1.4美白嫩肤\n     1.5淡斑祛斑\n     1.6紧致提拉\n     1.7修复护理\n     1.8脱毛\n     1.9眼部护理\n     1.10肩颈按摩\n     1.11SPA\n     1.12头疗\n     1.13养生调理\n     1.14瘦身纤体\n     1.15美胸美臀\n\n    2.适用部位：和服务名称对应。优先级：商品标题 > 服务功效 > 服务流程/步骤\n     枚举值：\n     2.1深层洁净/补水保湿/祛痘/美白嫩肤/淡斑祛斑/紧致提拉/修复护理：2.1.1面部,2.1.2部分面部,2.1.3背部 \n     2.2脱毛：2.2.1口唇,2.2.2腋下,2.2.3面部,2.2.4手臂,2.2.5腿部,2.2.6私密/比基尼\n     2.3眼部护理：2.3.1眼部 \n     2.4肩颈按摩：2.4.1肩颈,2.4.2肩颈+背 \n     2.5SPA：2.5.1全身,2.5.2肩颈+腰背,2.5.3肩颈+背部+腿部,2.5.4肩颈+腰腹+腿,2.5.5头+肩+颈+背,2.5.6背部 \n     2.6头疗：2.6.1头部\n     2.7养生调理：2.7.1全身(未指明部位),2.7.2局部(非全身，或者指明某个部位) \n     2.8瘦身纤体：2.8.1全身,2.8.2局部塑形 \n     2.9美胸美臀：2.9.1胸部,2.9.2臀部\n    \n    3.服务方式：和服务名称对应。优先级：项目单详情>商品标题\n     枚举值：（注意：1.未提到以下内容的，输出null;2.如果出现2种或者2种以上结果需要都输出）\n     3.1深层洁净：3.1.1)仪器(超微小气泡/大气泡/臭氧泡泡/魔法活氧泡泡) 3.1.2)海菲秀 3.1.3)泥膜/面膜 3.1.4)白牌产品 \n    3.2补水保湿：3.2.1)B5精华 3.2.2)修丽可 3.2.3)日式pola 3.2.4)日式晓姿 3.2.5)赫莲娜HR 3.2.6)伊芙珑evelom 3.2.7)海蓝之谜LA MER 3.2.8)瑞妍cellcosment 3.2.9)莱珀妮 LA PRAIRIE 3.2.10)迪奥DIOR 3.2.11)圣罗兰YSL 3.2.12)诚美DGR 3.2.13)法尔曼VALMONT 3.2.14)菲洛嘉FILORGA 3.2.15)白牌产品\n     3.3祛痘：3.3.1)手工针清/皮铲/护理 3.3.2)点阵激光 3.3.3)红蓝光/PDT光能/烤光 3.3.4)刷酸/果酸 3.3.5)草本 \n     3.4美白嫩肤：3.4.1)焕肤类 3.4.2)氨甲环酸 3.4.3)大牌产品(菲洛嘉) 3.4.4)普牌产品(欧诗漫) 3.4.5)白牌产品 \n     3.5紧致提拉：3.5.1)手法按摩类 3.5.2)抗糖祛黄/生物酶疗 3.5.3)木乃伊紧致 3.5.4)大牌产品(赫莲娜/日式POLA) 3.5.5)白牌产品 \n     3.6修复护理：3.6.1)酵素/乳糖酸/骨胶原/活性酶 3.6.2)大牌产品(赫莲娜/伊芙珑/海蓝之谜/瑞妍/莱珀妮/迪奥/圣罗兰诚美DGR/法尔曼/菲洛嘉) 3.6.3)白牌产品\n     3.7肩颈按摩：3.7.1)使用精油 3.7.2)不使用精油 3.7.3)热石精油 3.7.4)水疗\n     3.8全身SPA：3.8.1)使用精油 3.8.2)不使用精油 3.8.3)热石精油 3.8.4)水疗\n     3.9头疗：3.9.1)使用精油 3.9.2)不使用精油 \n     3.10养生调理：3.10.1)灸类 3.10.2)刮痧 3.10.3)罐类 3.10.4)蒸/浴类 3.10.5)经络/净排类 3.10.6)产后修复类\n     3.11瘦身纤体：3.11.1)针灸/拔罐/经络 3.11.2)刮痧 3.11.3)仪器 3.11.4)调理粉/精油\n     3.12.美胸美臀：3.12.1)使用精油 3.12.2)不使用精油\n\n    4.服务时长，总服务时长(服务项目的服务时长总和)。优先级：商品标题>项目单详情\n    需要映射到枚举值：(0-30]、(30-40]、(40-60]、(60-80]、(80-90]、(90-100]、(100-120]、(120-∞]（输出答案时需要输出具体的枚举值内容）\n\n    5.适用人群，包括性别、年龄、用户类型（出现“XX节”属于营销词，不能作为性别的判断，eg.女神节专属、母亲节，不能判断性别为女性） 优先级：购买限制>商品标题>项目单详情\n     枚举值：（注意：此项优先级：用户类型>性别>年龄，只需输出一个类别）\n     5.1用户类型：5.1.1新客价格（第一次使用该项目的用户）\n     5.2性别：5.2.1男性，5.2.2女性\n     5.3年龄：5.3.1儿童（0-12周岁）,5.3.2成人（18岁以上）\n     5.4不限通用(每人限购1份，不限年龄，性别)\n\n    6.适用日期/时段（注意：全天可用等于商家营业时间可用；闲时指的是周一到周五的下午4点前）  优先级：项目单详情>商品标题>购买须知\n    注意1：项目单详情中信息多处不符一致时，则取最小时段进行对比，eg1.A单适用日期：2025年7月1日-2025年9月1日，周一-周五10:00-19:00可用；B单适用日期2025.7.1-2025.10.1周一到周日10:00-22:00，则AB两单适用日期/时段不一致。eg2.2025年8月1日-2025年8月30日，周一-周五10:00-19:00可用；B单适用日期2025.7.1-2025.10.1周一-周天10:00-19:00可用，则AB两单适用日期/时段一致（不考虑年月日时格式）\n    注意2：适用日期/时段：从营业时间得到信息，仅看“周一-周日”、“xx月xx日-xx月xx日”、“xx:xx-xx:xx”、“xx点-xx点”等类似字眼，无需关注特殊节假日；时段：由“开始时间”和“结束时间”组成，输出具体的时间，例如“10:00-22:00” \n\n    7.非服务类商品：指的是除服务名称以外的内容，eg.“深层洁净60分钟+（含/送/赠）XX面膜2盒”，”非服务商品为“XX面膜，2盒”。如果是仅面膜、产品，零食、皮肤检测等非美容美体产品不算非服务产品，此时输出null。\n\n    8.白牌产品：指的是小厂商生产的没有牌子的商品，白牌是相对品牌而言的。\n\n\n    项目单匹配规则：根据抽取出来的要素和以下规则判断是否为同一项目单“注意：如果无法识别出来则默认为null”\n     1.服务名称：需完全一致，否则认为两个项目单不一致(不考虑顺序)。\n     2.适用部位：需完全一致，否则认为两个项目单不一致(不考虑顺序)。\n     3.服务方式：任意一方有值另一方空值，不可以视为一致。需要两侧都有值进行判断是否一致。\n     4.服务时长：如果任意一方有值另一方空值，可以视为一致。但当双方都有值时，双方时长一致才算一致。\n     5.适用人群：性别、年龄、用户类型要完全一样才算一致，如果任意一方空值则默认为“不限通用”，随后再对比出结果。\n     6.适用日期/时段：\n      1)当只有适用日期（年月日）时，日期精确到年月日相同则认为一致，eg.A单适用日期：2025年7月1日-2025年10月1日；B单适用日期2025.7.1-2025.10.1，则AB两单适用日期一致。（不考虑年月日格式）\n      2)当任意一方“适用日期”为空值，则取适用时段或者运营时间进行比较，AB两单之间起始及终止时间相差为1小时以内，可视为一致，超过1小时则为不一致。\n     7.非服务类商品：\n      1)纯非服务类商品，无需参与匹配。\n      2)若出现服务名称+非服务产品，针对服务内容按照规则匹配；非服务类商品需精准匹配，内容具体到名称+规格或者单位或者品牌。eg.“深层洁净60分钟+（含/送/赠）XX面膜2盒”，”非服务商品为“2盒XX面膜”\n    判断步骤：\n     1. 根据输入的项目单信息和规则抽取相应的要素，以及输出对应的枚举值内容\n     2. 根据抽取要素、枚举值内容和匹配规则来判断两个项目单是否匹配\n     \n     \n\n【Input】 \n2.项目单A：【三伏养生】舒缓推拿+古法艾灸+三伏养生贴。优惠：门市价198-优惠132，仅需66元。下单立省132元。优惠详情：中式按摩60分钟，服务流程：1.腰背推拿按摩30分钟2.背部古法艾灸30分钟3.三伏养生帖0分钟。须知：免预约，周一至周天全天可用，购买后90天内有效。保障：过期退，随时退。门店：101家门店适用。购买须知：适用时间：购买后90天内有效，预约规则：无需预约，如遇高峰期时段可能需排队。适用人数：每张优惠券最多一人使用。其他规则：如需优惠券发票，请您在消费时向商户咨询。项目单B：拔罐（留罐）15分钟。须知：免预约，周一至周日全天可用，购买90天内有效。保障：随时退，过期退。门店：340家门店可用。服务设施：一次性床单，女性用品：头绳。服务部位：以下部位可选一个，肩颈、腰背。补充说明：顾客您好，建议您提前电话联系，以免您的等待时间过长或商家无法接单哦。根据每个人的身体情况不同，具体拔罐时间以实际情况为准，一般为5-15分钟。预约规则：无需预约，如遇高峰期时段可能需排队。适用人数：每张优惠券最多一人使用。其他规则：不再与其他优惠同享。\n\n\n\n【Output Requirement】\n 你的输出必须满足以下JSON_SCHEMA{'$schema': 'http://json-schema.org/draft-07/schema#', 'type': 'object', 'properties': {'项目单A': {'type': 'object', 'properties': {'1.服务名称': {'type': 'array', 'items': {'type': 'string', 'enum': ['1.1', '1.2', '1.3', '1.4', '1.5', '1.6', '1.7', '1.8', '1.9', '1.10', '1.11', '1.12', '1.13', '1.14', '1.15', 'null']}}, '2.适用部位': {'type': 'array', 'items': {'type': 'string', 'enum': ['2.1.1', '2.1.2', '2.1.3', '2.2.1', '2.2.2', '2.2.3', '2.2.4', '2.2.5', '2.2.6', '2.3.1', '2.4.1', '2.4.2', '2.5.1', '2.5.2', '2.5.3', '2.5.4', '2.5.5', '2.5.6', '2.6.1', '2.7.1', '2.7.2', '2.8.1', '2.8.2', '2.9.1', '2.9.2', 'null']}}, '3.服务方式': {'type': 'array', 'items': {'type': 'string', 'enum': ['3.1.1', '3.1.2', '3.1.3', '3.1.4', '3.2.1', '3.2.2', '3.2.3', '3.2.4', '3.2.5', '3.2.6', '3.2.7', '3.2.8', '3.2.9', '3.2.10', '3.2.11', '3.2.12', '3.2.13', '3.2.14', '3.2.15', '3.3.1', '3.3.2', '3.3.3', '3.3.4', '3.3.5', '3.4.1', '3.4.2', '3.4.3', '3.4.4', '3.4.5', '3.5.1', '3.5.2', '3.5.3', '3.5.4', '3.5.5', '3.6.1', '3.6.2', '3.6.3', '3.7.1', '3.7.2', '3.7.3', '3.7.4', '3.8.1', '3.8.2', '3.8.3', '3.8.4', '3.9.1', '3.9.2', '3.10.1', '3.10.2', '3.10.3', '3.10.4', '3.10.5', '3.10.6', '3.11.1', '3.11.2', '3.11.3', '3.11.4', '3.12.1', '3.12.2', 'null']}}, '4.服务时长': {'type': 'string', 'enum': ['(0-30]', '(30-40]', '(40-60]', '(60-80]', '(80-90]', '(90-100]', '(100-120]', '(120-∞]', 'null']}, '5.适用人群': {'type': 'string', 'enum': ['5.1.1', '5.2.1', '5.2.2', '5.3.1', '5.3.2', '5.4', 'null']}, '6.适用日期/时段': {'type': 'string'}, '7.非服务类商品': {'type': 'string'}}, 'required': ['1.服务名称', '2.适用部位', '3.服务方式', '4.服务时长', '5.适用人群', '6.适用日期/时段', '7.非服务类商品'], 'additionalProperties': False}, '项目单B': {'type': 'object', 'properties': {'1.服务名称': {'type': 'array', 'items': {'type': 'string', 'enum': ['1.1', '1.2', '1.3', '1.4', '1.5', '1.6', '1.7', '1.8', '1.9', '1.10', '1.11', '1.12', '1.13', '1.14', '1.15', 'null']}}, '2.适用部位': {'type': 'array', 'items': {'type': 'string', 'enum': ['2.1.1', '2.1.2', '2.1.3', '2.2.1', '2.2.2', '2.2.3', '2.2.4', '2.2.5', '2.2.6', '2.3.1', '2.4.1', '2.4.2', '2.5.1', '2.5.2', '2.5.3', '2.5.4', '2.5.5', '2.5.6', '2.6.1', '2.7.1', '2.7.2', '2.8.1', '2.8.2', '2.9.1', '2.9.2', 'null']}}, '3.服务方式': {'type': 'array', 'items': {'type': 'string', 'enum': ['3.1.1', '3.1.2', '3.1.3', '3.1.4', '3.2.1', '3.2.2', '3.2.3', '3.2.4', '3.2.5', '3.2.6', '3.2.7', '3.2.8', '3.2.9', '3.2.10', '3.2.11', '3.2.12', '3.2.13', '3.2.14', '3.2.15', '3.3.1', '3.3.2', '3.3.3', '3.3.4', '3.3.5', '3.4.1', '3.4.2', '3.4.3', '3.4.4', '3.4.5', '3.5.1', '3.5.2', '3.5.3', '3.5.4', '3.5.5', '3.6.1', '3.6.2', '3.6.3', '3.7.1', '3.7.2', '3.7.3', '3.7.4', '3.8.1', '3.8.2', '3.8.3', '3.8.4', '3.9.1', '3.9.2', '3.10.1', '3.10.2', '3.10.3', '3.10.4', '3.10.5', '3.10.6', '3.11.1', '3.11.2', '3.11.3', '3.11.4', '3.12.1', '3.12.2', 'null']}}, '4.服务时长': {'type': 'string', 'enum': ['(0-30]', '(30-40]', '(40-60]', '(60-80]', '(80-90]', '(90-100]', '(100-120]', '(120-∞]', 'null']}, '5.适用人群': {'type': 'string', 'enum': ['5.1.1', '5.2.1', '5.2.2', '5.3.1', '5.3.2', '5.4', 'null']}, '6.适用日期/时段': {'type': 'string'}, '7.非服务类商品': {'type': 'string'}}, 'required': ['1.服务名称', '2.适用部位', '3.服务方式', '4.服务时长', '5.适用人群', '6.适用日期/时段', '7.非服务类商品'], 'additionalProperties': False}, '匹配结果': {'type': 'string', 'enum': ['是', '否']}}, 'required': ['项目单A', '项目单B', '匹配结果'], 'additionalProperties': False}",
        "target": {
            "项目单A": {
                "1.服务名称": [
                    "1.13"
                ],
                "2.适用部位": [
                    "2.7.2"
                ],
                "3.服务方式": [
                    "3.10.1"
                ],
                "4.服务时长": "(40-60]",
                "5.适用人群": "5.4",
                "6.适用日期/时段": "周一至周天全天",
                "7.非服务类商品": "null"
            },
            "项目单B": {
                "1.服务名称": [
                    "1.13"
                ],
                "2.适用部位": [
                    "2.7.2"
                ],
                "3.服务方式": [
                    "3.10.3"
                ],
                "4.服务时长": "(0-30]",
                "5.适用人群": "5.4",
                "6.适用日期/时段": "周一至周天全天",
                "7.非服务类商品": "null"
            },
            "匹配结果": "否"
        },
        "json_schema": {
            "$schema": "http://json-schema.org/draft-07/schema#",
            "type": "object",
            "properties": {
                "项目单A": {
                    "type": "object",
                    "properties": {
                        "1.服务名称": {
                            "type": "array",
                            "items": {
                                "type": "string",
                                "enum": [
                                    "1.1",
                                    "1.2",
                                    "1.3",
                                    "1.4",
                                    "1.5",
                                    "1.6",
                                    "1.7",
                                    "1.8",
                                    "1.9",
                                    "1.10",
                                    "1.11",
                                    "1.12",
                                    "1.13",
                                    "1.14",
                                    "1.15",
                                    "null"
                                ]
                            }
                        },
                        "2.适用部位": {
                            "type": "array",
                            "items": {
                                "type": "string",
                                "enum": [
                                    "2.1.1",
                                    "2.1.2",
                                    "2.1.3",
                                    "2.2.1",
                                    "2.2.2",
                                    "2.2.3",
                                    "2.2.4",
                                    "2.2.5",
                                    "2.2.6",
                                    "2.3.1",
                                    "2.4.1",
                                    "2.4.2",
                                    "2.5.1",
                                    "2.5.2",
                                    "2.5.3",
                                    "2.5.4",
                                    "2.5.5",
                                    "2.5.6",
                                    "2.6.1",
                                    "2.7.1",
                                    "2.7.2",
                                    "2.8.1",
                                    "2.8.2",
                                    "2.9.1",
                                    "2.9.2",
                                    "null"
                                ]
                            }
                        },
                        "3.服务方式": {
                            "type": "array",
                            "items": {
                                "type": "string",
                                "enum": [
                                    "3.1.1",
                                    "3.1.2",
                                    "3.1.3",
                                    "3.1.4",
                                    "3.2.1",
                                    "3.2.2",
                                    "3.2.3",
                                    "3.2.4",
                                    "3.2.5",
                                    "3.2.6",
                                    "3.2.7",
                                    "3.2.8",
                                    "3.2.9",
                                    "3.2.10",
                                    "3.2.11",
                                    "3.2.12",
                                    "3.2.13",
                                    "3.2.14",
                                    "3.2.15",
                                    "3.3.1",
                                    "3.3.2",
                                    "3.3.3",
                                    "3.3.4",
                                    "3.3.5",
                                    "3.4.1",
                                    "3.4.2",
                                    "3.4.3",
                                    "3.4.4",
                                    "3.4.5",
                                    "3.5.1",
                                    "3.5.2",
                                    "3.5.3",
                                    "3.5.4",
                                    "3.5.5",
                                    "3.6.1",
                                    "3.6.2",
                                    "3.6.3",
                                    "3.7.1",
                                    "3.7.2",
                                    "3.7.3",
                                    "3.7.4",
                                    "3.8.1",
                                    "3.8.2",
                                    "3.8.3",
                                    "3.8.4",
                                    "3.9.1",
                                    "3.9.2",
                                    "3.10.1",
                                    "3.10.2",
                                    "3.10.3",
                                    "3.10.4",
                                    "3.10.5",
                                    "3.10.6",
                                    "3.11.1",
                                    "3.11.2",
                                    "3.11.3",
                                    "3.11.4",
                                    "3.12.1",
                                    "3.12.2",
                                    "null"
                                ]
                            }
                        },
                        "4.服务时长": {
                            "type": "string",
                            "enum": [
                                "(0-30]",
                                "(30-40]",
                                "(40-60]",
                                "(60-80]",
                                "(80-90]",
                                "(90-100]",
                                "(100-120]",
                                "(120-∞]",
                                "null"
                            ]
                        },
                        "5.适用人群": {
                            "type": "string",
                            "enum": [
                                "5.1.1",
                                "5.2.1",
                                "5.2.2",
                                "5.3.1",
                                "5.3.2",
                                "5.4",
                                "null"
                            ]
                        },
                        "6.适用日期/时段": {
                            "type": "string"
                        },
                        "7.非服务类商品": {
                            "type": "string"
                        }
                    },
                    "required": [
                        "1.服务名称",
                        "2.适用部位",
                        "3.服务方式",
                        "4.服务时长",
                        "5.适用人群",
                        "6.适用日期/时段",
                        "7.非服务类商品"
                    ],
                    "additionalProperties": false
                },
                "项目单B": {
                    "type": "object",
                    "properties": {
                        "1.服务名称": {
                            "type": "array",
                            "items": {
                                "type": "string",
                                "enum": [
                                    "1.1",
                                    "1.2",
                                    "1.3",
                                    "1.4",
                                    "1.5",
                                    "1.6",
                                    "1.7",
                                    "1.8",
                                    "1.9",
                                    "1.10",
                                    "1.11",
                                    "1.12",
                                    "1.13",
                                    "1.14",
                                    "1.15",
                                    "null"
                                ]
                            }
                        },
                        "2.适用部位": {
                            "type": "array",
                            "items": {
                                "type": "string",
                                "enum": [
                                    "2.1.1",
                                    "2.1.2",
                                    "2.1.3",
                                    "2.2.1",
                                    "2.2.2",
                                    "2.2.3",
                                    "2.2.4",
                                    "2.2.5",
                                    "2.2.6",
                                    "2.3.1",
                                    "2.4.1",
                                    "2.4.2",
                                    "2.5.1",
                                    "2.5.2",
                                    "2.5.3",
                                    "2.5.4",
                                    "2.5.5",
                                    "2.5.6",
                                    "2.6.1",
                                    "2.7.1",
                                    "2.7.2",
                                    "2.8.1",
                                    "2.8.2",
                                    "2.9.1",
                                    "2.9.2",
                                    "null"
                                ]
                            }
                        },
                        "3.服务方式": {
                            "type": "array",
                            "items": {
                                "type": "string",
                                "enum": [
                                    "3.1.1",
                                    "3.1.2",
                                    "3.1.3",
                                    "3.1.4",
                                    "3.2.1",
                                    "3.2.2",
                                    "3.2.3",
                                    "3.2.4",
                                    "3.2.5",
                                    "3.2.6",
                                    "3.2.7",
                                    "3.2.8",
                                    "3.2.9",
                                    "3.2.10",
                                    "3.2.11",
                                    "3.2.12",
                                    "3.2.13",
                                    "3.2.14",
                                    "3.2.15",
                                    "3.3.1",
                                    "3.3.2",
                                    "3.3.3",
                                    "3.3.4",
                                    "3.3.5",
                                    "3.4.1",
                                    "3.4.2",
                                    "3.4.3",
                                    "3.4.4",
                                    "3.4.5",
                                    "3.5.1",
                                    "3.5.2",
                                    "3.5.3",
                                    "3.5.4",
                                    "3.5.5",
                                    "3.6.1",
                                    "3.6.2",
                                    "3.6.3",
                                    "3.7.1",
                                    "3.7.2",
                                    "3.7.3",
                                    "3.7.4",
                                    "3.8.1",
                                    "3.8.2",
                                    "3.8.3",
                                    "3.8.4",
                                    "3.9.1",
                                    "3.9.2",
                                    "3.10.1",
                                    "3.10.2",
                                    "3.10.3",
                                    "3.10.4",
                                    "3.10.5",
                                    "3.10.6",
                                    "3.11.1",
                                    "3.11.2",
                                    "3.11.3",
                                    "3.11.4",
                                    "3.12.1",
                                    "3.12.2",
                                    "null"
                                ]
                            }
                        },
                        "4.服务时长": {
                            "type": "string",
                            "enum": [
                                "(0-30]",
                                "(30-40]",
                                "(40-60]",
                                "(60-80]",
                                "(80-90]",
                                "(90-100]",
                                "(100-120]",
                                "(120-∞]",
                                "null"
                            ]
                        },
                        "5.适用人群": {
                            "type": "string",
                            "enum": [
                                "5.1.1",
                                "5.2.1",
                                "5.2.2",
                                "5.3.1",
                                "5.3.2",
                                "5.4",
                                "null"
                            ]
                        },
                        "6.适用日期/时段": {
                            "type": "string"
                        },
                        "7.非服务类商品": {
                            "type": "string"
                        }
                    },
                    "required": [
                        "1.服务名称",
                        "2.适用部位",
                        "3.服务方式",
                        "4.服务时长",
                        "5.适用人群",
                        "6.适用日期/时段",
                        "7.非服务类商品"
                    ],
                    "additionalProperties": false
                },
                "匹配结果": {
                    "type": "string",
                    "enum": [
                        "是",
                        "否"
                    ]
                }
            },
            "required": [
                "项目单A",
                "项目单B",
                "匹配结果"
            ],
            "additionalProperties": false
        },
        "no_required_eval_acc_keys": [
            "6.适用日期/时段"
        ],
        "model_response": "```json\n{\n    \"项目单A\": {\n        \"1.服务名称\": [\n            \"1.10\",\n            \"1.13\"\n        ],\n        \"2.适用部位\": [\n            \"2.4.1\",\n            \"2.7.1\"\n        ],\n        \"3.服务方式\": [\n            \"3.7.1\",\n            \"3.10.1\"\n        ],\n        \"4.服务时长\": \"(60-80]\",\n        \"5.适用人群\": \"5.4\",\n        \"6.适用日期/时段\": \"全天可用\",\n        \"7.非服务类商品\": \"三伏养生贴\"\n    },\n    \"项目单B\": {\n        \"1.服务名称\": [\n            \"1.13\"\n        ],\n        \"2.适用部位\": [\n            \"2.4.1\",\n            \"2.4.2\"\n        ],\n        \"3.服务方式\": [\n            \"3.10.3\"\n        ],\n        \"4.服务时长\": \"(0-30]\",\n        \"5.适用人群\": \"5.4\",\n        \"6.适用日期/时段\": \"全天可用\",\n        \"7.非服务类商品\": \"null\"\n    },\n    \"匹配结果\": \"否\"\n}\n```"
    },
    {
        "input": "【Background】\n【角色定义】你是一名消费者,你需要充分了解两个商家提供的生活项目并进行比较, 根据关键要素抽取规则和项目匹配规则来判断两个项目是否相同或匹配，并且以结构化数据的形式把两个项目结果展示出来。\n【Requirements】\n\n\n项目单的信息包括：商品标题、项目单详情、有效期、营业时间、适用人数、购买限制等。关键要素包括：服务名称、适用部位、服务方式、服务时长、适用人群、适用日期/时段、非服务类商品。（注意：如果有枚举值需要归类到枚举值，如果该内容在枚举值之外则默认为null；严格按照优先级，获取信息后不再考虑剩余。\"\n    \"1.服务名称，同一项目单可能包含多个项目，需要全部列举（注意：出现好评礼、会员礼所附赠的项目不计入服务名称。例如：“好评一次深层洁净60分钟”，则服务名称为“null”。优先级：商品标题 > 服务功效 > 服务流程/步骤\n     枚举值：\n     1.1深层洁净(收缩毛孔)\n     1.2补水保湿(皮肤清洁、毛孔洗澡)\n     1.3祛痘\n     1.4美白嫩肤\n     1.5淡斑祛斑\n     1.6紧致提拉\n     1.7修复护理\n     1.8脱毛\n     1.9眼部护理\n     1.10肩颈按摩\n     1.11SPA\n     1.12头疗\n     1.13养生调理\n     1.14瘦身纤体\n     1.15美胸美臀\n\n    2.适用部位：和服务名称对应。优先级：商品标题 > 服务功效 > 服务流程/步骤\n     枚举值：\n     2.1深层洁净/补水保湿/祛痘/美白嫩肤/淡斑祛斑/紧致提拉/修复护理：2.1.1面部,2.1.2部分面部,2.1.3背部 \n     2.2脱毛：2.2.1口唇,2.2.2腋下,2.2.3面部,2.2.4手臂,2.2.5腿部,2.2.6私密/比基尼\n     2.3眼部护理：2.3.1眼部 \n     2.4肩颈按摩：2.4.1肩颈,2.4.2肩颈+背 \n     2.5SPA：2.5.1全身,2.5.2肩颈+腰背,2.5.3肩颈+背部+腿部,2.5.4肩颈+腰腹+腿,2.5.5头+肩+颈+背,2.5.6背部 \n     2.6头疗：2.6.1头部\n     2.7养生调理：2.7.1全身(未指明部位),2.7.2局部(非全身，或者指明某个部位) \n     2.8瘦身纤体：2.8.1全身,2.8.2局部塑形 \n     2.9美胸美臀：2.9.1胸部,2.9.2臀部\n    \n    3.服务方式：和服务名称对应。优先级：项目单详情>商品标题\n     枚举值：（注意：1.未提到以下内容的，输出null;2.如果出现2种或者2种以上结果需要都输出）\n     3.1深层洁净：3.1.1)仪器(超微小气泡/大气泡/臭氧泡泡/魔法活氧泡泡) 3.1.2)海菲秀 3.1.3)泥膜/面膜 3.1.4)白牌产品 \n    3.2补水保湿：3.2.1)B5精华 3.2.2)修丽可 3.2.3)日式pola 3.2.4)日式晓姿 3.2.5)赫莲娜HR 3.2.6)伊芙珑evelom 3.2.7)海蓝之谜LA MER 3.2.8)瑞妍cellcosment 3.2.9)莱珀妮 LA PRAIRIE 3.2.10)迪奥DIOR 3.2.11)圣罗兰YSL 3.2.12)诚美DGR 3.2.13)法尔曼VALMONT 3.2.14)菲洛嘉FILORGA 3.2.15)白牌产品\n     3.3祛痘：3.3.1)手工针清/皮铲/护理 3.3.2)点阵激光 3.3.3)红蓝光/PDT光能/烤光 3.3.4)刷酸/果酸 3.3.5)草本 \n     3.4美白嫩肤：3.4.1)焕肤类 3.4.2)氨甲环酸 3.4.3)大牌产品(菲洛嘉) 3.4.4)普牌产品(欧诗漫) 3.4.5)白牌产品 \n     3.5紧致提拉：3.5.1)手法按摩类 3.5.2)抗糖祛黄/生物酶疗 3.5.3)木乃伊紧致 3.5.4)大牌产品(赫莲娜/日式POLA) 3.5.5)白牌产品 \n     3.6修复护理：3.6.1)酵素/乳糖酸/骨胶原/活性酶 3.6.2)大牌产品(赫莲娜/伊芙珑/海蓝之谜/瑞妍/莱珀妮/迪奥/圣罗兰诚美DGR/法尔曼/菲洛嘉) 3.6.3)白牌产品\n     3.7肩颈按摩：3.7.1)使用精油 3.7.2)不使用精油 3.7.3)热石精油 3.7.4)水疗\n     3.8全身SPA：3.8.1)使用精油 3.8.2)不使用精油 3.8.3)热石精油 3.8.4)水疗\n     3.9头疗：3.9.1)使用精油 3.9.2)不使用精油 \n     3.10养生调理：3.10.1)灸类 3.10.2)刮痧 3.10.3)罐类 3.10.4)蒸/浴类 3.10.5)经络/净排类 3.10.6)产后修复类\n     3.11瘦身纤体：3.11.1)针灸/拔罐/经络 3.11.2)刮痧 3.11.3)仪器 3.11.4)调理粉/精油\n     3.12.美胸美臀：3.12.1)使用精油 3.12.2)不使用精油\n\n    4.服务时长，总服务时长(服务项目的服务时长总和)。优先级：商品标题>项目单详情\n    需要映射到枚举值：(0-30]、(30-40]、(40-60]、(60-80]、(80-90]、(90-100]、(100-120]、(120-∞]（输出答案时需要输出具体的枚举值内容）\n\n    5.适用人群，包括性别、年龄、用户类型（出现“XX节”属于营销词，不能作为性别的判断，eg.女神节专属、母亲节，不能判断性别为女性） 优先级：购买限制>商品标题>项目单详情\n     枚举值：（注意：此项优先级：用户类型>性别>年龄，只需输出一个类别）\n     5.1用户类型：5.1.1新客价格（第一次使用该项目的用户）\n     5.2性别：5.2.1男性，5.2.2女性\n     5.3年龄：5.3.1儿童（0-12周岁）,5.3.2成人（18岁以上）\n     5.4不限通用(每人限购1份，不限年龄，性别)\n\n    6.适用日期/时段（注意：全天可用等于商家营业时间可用；闲时指的是周一到周五的下午4点前）  优先级：项目单详情>商品标题>购买须知\n    注意1：项目单详情中信息多处不符一致时，则取最小时段进行对比，eg1.A单适用日期：2025年7月1日-2025年9月1日，周一-周五10:00-19:00可用；B单适用日期2025.7.1-2025.10.1周一到周日10:00-22:00，则AB两单适用日期/时段不一致。eg2.2025年8月1日-2025年8月30日，周一-周五10:00-19:00可用；B单适用日期2025.7.1-2025.10.1周一-周天10:00-19:00可用，则AB两单适用日期/时段一致（不考虑年月日时格式）\n    注意2：适用日期/时段：从营业时间得到信息，仅看“周一-周日”、“xx月xx日-xx月xx日”、“xx:xx-xx:xx”、“xx点-xx点”等类似字眼，无需关注特殊节假日；时段：由“开始时间”和“结束时间”组成，输出具体的时间，例如“10:00-22:00” \n\n    7.非服务类商品：指的是除服务名称以外的内容，eg.“深层洁净60分钟+（含/送/赠）XX面膜2盒”，”非服务商品为“XX面膜，2盒”。如果是仅面膜、产品，零食、皮肤检测等非美容美体产品不算非服务产品，此时输出null。\n\n    8.白牌产品：指的是小厂商生产的没有牌子的商品，白牌是相对品牌而言的。\n\n\n    项目单匹配规则：根据抽取出来的要素和以下规则判断是否为同一项目单“注意：如果无法识别出来则默认为null”\n     1.服务名称：需完全一致，否则认为两个项目单不一致(不考虑顺序)。\n     2.适用部位：需完全一致，否则认为两个项目单不一致(不考虑顺序)。\n     3.服务方式：任意一方有值另一方空值，不可以视为一致。需要两侧都有值进行判断是否一致。\n     4.服务时长：如果任意一方有值另一方空值，可以视为一致。但当双方都有值时，双方时长一致才算一致。\n     5.适用人群：性别、年龄、用户类型要完全一样才算一致，如果任意一方空值则默认为“不限通用”，随后再对比出结果。\n     6.适用日期/时段：\n      1)当只有适用日期（年月日）时，日期精确到年月日相同则认为一致，eg.A单适用日期：2025年7月1日-2025年10月1日；B单适用日期2025.7.1-2025.10.1，则AB两单适用日期一致。（不考虑年月日格式）\n      2)当任意一方“适用日期”为空值，则取适用时段或者运营时间进行比较，AB两单之间起始及终止时间相差为1小时以内，可视为一致，超过1小时则为不一致。\n     7.非服务类商品：\n      1)纯非服务类商品，无需参与匹配。\n      2)若出现服务名称+非服务产品，针对服务内容按照规则匹配；非服务类商品需精准匹配，内容具体到名称+规格或者单位或者品牌。eg.“深层洁净60分钟+（含/送/赠）XX面膜2盒”，”非服务商品为“2盒XX面膜”\n    判断步骤：\n     1. 根据输入的项目单信息和规则抽取相应的要素，以及输出对应的枚举值内容\n     2. 根据抽取要素、枚举值内容和匹配规则来判断两个项目单是否匹配\n     \n     \n\n【Input】 \n3.项目单A：M22光子嫩肤全模式|滤片任选|私信置换黄金超光子|新客赠面膜；保障：严审资质，随时退，过期退。赠礼：到店礼or下单礼“半岛第五代黄金微针私信领取”套餐详情：光子嫩肤1份，技术：OPT，仪器型号：科医人王者之冠，模式：全模式（根据皮肤状态采取对应模式进行治疗，除DPL仪器及LPL部分仪器仅使用一个探头外，一般使用滤片/探头数不少于2个）服务流程：7步1.卸妆洁面：自助洁面5分钟；2.医生面诊：个性化皮肤综合方案5分钟；3.涂冷凝胶3分钟；4.护目2分钟；5.项目操作：黄金超光子【送品牌面膜1张】15分钟；6.术后清洁3分钟；7.术后指导2分钟。免费福利：免费停车、无线wifi、茶水饮料、糕点糖果、专业回访。购买须知：购买之日起360天内有效，需要提前30分钟预定。可用时间周一到周日09:00:00-21:00:00.预约流程：在线咨询-预约-到院面诊-安排治疗。购买人群：未成年人请勿购买，如有治疗需求请按医嘱选购。退款须知：支持整单随时退，过期自动退。项目单B：润致熨纹1.5ml【玻尿酸除皱】静态纹注射填充|面部舒适淡纹，保障：正品验真，可视化配药，严审资质，随时退，过期退。赠礼：到店礼，下单礼品牌：润致，型号：润致熨纹，剂量：1.5ml，数量：1支，适用部位：面部细纹。服务流程：1.卸妆洁面5分钟；2.医生面诊10分钟；3.项目操作20分钟；4.术后观察15分钟；术后指导5分钟。免费福利：免费停车、无线wifi、茶水饮料、糕点糖果、专业回访。购买须知：购买之日起360天内有效，需要提前30分钟预定。可用时间周一到周日09:00:00-21:00:00.预约流程：在线咨询-预约-到院面诊-安排治疗。购买人群：未成年人请勿购买，如有治疗需求请按医嘱选购。退款须知：支持整单随时退，过期自动退。\n\n\n\n【Output Requirement】\n 你的输出必须满足以下JSON_SCHEMA{'$schema': 'http://json-schema.org/draft-07/schema#', 'type': 'object', 'properties': {'项目单A': {'type': 'object', 'properties': {'1.服务名称': {'type': 'array', 'items': {'type': 'string', 'enum': ['1.1', '1.2', '1.3', '1.4', '1.5', '1.6', '1.7', '1.8', '1.9', '1.10', '1.11', '1.12', '1.13', '1.14', '1.15', 'null']}}, '2.适用部位': {'type': 'array', 'items': {'type': 'string', 'enum': ['2.1.1', '2.1.2', '2.1.3', '2.2.1', '2.2.2', '2.2.3', '2.2.4', '2.2.5', '2.2.6', '2.3.1', '2.4.1', '2.4.2', '2.5.1', '2.5.2', '2.5.3', '2.5.4', '2.5.5', '2.5.6', '2.6.1', '2.7.1', '2.7.2', '2.8.1', '2.8.2', '2.9.1', '2.9.2', 'null']}}, '3.服务方式': {'type': 'array', 'items': {'type': 'string', 'enum': ['3.1.1', '3.1.2', '3.1.3', '3.1.4', '3.2.1', '3.2.2', '3.2.3', '3.2.4', '3.2.5', '3.2.6', '3.2.7', '3.2.8', '3.2.9', '3.2.10', '3.2.11', '3.2.12', '3.2.13', '3.2.14', '3.2.15', '3.3.1', '3.3.2', '3.3.3', '3.3.4', '3.3.5', '3.4.1', '3.4.2', '3.4.3', '3.4.4', '3.4.5', '3.5.1', '3.5.2', '3.5.3', '3.5.4', '3.5.5', '3.6.1', '3.6.2', '3.6.3', '3.7.1', '3.7.2', '3.7.3', '3.7.4', '3.8.1', '3.8.2', '3.8.3', '3.8.4', '3.9.1', '3.9.2', '3.10.1', '3.10.2', '3.10.3', '3.10.4', '3.10.5', '3.10.6', '3.11.1', '3.11.2', '3.11.3', '3.11.4', '3.12.1', '3.12.2', 'null']}}, '4.服务时长': {'type': 'string', 'enum': ['(0-30]', '(30-40]', '(40-60]', '(60-80]', '(80-90]', '(90-100]', '(100-120]', '(120-∞]', 'null']}, '5.适用人群': {'type': 'string', 'enum': ['5.1.1', '5.2.1', '5.2.2', '5.3.1', '5.3.2', '5.4', 'null']}, '6.适用日期/时段': {'type': 'string'}, '7.非服务类商品': {'type': 'string'}}, 'required': ['1.服务名称', '2.适用部位', '3.服务方式', '4.服务时长', '5.适用人群', '6.适用日期/时段', '7.非服务类商品'], 'additionalProperties': False}, '项目单B': {'type': 'object', 'properties': {'1.服务名称': {'type': 'array', 'items': {'type': 'string', 'enum': ['1.1', '1.2', '1.3', '1.4', '1.5', '1.6', '1.7', '1.8', '1.9', '1.10', '1.11', '1.12', '1.13', '1.14', '1.15', 'null']}}, '2.适用部位': {'type': 'array', 'items': {'type': 'string', 'enum': ['2.1.1', '2.1.2', '2.1.3', '2.2.1', '2.2.2', '2.2.3', '2.2.4', '2.2.5', '2.2.6', '2.3.1', '2.4.1', '2.4.2', '2.5.1', '2.5.2', '2.5.3', '2.5.4', '2.5.5', '2.5.6', '2.6.1', '2.7.1', '2.7.2', '2.8.1', '2.8.2', '2.9.1', '2.9.2', 'null']}}, '3.服务方式': {'type': 'array', 'items': {'type': 'string', 'enum': ['3.1.1', '3.1.2', '3.1.3', '3.1.4', '3.2.1', '3.2.2', '3.2.3', '3.2.4', '3.2.5', '3.2.6', '3.2.7', '3.2.8', '3.2.9', '3.2.10', '3.2.11', '3.2.12', '3.2.13', '3.2.14', '3.2.15', '3.3.1', '3.3.2', '3.3.3', '3.3.4', '3.3.5', '3.4.1', '3.4.2', '3.4.3', '3.4.4', '3.4.5', '3.5.1', '3.5.2', '3.5.3', '3.5.4', '3.5.5', '3.6.1', '3.6.2', '3.6.3', '3.7.1', '3.7.2', '3.7.3', '3.7.4', '3.8.1', '3.8.2', '3.8.3', '3.8.4', '3.9.1', '3.9.2', '3.10.1', '3.10.2', '3.10.3', '3.10.4', '3.10.5', '3.10.6', '3.11.1', '3.11.2', '3.11.3', '3.11.4', '3.12.1', '3.12.2', 'null']}}, '4.服务时长': {'type': 'string', 'enum': ['(0-30]', '(30-40]', '(40-60]', '(60-80]', '(80-90]', '(90-100]', '(100-120]', '(120-∞]', 'null']}, '5.适用人群': {'type': 'string', 'enum': ['5.1.1', '5.2.1', '5.2.2', '5.3.1', '5.3.2', '5.4', 'null']}, '6.适用日期/时段': {'type': 'string'}, '7.非服务类商品': {'type': 'string'}}, 'required': ['1.服务名称', '2.适用部位', '3.服务方式', '4.服务时长', '5.适用人群', '6.适用日期/时段', '7.非服务类商品'], 'additionalProperties': False}, '匹配结果': {'type': 'string', 'enum': ['是', '否']}}, 'required': ['项目单A', '项目单B', '匹配结果'], 'additionalProperties': False}",
        "target": {
            "项目单A": {
                "1.服务名称": [
                    "1.4"
                ],
                "2.适用部位": [
                    "2.1.1"
                ],
                "3.服务方式": [
                    "3.4.5"
                ],
                "4.服务时长": "(30-40]",
                "5.适用人群": "5.3.2",
                "6.适用日期/时段": "周一到周日09:00:00-21:00:00",
                "7.非服务类商品": "品牌面膜1张"
            },
            "项目单B": {
                "1.服务名称": [
                    "1.6"
                ],
                "2.适用部位": [
                    "2.1.1"
                ],
                "3.服务方式": [
                    "3.5.4"
                ],
                "4.服务时长": "(40-60]",
                "5.适用人群": "5.3.2",
                "6.适用日期/时段": "周一到周日09:00:00-21:00:00",
                "7.非服务类商品": "null"
            },
            "匹配结果": "否"
        },
        "json_schema": {
            "$schema": "http://json-schema.org/draft-07/schema#",
            "type": "object",
            "properties": {
                "项目单A": {
                    "type": "object",
                    "properties": {
                        "1.服务名称": {
                            "type": "array",
                            "items": {
                                "type": "string",
                                "enum": [
                                    "1.1",
                                    "1.2",
                                    "1.3",
                                    "1.4",
                                    "1.5",
                                    "1.6",
                                    "1.7",
                                    "1.8",
                                    "1.9",
                                    "1.10",
                                    "1.11",
                                    "1.12",
                                    "1.13",
                                    "1.14",
                                    "1.15",
                                    "null"
                                ]
                            }
                        },
                        "2.适用部位": {
                            "type": "array",
                            "items": {
                                "type": "string",
                                "enum": [
                                    "2.1.1",
                                    "2.1.2",
                                    "2.1.3",
                                    "2.2.1",
                                    "2.2.2",
                                    "2.2.3",
                                    "2.2.4",
                                    "2.2.5",
                                    "2.2.6",
                                    "2.3.1",
                                    "2.4.1",
                                    "2.4.2",
                                    "2.5.1",
                                    "2.5.2",
                                    "2.5.3",
                                    "2.5.4",
                                    "2.5.5",
                                    "2.5.6",
                                    "2.6.1",
                                    "2.7.1",
                                    "2.7.2",
                                    "2.8.1",
                                    "2.8.2",
                                    "2.9.1",
                                    "2.9.2",
                                    "null"
                                ]
                            }
                        },
                        "3.服务方式": {
                            "type": "array",
                            "items": {
                                "type": "string",
                                "enum": [
                                    "3.1.1",
                                    "3.1.2",
                                    "3.1.3",
                                    "3.1.4",
                                    "3.2.1",
                                    "3.2.2",
                                    "3.2.3",
                                    "3.2.4",
                                    "3.2.5",
                                    "3.2.6",
                                    "3.2.7",
                                    "3.2.8",
                                    "3.2.9",
                                    "3.2.10",
                                    "3.2.11",
                                    "3.2.12",
                                    "3.2.13",
                                    "3.2.14",
                                    "3.2.15",
                                    "3.3.1",
                                    "3.3.2",
                                    "3.3.3",
                                    "3.3.4",
                                    "3.3.5",
                                    "3.4.1",
                                    "3.4.2",
                                    "3.4.3",
                                    "3.4.4",
                                    "3.4.5",
                                    "3.5.1",
                                    "3.5.2",
                                    "3.5.3",
                                    "3.5.4",
                                    "3.5.5",
                                    "3.6.1",
                                    "3.6.2",
                                    "3.6.3",
                                    "3.7.1",
                                    "3.7.2",
                                    "3.7.3",
                                    "3.7.4",
                                    "3.8.1",
                                    "3.8.2",
                                    "3.8.3",
                                    "3.8.4",
                                    "3.9.1",
                                    "3.9.2",
                                    "3.10.1",
                                    "3.10.2",
                                    "3.10.3",
                                    "3.10.4",
                                    "3.10.5",
                                    "3.10.6",
                                    "3.11.1",
                                    "3.11.2",
                                    "3.11.3",
                                    "3.11.4",
                                    "3.12.1",
                                    "3.12.2",
                                    "null"
                                ]
                            }
                        },
                        "4.服务时长": {
                            "type": "string",
                            "enum": [
                                "(0-30]",
                                "(30-40]",
                                "(40-60]",
                                "(60-80]",
                                "(80-90]",
                                "(90-100]",
                                "(100-120]",
                                "(120-∞]",
                                "null"
                            ]
                        },
                        "5.适用人群": {
                            "type": "string",
                            "enum": [
                                "5.1.1",
                                "5.2.1",
                                "5.2.2",
                                "5.3.1",
                                "5.3.2",
                                "5.4",
                                "null"
                            ]
                        },
                        "6.适用日期/时段": {
                            "type": "string"
                        },
                        "7.非服务类商品": {
                            "type": "string"
                        }
                    },
                    "required": [
                        "1.服务名称",
                        "2.适用部位",
                        "3.服务方式",
                        "4.服务时长",
                        "5.适用人群",
                        "6.适用日期/时段",
                        "7.非服务类商品"
                    ],
                    "additionalProperties": false
                },
                "项目单B": {
                    "type": "object",
                    "properties": {
                        "1.服务名称": {
                            "type": "array",
                            "items": {
                                "type": "string",
                                "enum": [
                                    "1.1",
                                    "1.2",
                                    "1.3",
                                    "1.4",
                                    "1.5",
                                    "1.6",
                                    "1.7",
                                    "1.8",
                                    "1.9",
                                    "1.10",
                                    "1.11",
                                    "1.12",
                                    "1.13",
                                    "1.14",
                                    "1.15",
                                    "null"
                                ]
                            }
                        },
                        "2.适用部位": {
                            "type": "array",
                            "items": {
                                "type": "string",
                                "enum": [
                                    "2.1.1",
                                    "2.1.2",
                                    "2.1.3",
                                    "2.2.1",
                                    "2.2.2",
                                    "2.2.3",
                                    "2.2.4",
                                    "2.2.5",
                                    "2.2.6",
                                    "2.3.1",
                                    "2.4.1",
                                    "2.4.2",
                                    "2.5.1",
                                    "2.5.2",
                                    "2.5.3",
                                    "2.5.4",
                                    "2.5.5",
                                    "2.5.6",
                                    "2.6.1",
                                    "2.7.1",
                                    "2.7.2",
                                    "2.8.1",
                                    "2.8.2",
                                    "2.9.1",
                                    "2.9.2",
                                    "null"
                                ]
                            }
                        },
                        "3.服务方式": {
                            "type": "array",
                            "items": {
                                "type": "string",
                                "enum": [
                                    "3.1.1",
                                    "3.1.2",
                                    "3.1.3",
                                    "3.1.4",
                                    "3.2.1",
                                    "3.2.2",
                                    "3.2.3",
                                    "3.2.4",
                                    "3.2.5",
                                    "3.2.6",
                                    "3.2.7",
                                    "3.2.8",
                                    "3.2.9",
                                    "3.2.10",
                                    "3.2.11",
                                    "3.2.12",
                                    "3.2.13",
                                    "3.2.14",
                                    "3.2.15",
                                    "3.3.1",
                                    "3.3.2",
                                    "3.3.3",
                                    "3.3.4",
                                    "3.3.5",
                                    "3.4.1",
                                    "3.4.2",
                                    "3.4.3",
                                    "3.4.4",
                                    "3.4.5",
                                    "3.5.1",
                                    "3.5.2",
                                    "3.5.3",
                                    "3.5.4",
                                    "3.5.5",
                                    "3.6.1",
                                    "3.6.2",
                                    "3.6.3",
                                    "3.7.1",
                                    "3.7.2",
                                    "3.7.3",
                                    "3.7.4",
                                    "3.8.1",
                                    "3.8.2",
                                    "3.8.3",
                                    "3.8.4",
                                    "3.9.1",
                                    "3.9.2",
                                    "3.10.1",
                                    "3.10.2",
                                    "3.10.3",
                                    "3.10.4",
                                    "3.10.5",
                                    "3.10.6",
                                    "3.11.1",
                                    "3.11.2",
                                    "3.11.3",
                                    "3.11.4",
                                    "3.12.1",
                                    "3.12.2",
                                    "null"
                                ]
                            }
                        },
                        "4.服务时长": {
                            "type": "string",
                            "enum": [
                                "(0-30]",
                                "(30-40]",
                                "(40-60]",
                                "(60-80]",
                                "(80-90]",
                                "(90-100]",
                                "(100-120]",
                                "(120-∞]",
                                "null"
                            ]
                        },
                        "5.适用人群": {
                            "type": "string",
                            "enum": [
                                "5.1.1",
                                "5.2.1",
                                "5.2.2",
                                "5.3.1",
                                "5.3.2",
                                "5.4",
                                "null"
                            ]
                        },
                        "6.适用日期/时段": {
                            "type": "string"
                        },
                        "7.非服务类商品": {
                            "type": "string"
                        }
                    },
                    "required": [
                        "1.服务名称",
                        "2.适用部位",
                        "3.服务方式",
                        "4.服务时长",
                        "5.适用人群",
                        "6.适用日期/时段",
                        "7.非服务类商品"
                    ],
                    "additionalProperties": false
                },
                "匹配结果": {
                    "type": "string",
                    "enum": [
                        "是",
                        "否"
                    ]
                }
            },
            "required": [
                "项目单A",
                "项目单B",
                "匹配结果"
            ],
            "additionalProperties": false
        },
        "no_required_eval_acc_keys": [
            "6.适用日期/时段"
        ],
        "model_response": "```json\n{\n    \"项目单A\": {\n        \"1.服务名称\": [\n            \"1.4\"\n        ],\n        \"2.适用部位\": [\n            \"2.1.1\"\n        ],\n        \"3.服务方式\": [\n            \"null\"\n        ],\n        \"4.服务时长\": \"(30-40]\",\n        \"5.适用人群\": \"5.4\",\n        \"6.适用日期/时段\": \"09:00:00-21:00:00\",\n        \"7.非服务类商品\": \"品牌面膜, 1张\"\n    },\n    \"项目单B\": {\n        \"1.服务名称\": [\n            \"null\"\n        ],\n        \"2.适用部位\": [\n            \"2.1.1\"\n        ],\n        \"3.服务方式\": [\n            \"null\"\n        ],\n        \"4.服务时长\": \"(40-60]\",\n        \"5.适用人群\": \"5.4\",\n        \"6.适用日期/时段\": \"09:00:00-21:00:00\",\n        \"7.非服务类商品\": \"null\"\n    },\n    \"匹配结果\": \"否\"\n}\n```"
    },
    {
        "input": "【Background】\n【角色定义】你是一名消费者,你需要充分了解两个商家提供的生活项目并进行比较, 根据关键要素抽取规则和项目匹配规则来判断两个项目是否相同或匹配，并且以结构化数据的形式把两个项目结果展示出来。\n【Requirements】\n\n\n项目单的信息包括：商品标题、项目单详情、有效期、营业时间、适用人数、购买限制等。关键要素包括：服务名称、适用部位、服务方式、服务时长、适用人群、适用日期/时段、非服务类商品。（注意：如果有枚举值需要归类到枚举值，如果该内容在枚举值之外则默认为null；严格按照优先级，获取信息后不再考虑剩余。\"\n    \"1.服务名称，同一项目单可能包含多个项目，需要全部列举（注意：出现好评礼、会员礼所附赠的项目不计入服务名称。例如：“好评一次深层洁净60分钟”，则服务名称为“null”。优先级：商品标题 > 服务功效 > 服务流程/步骤\n     枚举值：\n     1.1深层洁净(收缩毛孔)\n     1.2补水保湿(皮肤清洁、毛孔洗澡)\n     1.3祛痘\n     1.4美白嫩肤\n     1.5淡斑祛斑\n     1.6紧致提拉\n     1.7修复护理\n     1.8脱毛\n     1.9眼部护理\n     1.10肩颈按摩\n     1.11SPA\n     1.12头疗\n     1.13养生调理\n     1.14瘦身纤体\n     1.15美胸美臀\n\n    2.适用部位：和服务名称对应。优先级：商品标题 > 服务功效 > 服务流程/步骤\n     枚举值：\n     2.1深层洁净/补水保湿/祛痘/美白嫩肤/淡斑祛斑/紧致提拉/修复护理：2.1.1面部,2.1.2部分面部,2.1.3背部 \n     2.2脱毛：2.2.1口唇,2.2.2腋下,2.2.3面部,2.2.4手臂,2.2.5腿部,2.2.6私密/比基尼\n     2.3眼部护理：2.3.1眼部 \n     2.4肩颈按摩：2.4.1肩颈,2.4.2肩颈+背 \n     2.5SPA：2.5.1全身,2.5.2肩颈+腰背,2.5.3肩颈+背部+腿部,2.5.4肩颈+腰腹+腿,2.5.5头+肩+颈+背,2.5.6背部 \n     2.6头疗：2.6.1头部\n     2.7养生调理：2.7.1全身(未指明部位),2.7.2局部(非全身，或者指明某个部位) \n     2.8瘦身纤体：2.8.1全身,2.8.2局部塑形 \n     2.9美胸美臀：2.9.1胸部,2.9.2臀部\n    \n    3.服务方式：和服务名称对应。优先级：项目单详情>商品标题\n     枚举值：（注意：1.未提到以下内容的，输出null;2.如果出现2种或者2种以上结果需要都输出）\n     3.1深层洁净：3.1.1)仪器(超微小气泡/大气泡/臭氧泡泡/魔法活氧泡泡) 3.1.2)海菲秀 3.1.3)泥膜/面膜 3.1.4)白牌产品 \n    3.2补水保湿：3.2.1)B5精华 3.2.2)修丽可 3.2.3)日式pola 3.2.4)日式晓姿 3.2.5)赫莲娜HR 3.2.6)伊芙珑evelom 3.2.7)海蓝之谜LA MER 3.2.8)瑞妍cellcosment 3.2.9)莱珀妮 LA PRAIRIE 3.2.10)迪奥DIOR 3.2.11)圣罗兰YSL 3.2.12)诚美DGR 3.2.13)法尔曼VALMONT 3.2.14)菲洛嘉FILORGA 3.2.15)白牌产品\n     3.3祛痘：3.3.1)手工针清/皮铲/护理 3.3.2)点阵激光 3.3.3)红蓝光/PDT光能/烤光 3.3.4)刷酸/果酸 3.3.5)草本 \n     3.4美白嫩肤：3.4.1)焕肤类 3.4.2)氨甲环酸 3.4.3)大牌产品(菲洛嘉) 3.4.4)普牌产品(欧诗漫) 3.4.5)白牌产品 \n     3.5紧致提拉：3.5.1)手法按摩类 3.5.2)抗糖祛黄/生物酶疗 3.5.3)木乃伊紧致 3.5.4)大牌产品(赫莲娜/日式POLA) 3.5.5)白牌产品 \n     3.6修复护理：3.6.1)酵素/乳糖酸/骨胶原/活性酶 3.6.2)大牌产品(赫莲娜/伊芙珑/海蓝之谜/瑞妍/莱珀妮/迪奥/圣罗兰诚美DGR/法尔曼/菲洛嘉) 3.6.3)白牌产品\n     3.7肩颈按摩：3.7.1)使用精油 3.7.2)不使用精油 3.7.3)热石精油 3.7.4)水疗\n     3.8全身SPA：3.8.1)使用精油 3.8.2)不使用精油 3.8.3)热石精油 3.8.4)水疗\n     3.9头疗：3.9.1)使用精油 3.9.2)不使用精油 \n     3.10养生调理：3.10.1)灸类 3.10.2)刮痧 3.10.3)罐类 3.10.4)蒸/浴类 3.10.5)经络/净排类 3.10.6)产后修复类\n     3.11瘦身纤体：3.11.1)针灸/拔罐/经络 3.11.2)刮痧 3.11.3)仪器 3.11.4)调理粉/精油\n     3.12.美胸美臀：3.12.1)使用精油 3.12.2)不使用精油\n\n    4.服务时长，总服务时长(服务项目的服务时长总和)。优先级：商品标题>项目单详情\n    需要映射到枚举值：(0-30]、(30-40]、(40-60]、(60-80]、(80-90]、(90-100]、(100-120]、(120-∞]（输出答案时需要输出具体的枚举值内容）\n\n    5.适用人群，包括性别、年龄、用户类型（出现“XX节”属于营销词，不能作为性别的判断，eg.女神节专属、母亲节，不能判断性别为女性） 优先级：购买限制>商品标题>项目单详情\n     枚举值：（注意：此项优先级：用户类型>性别>年龄，只需输出一个类别）\n     5.1用户类型：5.1.1新客价格（第一次使用该项目的用户）\n     5.2性别：5.2.1男性，5.2.2女性\n     5.3年龄：5.3.1儿童（0-12周岁）,5.3.2成人（18岁以上）\n     5.4不限通用(每人限购1份，不限年龄，性别)\n\n    6.适用日期/时段（注意：全天可用等于商家营业时间可用；闲时指的是周一到周五的下午4点前）  优先级：项目单详情>商品标题>购买须知\n    注意1：项目单详情中信息多处不符一致时，则取最小时段进行对比，eg1.A单适用日期：2025年7月1日-2025年9月1日，周一-周五10:00-19:00可用；B单适用日期2025.7.1-2025.10.1周一到周日10:00-22:00，则AB两单适用日期/时段不一致。eg2.2025年8月1日-2025年8月30日，周一-周五10:00-19:00可用；B单适用日期2025.7.1-2025.10.1周一-周天10:00-19:00可用，则AB两单适用日期/时段一致（不考虑年月日时格式）\n    注意2：适用日期/时段：从营业时间得到信息，仅看“周一-周日”、“xx月xx日-xx月xx日”、“xx:xx-xx:xx”、“xx点-xx点”等类似字眼，无需关注特殊节假日；时段：由“开始时间”和“结束时间”组成，输出具体的时间，例如“10:00-22:00” \n\n    7.非服务类商品：指的是除服务名称以外的内容，eg.“深层洁净60分钟+（含/送/赠）XX面膜2盒”，”非服务商品为“XX面膜，2盒”。如果是仅面膜、产品，零食、皮肤检测等非美容美体产品不算非服务产品，此时输出null。\n\n    8.白牌产品：指的是小厂商生产的没有牌子的商品，白牌是相对品牌而言的。\n\n\n    项目单匹配规则：根据抽取出来的要素和以下规则判断是否为同一项目单“注意：如果无法识别出来则默认为null”\n     1.服务名称：需完全一致，否则认为两个项目单不一致(不考虑顺序)。\n     2.适用部位：需完全一致，否则认为两个项目单不一致(不考虑顺序)。\n     3.服务方式：任意一方有值另一方空值，不可以视为一致。需要两侧都有值进行判断是否一致。\n     4.服务时长：如果任意一方有值另一方空值，可以视为一致。但当双方都有值时，双方时长一致才算一致。\n     5.适用人群：性别、年龄、用户类型要完全一样才算一致，如果任意一方空值则默认为“不限通用”，随后再对比出结果。\n     6.适用日期/时段：\n      1)当只有适用日期（年月日）时，日期精确到年月日相同则认为一致，eg.A单适用日期：2025年7月1日-2025年10月1日；B单适用日期2025.7.1-2025.10.1，则AB两单适用日期一致。（不考虑年月日格式）\n      2)当任意一方“适用日期”为空值，则取适用时段或者运营时间进行比较，AB两单之间起始及终止时间相差为1小时以内，可视为一致，超过1小时则为不一致。\n     7.非服务类商品：\n      1)纯非服务类商品，无需参与匹配。\n      2)若出现服务名称+非服务产品，针对服务内容按照规则匹配；非服务类商品需精准匹配，内容具体到名称+规格或者单位或者品牌。eg.“深层洁净60分钟+（含/送/赠）XX面膜2盒”，”非服务商品为“2盒XX面膜”\n    判断步骤：\n     1. 根据输入的项目单信息和规则抽取相应的要素，以及输出对应的枚举值内容\n     2. 根据抽取要素、枚举值内容和匹配规则来判断两个项目单是否匹配\n     \n     \n\n【Input】 \n4.项目单A：【帝王贵套】沐阳SPA +入境臋疗+温养矾石-享赋能。优惠详情：需预约，周一至周天全天可用，购买后90天内有效，随时退过期退。服务部位：腰背、足部。优惠详情：精油SPA70分钟。服务流程：1.尊雅欢迎礼・咨询接待；2.尊雅入境礼・预备更衣；3.独立卫浴・舒心隐秘；4.红袖 JS・品质服务；5.净足・草本养生沐足；6.舒缓・肩颈放松放松；7.解压・腰背经络疏通；8.保养・太极醫疗展油 spa；9. 疏通・褪后侧手法油压；10.温阳・腰背矾石走经络；11.漫游沉浸・主题氛围；12.商务私 Ding・艺术养生；13.应季汤品・畅享私厨；14.知名品牌洗护用品；15.棉柔床品・星级布草；16.免费简餐 | 免费茶水 | 免费饮品；17.高端定制客用物品，一用一消一换。服务设施：小吃简餐（水饺、汤圆、抄手、小面）茶点水果；玩乐设施（独立淋浴房）。适用时间：购买后90天内有效，提前2H预约，每张优惠券最多1人使用，男士专属，未成年人不可用。项目单B：【温享3次卡】丹沁SPA|尊雅奶浴+渘沁养护+港式油展深焕。须知：提前2H预约，购买后90天内有效。周一至周日全天可用；可单次核销多份，每张优惠券最多可1人使用，限男士，不能与其他优惠同享。退款规则：1.支持随时退，过期退；2.若次数未使用，可随时退全款。3.若发生核销后再申请退款，剩余所有未核销次数将一起退款，本商品为阶梯定价品，退款金额须按照如下规则进行计算：累积使用1次，单次价格489元，预计可退金额：904元；累积使用2次，单次价格452元，预计可退金额：452元；累积使用3次，单次价格452元，预计可退金额：0元。优惠详情精油SPA110分钟，适用于全身（肩颈、腰背、手臂、手部、腿部。）服务流程：1.尊雅欢迎礼·咨询接待；2.独立泡浴·逸境舒适；3.逸境放松·肆压养护；4.錵漾舒压·放松5.舒释·腰背放松；6.腿部放松·愈疗享受；7.养护舒压·调理舒缓；8.面部清洁·舒缓肌肤；9.头部舒压·安神助眠；10.应季汤品·畅享私厨；11.商务个性化·古法调理；12.知名品牌洗护用品；13.棉柔床品·星级布草；14.免费简餐|免费茶水|免费饮品；15.高端定制客用物品，一用一消一换。服务设施：小吃简餐（水饺、汤圆、馄饨、抄手、小面、应季养生汤品，小吃拼盘）茶点水果；玩乐设施（独立淋浴房）\n\n\n\n【Output Requirement】\n 你的输出必须满足以下JSON_SCHEMA{'$schema': 'http://json-schema.org/draft-07/schema#', 'type': 'object', 'properties': {'项目单A': {'type': 'object', 'properties': {'1.服务名称': {'type': 'array', 'items': {'type': 'string', 'enum': ['1.1', '1.2', '1.3', '1.4', '1.5', '1.6', '1.7', '1.8', '1.9', '1.10', '1.11', '1.12', '1.13', '1.14', '1.15', 'null']}}, '2.适用部位': {'type': 'array', 'items': {'type': 'string', 'enum': ['2.1.1', '2.1.2', '2.1.3', '2.2.1', '2.2.2', '2.2.3', '2.2.4', '2.2.5', '2.2.6', '2.3.1', '2.4.1', '2.4.2', '2.5.1', '2.5.2', '2.5.3', '2.5.4', '2.5.5', '2.5.6', '2.6.1', '2.7.1', '2.7.2', '2.8.1', '2.8.2', '2.9.1', '2.9.2', 'null']}}, '3.服务方式': {'type': 'array', 'items': {'type': 'string', 'enum': ['3.1.1', '3.1.2', '3.1.3', '3.1.4', '3.2.1', '3.2.2', '3.2.3', '3.2.4', '3.2.5', '3.2.6', '3.2.7', '3.2.8', '3.2.9', '3.2.10', '3.2.11', '3.2.12', '3.2.13', '3.2.14', '3.2.15', '3.3.1', '3.3.2', '3.3.3', '3.3.4', '3.3.5', '3.4.1', '3.4.2', '3.4.3', '3.4.4', '3.4.5', '3.5.1', '3.5.2', '3.5.3', '3.5.4', '3.5.5', '3.6.1', '3.6.2', '3.6.3', '3.7.1', '3.7.2', '3.7.3', '3.7.4', '3.8.1', '3.8.2', '3.8.3', '3.8.4', '3.9.1', '3.9.2', '3.10.1', '3.10.2', '3.10.3', '3.10.4', '3.10.5', '3.10.6', '3.11.1', '3.11.2', '3.11.3', '3.11.4', '3.12.1', '3.12.2', 'null']}}, '4.服务时长': {'type': 'string', 'enum': ['(0-30]', '(30-40]', '(40-60]', '(60-80]', '(80-90]', '(90-100]', '(100-120]', '(120-∞]', 'null']}, '5.适用人群': {'type': 'string', 'enum': ['5.1.1', '5.2.1', '5.2.2', '5.3.1', '5.3.2', '5.4', 'null']}, '6.适用日期/时段': {'type': 'string'}, '7.非服务类商品': {'type': 'string'}}, 'required': ['1.服务名称', '2.适用部位', '3.服务方式', '4.服务时长', '5.适用人群', '6.适用日期/时段', '7.非服务类商品'], 'additionalProperties': False}, '项目单B': {'type': 'object', 'properties': {'1.服务名称': {'type': 'array', 'items': {'type': 'string', 'enum': ['1.1', '1.2', '1.3', '1.4', '1.5', '1.6', '1.7', '1.8', '1.9', '1.10', '1.11', '1.12', '1.13', '1.14', '1.15', 'null']}}, '2.适用部位': {'type': 'array', 'items': {'type': 'string', 'enum': ['2.1.1', '2.1.2', '2.1.3', '2.2.1', '2.2.2', '2.2.3', '2.2.4', '2.2.5', '2.2.6', '2.3.1', '2.4.1', '2.4.2', '2.5.1', '2.5.2', '2.5.3', '2.5.4', '2.5.5', '2.5.6', '2.6.1', '2.7.1', '2.7.2', '2.8.1', '2.8.2', '2.9.1', '2.9.2', 'null']}}, '3.服务方式': {'type': 'array', 'items': {'type': 'string', 'enum': ['3.1.1', '3.1.2', '3.1.3', '3.1.4', '3.2.1', '3.2.2', '3.2.3', '3.2.4', '3.2.5', '3.2.6', '3.2.7', '3.2.8', '3.2.9', '3.2.10', '3.2.11', '3.2.12', '3.2.13', '3.2.14', '3.2.15', '3.3.1', '3.3.2', '3.3.3', '3.3.4', '3.3.5', '3.4.1', '3.4.2', '3.4.3', '3.4.4', '3.4.5', '3.5.1', '3.5.2', '3.5.3', '3.5.4', '3.5.5', '3.6.1', '3.6.2', '3.6.3', '3.7.1', '3.7.2', '3.7.3', '3.7.4', '3.8.1', '3.8.2', '3.8.3', '3.8.4', '3.9.1', '3.9.2', '3.10.1', '3.10.2', '3.10.3', '3.10.4', '3.10.5', '3.10.6', '3.11.1', '3.11.2', '3.11.3', '3.11.4', '3.12.1', '3.12.2', 'null']}}, '4.服务时长': {'type': 'string', 'enum': ['(0-30]', '(30-40]', '(40-60]', '(60-80]', '(80-90]', '(90-100]', '(100-120]', '(120-∞]', 'null']}, '5.适用人群': {'type': 'string', 'enum': ['5.1.1', '5.2.1', '5.2.2', '5.3.1', '5.3.2', '5.4', 'null']}, '6.适用日期/时段': {'type': 'string'}, '7.非服务类商品': {'type': 'string'}}, 'required': ['1.服务名称', '2.适用部位', '3.服务方式', '4.服务时长', '5.适用人群', '6.适用日期/时段', '7.非服务类商品'], 'additionalProperties': False}, '匹配结果': {'type': 'string', 'enum': ['是', '否']}}, 'required': ['项目单A', '项目单B', '匹配结果'], 'additionalProperties': False}",
        "target": {
            "项目单A": {
                "1.服务名称": [
                    "1.11"
                ],
                "2.适用部位": [
                    "null"
                ],
                "3.服务方式": [
                    "3.8.1",
                    "3.8.3"
                ],
                "4.服务时长": "(60-80]",
                "5.适用人群": "5.2.1",
                "6.适用日期/时段": "周一至周天全天可用",
                "7.非服务类商品": "null"
            },
            "项目单B": {
                "1.服务名称": [
                    "1.11"
                ],
                "2.适用部位": [
                    "2.5.1"
                ],
                "3.服务方式": [
                    "3.8.1"
                ],
                "4.服务时长": "(100-120]",
                "5.适用人群": "5.2.1",
                "6.适用日期/时段": "周一至周日全天可用",
                "7.非服务类商品": "null"
            },
            "匹配结果": "否"
        },
        "json_schema": {
            "$schema": "http://json-schema.org/draft-07/schema#",
            "type": "object",
            "properties": {
                "项目单A": {
                    "type": "object",
                    "properties": {
                        "1.服务名称": {
                            "type": "array",
                            "items": {
                                "type": "string",
                                "enum": [
                                    "1.1",
                                    "1.2",
                                    "1.3",
                                    "1.4",
                                    "1.5",
                                    "1.6",
                                    "1.7",
                                    "1.8",
                                    "1.9",
                                    "1.10",
                                    "1.11",
                                    "1.12",
                                    "1.13",
                                    "1.14",
                                    "1.15",
                                    "null"
                                ]
                            }
                        },
                        "2.适用部位": {
                            "type": "array",
                            "items": {
                                "type": "string",
                                "enum": [
                                    "2.1.1",
                                    "2.1.2",
                                    "2.1.3",
                                    "2.2.1",
                                    "2.2.2",
                                    "2.2.3",
                                    "2.2.4",
                                    "2.2.5",
                                    "2.2.6",
                                    "2.3.1",
                                    "2.4.1",
                                    "2.4.2",
                                    "2.5.1",
                                    "2.5.2",
                                    "2.5.3",
                                    "2.5.4",
                                    "2.5.5",
                                    "2.5.6",
                                    "2.6.1",
                                    "2.7.1",
                                    "2.7.2",
                                    "2.8.1",
                                    "2.8.2",
                                    "2.9.1",
                                    "2.9.2",
                                    "null"
                                ]
                            }
                        },
                        "3.服务方式": {
                            "type": "array",
                            "items": {
                                "type": "string",
                                "enum": [
                                    "3.1.1",
                                    "3.1.2",
                                    "3.1.3",
                                    "3.1.4",
                                    "3.2.1",
                                    "3.2.2",
                                    "3.2.3",
                                    "3.2.4",
                                    "3.2.5",
                                    "3.2.6",
                                    "3.2.7",
                                    "3.2.8",
                                    "3.2.9",
                                    "3.2.10",
                                    "3.2.11",
                                    "3.2.12",
                                    "3.2.13",
                                    "3.2.14",
                                    "3.2.15",
                                    "3.3.1",
                                    "3.3.2",
                                    "3.3.3",
                                    "3.3.4",
                                    "3.3.5",
                                    "3.4.1",
                                    "3.4.2",
                                    "3.4.3",
                                    "3.4.4",
                                    "3.4.5",
                                    "3.5.1",
                                    "3.5.2",
                                    "3.5.3",
                                    "3.5.4",
                                    "3.5.5",
                                    "3.6.1",
                                    "3.6.2",
                                    "3.6.3",
                                    "3.7.1",
                                    "3.7.2",
                                    "3.7.3",
                                    "3.7.4",
                                    "3.8.1",
                                    "3.8.2",
                                    "3.8.3",
                                    "3.8.4",
                                    "3.9.1",
                                    "3.9.2",
                                    "3.10.1",
                                    "3.10.2",
                                    "3.10.3",
                                    "3.10.4",
                                    "3.10.5",
                                    "3.10.6",
                                    "3.11.1",
                                    "3.11.2",
                                    "3.11.3",
                                    "3.11.4",
                                    "3.12.1",
                                    "3.12.2",
                                    "null"
                                ]
                            }
                        },
                        "4.服务时长": {
                            "type": "string",
                            "enum": [
                                "(0-30]",
                                "(30-40]",
                                "(40-60]",
                                "(60-80]",
                                "(80-90]",
                                "(90-100]",
                                "(100-120]",
                                "(120-∞]",
                                "null"
                            ]
                        },
                        "5.适用人群": {
                            "type": "string",
                            "enum": [
                                "5.1.1",
                                "5.2.1",
                                "5.2.2",
                                "5.3.1",
                                "5.3.2",
                                "5.4",
                                "null"
                            ]
                        },
                        "6.适用日期/时段": {
                            "type": "string"
                        },
                        "7.非服务类商品": {
                            "type": "string"
                        }
                    },
                    "required": [
                        "1.服务名称",
                        "2.适用部位",
                        "3.服务方式",
                        "4.服务时长",
                        "5.适用人群",
                        "6.适用日期/时段",
                        "7.非服务类商品"
                    ],
                    "additionalProperties": false
                },
                "项目单B": {
                    "type": "object",
                    "properties": {
                        "1.服务名称": {
                            "type": "array",
                            "items": {
                                "type": "string",
                                "enum": [
                                    "1.1",
                                    "1.2",
                                    "1.3",
                                    "1.4",
                                    "1.5",
                                    "1.6",
                                    "1.7",
                                    "1.8",
                                    "1.9",
                                    "1.10",
                                    "1.11",
                                    "1.12",
                                    "1.13",
                                    "1.14",
                                    "1.15",
                                    "null"
                                ]
                            }
                        },
                        "2.适用部位": {
                            "type": "array",
                            "items": {
                                "type": "string",
                                "enum": [
                                    "2.1.1",
                                    "2.1.2",
                                    "2.1.3",
                                    "2.2.1",
                                    "2.2.2",
                                    "2.2.3",
                                    "2.2.4",
                                    "2.2.5",
                                    "2.2.6",
                                    "2.3.1",
                                    "2.4.1",
                                    "2.4.2",
                                    "2.5.1",
                                    "2.5.2",
                                    "2.5.3",
                                    "2.5.4",
                                    "2.5.5",
                                    "2.5.6",
                                    "2.6.1",
                                    "2.7.1",
                                    "2.7.2",
                                    "2.8.1",
                                    "2.8.2",
                                    "2.9.1",
                                    "2.9.2",
                                    "null"
                                ]
                            }
                        },
                        "3.服务方式": {
                            "type": "array",
                            "items": {
                                "type": "string",
                                "enum": [
                                    "3.1.1",
                                    "3.1.2",
                                    "3.1.3",
                                    "3.1.4",
                                    "3.2.1",
                                    "3.2.2",
                                    "3.2.3",
                                    "3.2.4",
                                    "3.2.5",
                                    "3.2.6",
                                    "3.2.7",
                                    "3.2.8",
                                    "3.2.9",
                                    "3.2.10",
                                    "3.2.11",
                                    "3.2.12",
                                    "3.2.13",
                                    "3.2.14",
                                    "3.2.15",
                                    "3.3.1",
                                    "3.3.2",
                                    "3.3.3",
                                    "3.3.4",
                                    "3.3.5",
                                    "3.4.1",
                                    "3.4.2",
                                    "3.4.3",
                                    "3.4.4",
                                    "3.4.5",
                                    "3.5.1",
                                    "3.5.2",
                                    "3.5.3",
                                    "3.5.4",
                                    "3.5.5",
                                    "3.6.1",
                                    "3.6.2",
                                    "3.6.3",
                                    "3.7.1",
                                    "3.7.2",
                                    "3.7.3",
                                    "3.7.4",
                                    "3.8.1",
                                    "3.8.2",
                                    "3.8.3",
                                    "3.8.4",
                                    "3.9.1",
                                    "3.9.2",
                                    "3.10.1",
                                    "3.10.2",
                                    "3.10.3",
                                    "3.10.4",
                                    "3.10.5",
                                    "3.10.6",
                                    "3.11.1",
                                    "3.11.2",
                                    "3.11.3",
                                    "3.11.4",
                                    "3.12.1",
                                    "3.12.2",
                                    "null"
                                ]
                            }
                        },
                        "4.服务时长": {
                            "type": "string",
                            "enum": [
                                "(0-30]",
                                "(30-40]",
                                "(40-60]",
                                "(60-80]",
                                "(80-90]",
                                "(90-100]",
                                "(100-120]",
                                "(120-∞]",
                                "null"
                            ]
                        },
                        "5.适用人群": {
                            "type": "string",
                            "enum": [
                                "5.1.1",
                                "5.2.1",
                                "5.2.2",
                                "5.3.1",
                                "5.3.2",
                                "5.4",
                                "null"
                            ]
                        },
                        "6.适用日期/时段": {
                            "type": "string"
                        },
                        "7.非服务类商品": {
                            "type": "string"
                        }
                    },
                    "required": [
                        "1.服务名称",
                        "2.适用部位",
                        "3.服务方式",
                        "4.服务时长",
                        "5.适用人群",
                        "6.适用日期/时段",
                        "7.非服务类商品"
                    ],
                    "additionalProperties": false
                },
                "匹配结果": {
                    "type": "string",
                    "enum": [
                        "是",
                        "否"
                    ]
                }
            },
            "required": [
                "项目单A",
                "项目单B",
                "匹配结果"
            ],
            "additionalProperties": false
        },
        "no_required_eval_acc_keys": [
            "6.适用日期/时段"
        ],
        "model_response": "```json\n{\n  \"项目单A\": {\n    \"1.服务名称\": [\n      \"1.11\"\n    ],\n    \"2.适用部位\": [\n      \"2.5.2\"\n    ],\n    \"3.服务方式\": [\n      \"3.8.1\"\n    ],\n    \"4.服务时长\": \"(60-80]\",\n    \"5.适用人群\": \"5.2.1\",\n    \"6.适用日期/时段\": \"全天可用\",\n    \"7.非服务类商品\": \"null\"\n  },\n  \"项目单B\": {\n    \"1.服务名称\": [\n      \"1.11\"\n    ],\n    \"2.适用部位\": [\n      \"2.5.1\"\n    ],\n    \"3.服务方式\": [\n      \"3.8.1\"\n    ],\n    \"4.服务时长\": \"(100-120]\",\n    \"5.适用人群\": \"5.2.1\",\n    \"6.适用日期/时段\": \"全天可用\",\n    \"7.非服务类商品\": \"null\"\n  },\n  \"匹配结果\": \"否\"\n}\n```"
    },
    {
        "input": "【Background】\n【角色定义】你是一名消费者,你需要充分了解两个商家提供的生活项目并进行比较, 根据关键要素抽取规则和项目匹配规则来判断两个项目是否相同或匹配，并且以结构化数据的形式把两个项目结果展示出来。\n【Requirements】\n\n\n项目单的信息包括：商品标题、项目单详情、有效期、营业时间、适用人数、购买限制等。关键要素包括：服务名称、适用部位、服务方式、服务时长、适用人群、适用日期/时段、非服务类商品。（注意：如果有枚举值需要归类到枚举值，如果该内容在枚举值之外则默认为null；严格按照优先级，获取信息后不再考虑剩余。\"\n    \"1.服务名称，同一项目单可能包含多个项目，需要全部列举（注意：出现好评礼、会员礼所附赠的项目不计入服务名称。例如：“好评一次深层洁净60分钟”，则服务名称为“null”。优先级：商品标题 > 服务功效 > 服务流程/步骤\n     枚举值：\n     1.1深层洁净(收缩毛孔)\n     1.2补水保湿(皮肤清洁、毛孔洗澡)\n     1.3祛痘\n     1.4美白嫩肤\n     1.5淡斑祛斑\n     1.6紧致提拉\n     1.7修复护理\n     1.8脱毛\n     1.9眼部护理\n     1.10肩颈按摩\n     1.11SPA\n     1.12头疗\n     1.13养生调理\n     1.14瘦身纤体\n     1.15美胸美臀\n\n    2.适用部位：和服务名称对应。优先级：商品标题 > 服务功效 > 服务流程/步骤\n     枚举值：\n     2.1深层洁净/补水保湿/祛痘/美白嫩肤/淡斑祛斑/紧致提拉/修复护理：2.1.1面部,2.1.2部分面部,2.1.3背部 \n     2.2脱毛：2.2.1口唇,2.2.2腋下,2.2.3面部,2.2.4手臂,2.2.5腿部,2.2.6私密/比基尼\n     2.3眼部护理：2.3.1眼部 \n     2.4肩颈按摩：2.4.1肩颈,2.4.2肩颈+背 \n     2.5SPA：2.5.1全身,2.5.2肩颈+腰背,2.5.3肩颈+背部+腿部,2.5.4肩颈+腰腹+腿,2.5.5头+肩+颈+背,2.5.6背部 \n     2.6头疗：2.6.1头部\n     2.7养生调理：2.7.1全身(未指明部位),2.7.2局部(非全身，或者指明某个部位) \n     2.8瘦身纤体：2.8.1全身,2.8.2局部塑形 \n     2.9美胸美臀：2.9.1胸部,2.9.2臀部\n    \n    3.服务方式：和服务名称对应。优先级：项目单详情>商品标题\n     枚举值：（注意：1.未提到以下内容的，输出null;2.如果出现2种或者2种以上结果需要都输出）\n     3.1深层洁净：3.1.1)仪器(超微小气泡/大气泡/臭氧泡泡/魔法活氧泡泡) 3.1.2)海菲秀 3.1.3)泥膜/面膜 3.1.4)白牌产品 \n    3.2补水保湿：3.2.1)B5精华 3.2.2)修丽可 3.2.3)日式pola 3.2.4)日式晓姿 3.2.5)赫莲娜HR 3.2.6)伊芙珑evelom 3.2.7)海蓝之谜LA MER 3.2.8)瑞妍cellcosment 3.2.9)莱珀妮 LA PRAIRIE 3.2.10)迪奥DIOR 3.2.11)圣罗兰YSL 3.2.12)诚美DGR 3.2.13)法尔曼VALMONT 3.2.14)菲洛嘉FILORGA 3.2.15)白牌产品\n     3.3祛痘：3.3.1)手工针清/皮铲/护理 3.3.2)点阵激光 3.3.3)红蓝光/PDT光能/烤光 3.3.4)刷酸/果酸 3.3.5)草本 \n     3.4美白嫩肤：3.4.1)焕肤类 3.4.2)氨甲环酸 3.4.3)大牌产品(菲洛嘉) 3.4.4)普牌产品(欧诗漫) 3.4.5)白牌产品 \n     3.5紧致提拉：3.5.1)手法按摩类 3.5.2)抗糖祛黄/生物酶疗 3.5.3)木乃伊紧致 3.5.4)大牌产品(赫莲娜/日式POLA) 3.5.5)白牌产品 \n     3.6修复护理：3.6.1)酵素/乳糖酸/骨胶原/活性酶 3.6.2)大牌产品(赫莲娜/伊芙珑/海蓝之谜/瑞妍/莱珀妮/迪奥/圣罗兰诚美DGR/法尔曼/菲洛嘉) 3.6.3)白牌产品\n     3.7肩颈按摩：3.7.1)使用精油 3.7.2)不使用精油 3.7.3)热石精油 3.7.4)水疗\n     3.8全身SPA：3.8.1)使用精油 3.8.2)不使用精油 3.8.3)热石精油 3.8.4)水疗\n     3.9头疗：3.9.1)使用精油 3.9.2)不使用精油 \n     3.10养生调理：3.10.1)灸类 3.10.2)刮痧 3.10.3)罐类 3.10.4)蒸/浴类 3.10.5)经络/净排类 3.10.6)产后修复类\n     3.11瘦身纤体：3.11.1)针灸/拔罐/经络 3.11.2)刮痧 3.11.3)仪器 3.11.4)调理粉/精油\n     3.12.美胸美臀：3.12.1)使用精油 3.12.2)不使用精油\n\n    4.服务时长，总服务时长(服务项目的服务时长总和)。优先级：商品标题>项目单详情\n    需要映射到枚举值：(0-30]、(30-40]、(40-60]、(60-80]、(80-90]、(90-100]、(100-120]、(120-∞]（输出答案时需要输出具体的枚举值内容）\n\n    5.适用人群，包括性别、年龄、用户类型（出现“XX节”属于营销词，不能作为性别的判断，eg.女神节专属、母亲节，不能判断性别为女性） 优先级：购买限制>商品标题>项目单详情\n     枚举值：（注意：此项优先级：用户类型>性别>年龄，只需输出一个类别）\n     5.1用户类型：5.1.1新客价格（第一次使用该项目的用户）\n     5.2性别：5.2.1男性，5.2.2女性\n     5.3年龄：5.3.1儿童（0-12周岁）,5.3.2成人（18岁以上）\n     5.4不限通用(每人限购1份，不限年龄，性别)\n\n    6.适用日期/时段（注意：全天可用等于商家营业时间可用；闲时指的是周一到周五的下午4点前）  优先级：项目单详情>商品标题>购买须知\n    注意1：项目单详情中信息多处不符一致时，则取最小时段进行对比，eg1.A单适用日期：2025年7月1日-2025年9月1日，周一-周五10:00-19:00可用；B单适用日期2025.7.1-2025.10.1周一到周日10:00-22:00，则AB两单适用日期/时段不一致。eg2.2025年8月1日-2025年8月30日，周一-周五10:00-19:00可用；B单适用日期2025.7.1-2025.10.1周一-周天10:00-19:00可用，则AB两单适用日期/时段一致（不考虑年月日时格式）\n    注意2：适用日期/时段：从营业时间得到信息，仅看“周一-周日”、“xx月xx日-xx月xx日”、“xx:xx-xx:xx”、“xx点-xx点”等类似字眼，无需关注特殊节假日；时段：由“开始时间”和“结束时间”组成，输出具体的时间，例如“10:00-22:00” \n\n    7.非服务类商品：指的是除服务名称以外的内容，eg.“深层洁净60分钟+（含/送/赠）XX面膜2盒”，”非服务商品为“XX面膜，2盒”。如果是仅面膜、产品，零食、皮肤检测等非美容美体产品不算非服务产品，此时输出null。\n\n    8.白牌产品：指的是小厂商生产的没有牌子的商品，白牌是相对品牌而言的。\n\n\n    项目单匹配规则：根据抽取出来的要素和以下规则判断是否为同一项目单“注意：如果无法识别出来则默认为null”\n     1.服务名称：需完全一致，否则认为两个项目单不一致(不考虑顺序)。\n     2.适用部位：需完全一致，否则认为两个项目单不一致(不考虑顺序)。\n     3.服务方式：任意一方有值另一方空值，不可以视为一致。需要两侧都有值进行判断是否一致。\n     4.服务时长：如果任意一方有值另一方空值，可以视为一致。但当双方都有值时，双方时长一致才算一致。\n     5.适用人群：性别、年龄、用户类型要完全一样才算一致，如果任意一方空值则默认为“不限通用”，随后再对比出结果。\n     6.适用日期/时段：\n      1)当只有适用日期（年月日）时，日期精确到年月日相同则认为一致，eg.A单适用日期：2025年7月1日-2025年10月1日；B单适用日期2025.7.1-2025.10.1，则AB两单适用日期一致。（不考虑年月日格式）\n      2)当任意一方“适用日期”为空值，则取适用时段或者运营时间进行比较，AB两单之间起始及终止时间相差为1小时以内，可视为一致，超过1小时则为不一致。\n     7.非服务类商品：\n      1)纯非服务类商品，无需参与匹配。\n      2)若出现服务名称+非服务产品，针对服务内容按照规则匹配；非服务类商品需精准匹配，内容具体到名称+规格或者单位或者品牌。eg.“深层洁净60分钟+（含/送/赠）XX面膜2盒”，”非服务商品为“2盒XX面膜”\n    判断步骤：\n     1. 根据输入的项目单信息和规则抽取相应的要素，以及输出对应的枚举值内容\n     2. 根据抽取要素、枚举值内容和匹配规则来判断两个项目单是否匹配\n     \n     \n\n【Input】 \n5.项目单A：【毛孔清洁4部曲】收缩毛孔清爽控油(毛孔深层淳洗)。温馨提示：1:孕妇不可用；2:敏感肌或者其他肤质问题，请咨询商家。使用须知：每张优惠券最多1人使用，每人不限购买次数，不限会员使用，不再与其他优惠同享。营业时间：周一至周日10:00-22:00。服务流程：1.浅度清洁3分钟，产品说明：【慕斯大泡沫】1000倍绵密氨基酸大泡沫，仿佛扎进云朵里；。2.毛孔舒张5分钟，产品说明：【水氧清洁】细密水雾颗粒高压清洗，深度清洁毛孔；3.深度清洁17分钟；4.面部铲皮清洁1分钟；5. 冷喷镇静2分钟；6. 【收尾护理】水乳保湿+防晒2分钟。项目单B：【拜拜草莓鼻】黑头大扫除|深层清洁(黑头深层淳洗)30分钟。服务流程：1.慕斯大泡沫全脸部，说明：绵密氨基酸大泡沫，仿佛扎进云朵里；2.湿敷黑头导出液T区，说明：采用天然表面活性剂皂苷，温和不刺激；3.热喷舒缓全脸部，说明：40°C，舒张每一个毛孔；4.头部舒缓放松头部，说明：头部解压舒缓SPA；5.小气泡清洁T区，说明：小气泡深层清洁T区黑头；6.顽固黑头可视化清洁T区，说明：直面一颗颗黑头被清除；7.铲皮机清洁T区，说明：铲皮机铲走顽固残留；8.涂抹收敛水全脸部，说明：富含北美金缕梅提取物，收缩毛孔；9.冰锤收敛全脸部，说明：4°C，自然收细每一个毛孔；10.收尾护理全脸部，说明：水乳保湿+防晒。温馨提示：1.为避免排队给您带来不悦，请提前2小时拨打门店电话预约；2.孕妇不可用、敏感肌请咨询商家。使用须知：每张优惠券限1人使用，单次消费不限制使用张数，不与店内优惠同享，发票问题请询问商家。购买后60天有效。可用时间：10:00-20:00。适用全脸。服务功效：深层清洁、去黑头。\n\n\n\n【Output Requirement】\n 你的输出必须满足以下JSON_SCHEMA{'$schema': 'http://json-schema.org/draft-07/schema#', 'type': 'object', 'properties': {'项目单A': {'type': 'object', 'properties': {'1.服务名称': {'type': 'array', 'items': {'type': 'string', 'enum': ['1.1', '1.2', '1.3', '1.4', '1.5', '1.6', '1.7', '1.8', '1.9', '1.10', '1.11', '1.12', '1.13', '1.14', '1.15', 'null']}}, '2.适用部位': {'type': 'array', 'items': {'type': 'string', 'enum': ['2.1.1', '2.1.2', '2.1.3', '2.2.1', '2.2.2', '2.2.3', '2.2.4', '2.2.5', '2.2.6', '2.3.1', '2.4.1', '2.4.2', '2.5.1', '2.5.2', '2.5.3', '2.5.4', '2.5.5', '2.5.6', '2.6.1', '2.7.1', '2.7.2', '2.8.1', '2.8.2', '2.9.1', '2.9.2', 'null']}}, '3.服务方式': {'type': 'array', 'items': {'type': 'string', 'enum': ['3.1.1', '3.1.2', '3.1.3', '3.1.4', '3.2.1', '3.2.2', '3.2.3', '3.2.4', '3.2.5', '3.2.6', '3.2.7', '3.2.8', '3.2.9', '3.2.10', '3.2.11', '3.2.12', '3.2.13', '3.2.14', '3.2.15', '3.3.1', '3.3.2', '3.3.3', '3.3.4', '3.3.5', '3.4.1', '3.4.2', '3.4.3', '3.4.4', '3.4.5', '3.5.1', '3.5.2', '3.5.3', '3.5.4', '3.5.5', '3.6.1', '3.6.2', '3.6.3', '3.7.1', '3.7.2', '3.7.3', '3.7.4', '3.8.1', '3.8.2', '3.8.3', '3.8.4', '3.9.1', '3.9.2', '3.10.1', '3.10.2', '3.10.3', '3.10.4', '3.10.5', '3.10.6', '3.11.1', '3.11.2', '3.11.3', '3.11.4', '3.12.1', '3.12.2', 'null']}}, '4.服务时长': {'type': 'string', 'enum': ['(0-30]', '(30-40]', '(40-60]', '(60-80]', '(80-90]', '(90-100]', '(100-120]', '(120-∞]', 'null']}, '5.适用人群': {'type': 'string', 'enum': ['5.1.1', '5.2.1', '5.2.2', '5.3.1', '5.3.2', '5.4', 'null']}, '6.适用日期/时段': {'type': 'string'}, '7.非服务类商品': {'type': 'string'}}, 'required': ['1.服务名称', '2.适用部位', '3.服务方式', '4.服务时长', '5.适用人群', '6.适用日期/时段', '7.非服务类商品'], 'additionalProperties': False}, '项目单B': {'type': 'object', 'properties': {'1.服务名称': {'type': 'array', 'items': {'type': 'string', 'enum': ['1.1', '1.2', '1.3', '1.4', '1.5', '1.6', '1.7', '1.8', '1.9', '1.10', '1.11', '1.12', '1.13', '1.14', '1.15', 'null']}}, '2.适用部位': {'type': 'array', 'items': {'type': 'string', 'enum': ['2.1.1', '2.1.2', '2.1.3', '2.2.1', '2.2.2', '2.2.3', '2.2.4', '2.2.5', '2.2.6', '2.3.1', '2.4.1', '2.4.2', '2.5.1', '2.5.2', '2.5.3', '2.5.4', '2.5.5', '2.5.6', '2.6.1', '2.7.1', '2.7.2', '2.8.1', '2.8.2', '2.9.1', '2.9.2', 'null']}}, '3.服务方式': {'type': 'array', 'items': {'type': 'string', 'enum': ['3.1.1', '3.1.2', '3.1.3', '3.1.4', '3.2.1', '3.2.2', '3.2.3', '3.2.4', '3.2.5', '3.2.6', '3.2.7', '3.2.8', '3.2.9', '3.2.10', '3.2.11', '3.2.12', '3.2.13', '3.2.14', '3.2.15', '3.3.1', '3.3.2', '3.3.3', '3.3.4', '3.3.5', '3.4.1', '3.4.2', '3.4.3', '3.4.4', '3.4.5', '3.5.1', '3.5.2', '3.5.3', '3.5.4', '3.5.5', '3.6.1', '3.6.2', '3.6.3', '3.7.1', '3.7.2', '3.7.3', '3.7.4', '3.8.1', '3.8.2', '3.8.3', '3.8.4', '3.9.1', '3.9.2', '3.10.1', '3.10.2', '3.10.3', '3.10.4', '3.10.5', '3.10.6', '3.11.1', '3.11.2', '3.11.3', '3.11.4', '3.12.1', '3.12.2', 'null']}}, '4.服务时长': {'type': 'string', 'enum': ['(0-30]', '(30-40]', '(40-60]', '(60-80]', '(80-90]', '(90-100]', '(100-120]', '(120-∞]', 'null']}, '5.适用人群': {'type': 'string', 'enum': ['5.1.1', '5.2.1', '5.2.2', '5.3.1', '5.3.2', '5.4', 'null']}, '6.适用日期/时段': {'type': 'string'}, '7.非服务类商品': {'type': 'string'}}, 'required': ['1.服务名称', '2.适用部位', '3.服务方式', '4.服务时长', '5.适用人群', '6.适用日期/时段', '7.非服务类商品'], 'additionalProperties': False}, '匹配结果': {'type': 'string', 'enum': ['是', '否']}}, 'required': ['项目单A', '项目单B', '匹配结果'], 'additionalProperties': False}",
        "target": {
            "项目单A": {
                "1.服务名称": [
                    "1.1"
                ],
                "2.适用部位": [
                    "2.1.1"
                ],
                "3.服务方式": [
                    "3.1.1"
                ],
                "4.服务时长": "(0-30]",
                "5.适用人群": "5.4",
                "6.适用日期/时段": "周一至周日10:00-22:00",
                "7.非服务类商品": "null"
            },
            "项目单B": {
                "1.服务名称": [
                    "1.1"
                ],
                "2.适用部位": [
                    "2.1.1"
                ],
                "3.服务方式": [
                    "3.1.1"
                ],
                "4.服务时长": "(0-30]",
                "5.适用人群": "5.4",
                "6.适用日期/时段": "10:00-20:00",
                "7.非服务类商品": "null"
            },
            "匹配结果": "否"
        },
        "json_schema": {
            "$schema": "http://json-schema.org/draft-07/schema#",
            "type": "object",
            "properties": {
                "项目单A": {
                    "type": "object",
                    "properties": {
                        "1.服务名称": {
                            "type": "array",
                            "items": {
                                "type": "string",
                                "enum": [
                                    "1.1",
                                    "1.2",
                                    "1.3",
                                    "1.4",
                                    "1.5",
                                    "1.6",
                                    "1.7",
                                    "1.8",
                                    "1.9",
                                    "1.10",
                                    "1.11",
                                    "1.12",
                                    "1.13",
                                    "1.14",
                                    "1.15",
                                    "null"
                                ]
                            }
                        },
                        "2.适用部位": {
                            "type": "array",
                            "items": {
                                "type": "string",
                                "enum": [
                                    "2.1.1",
                                    "2.1.2",
                                    "2.1.3",
                                    "2.2.1",
                                    "2.2.2",
                                    "2.2.3",
                                    "2.2.4",
                                    "2.2.5",
                                    "2.2.6",
                                    "2.3.1",
                                    "2.4.1",
                                    "2.4.2",
                                    "2.5.1",
                                    "2.5.2",
                                    "2.5.3",
                                    "2.5.4",
                                    "2.5.5",
                                    "2.5.6",
                                    "2.6.1",
                                    "2.7.1",
                                    "2.7.2",
                                    "2.8.1",
                                    "2.8.2",
                                    "2.9.1",
                                    "2.9.2",
                                    "null"
                                ]
                            }
                        },
                        "3.服务方式": {
                            "type": "array",
                            "items": {
                                "type": "string",
                                "enum": [
                                    "3.1.1",
                                    "3.1.2",
                                    "3.1.3",
                                    "3.1.4",
                                    "3.2.1",
                                    "3.2.2",
                                    "3.2.3",
                                    "3.2.4",
                                    "3.2.5",
                                    "3.2.6",
                                    "3.2.7",
                                    "3.2.8",
                                    "3.2.9",
                                    "3.2.10",
                                    "3.2.11",
                                    "3.2.12",
                                    "3.2.13",
                                    "3.2.14",
                                    "3.2.15",
                                    "3.3.1",
                                    "3.3.2",
                                    "3.3.3",
                                    "3.3.4",
                                    "3.3.5",
                                    "3.4.1",
                                    "3.4.2",
                                    "3.4.3",
                                    "3.4.4",
                                    "3.4.5",
                                    "3.5.1",
                                    "3.5.2",
                                    "3.5.3",
                                    "3.5.4",
                                    "3.5.5",
                                    "3.6.1",
                                    "3.6.2",
                                    "3.6.3",
                                    "3.7.1",
                                    "3.7.2",
                                    "3.7.3",
                                    "3.7.4",
                                    "3.8.1",
                                    "3.8.2",
                                    "3.8.3",
                                    "3.8.4",
                                    "3.9.1",
                                    "3.9.2",
                                    "3.10.1",
                                    "3.10.2",
                                    "3.10.3",
                                    "3.10.4",
                                    "3.10.5",
                                    "3.10.6",
                                    "3.11.1",
                                    "3.11.2",
                                    "3.11.3",
                                    "3.11.4",
                                    "3.12.1",
                                    "3.12.2",
                                    "null"
                                ]
                            }
                        },
                        "4.服务时长": {
                            "type": "string",
                            "enum": [
                                "(0-30]",
                                "(30-40]",
                                "(40-60]",
                                "(60-80]",
                                "(80-90]",
                                "(90-100]",
                                "(100-120]",
                                "(120-∞]",
                                "null"
                            ]
                        },
                        "5.适用人群": {
                            "type": "string",
                            "enum": [
                                "5.1.1",
                                "5.2.1",
                                "5.2.2",
                                "5.3.1",
                                "5.3.2",
                                "5.4",
                                "null"
                            ]
                        },
                        "6.适用日期/时段": {
                            "type": "string"
                        },
                        "7.非服务类商品": {
                            "type": "string"
                        }
                    },
                    "required": [
                        "1.服务名称",
                        "2.适用部位",
                        "3.服务方式",
                        "4.服务时长",
                        "5.适用人群",
                        "6.适用日期/时段",
                        "7.非服务类商品"
                    ],
                    "additionalProperties": false
                },
                "项目单B": {
                    "type": "object",
                    "properties": {
                        "1.服务名称": {
                            "type": "array",
                            "items": {
                                "type": "string",
                                "enum": [
                                    "1.1",
                                    "1.2",
                                    "1.3",
                                    "1.4",
                                    "1.5",
                                    "1.6",
                                    "1.7",
                                    "1.8",
                                    "1.9",
                                    "1.10",
                                    "1.11",
                                    "1.12",
                                    "1.13",
                                    "1.14",
                                    "1.15",
                                    "null"
                                ]
                            }
                        },
                        "2.适用部位": {
                            "type": "array",
                            "items": {
                                "type": "string",
                                "enum": [
                                    "2.1.1",
                                    "2.1.2",
                                    "2.1.3",
                                    "2.2.1",
                                    "2.2.2",
                                    "2.2.3",
                                    "2.2.4",
                                    "2.2.5",
                                    "2.2.6",
                                    "2.3.1",
                                    "2.4.1",
                                    "2.4.2",
                                    "2.5.1",
                                    "2.5.2",
                                    "2.5.3",
                                    "2.5.4",
                                    "2.5.5",
                                    "2.5.6",
                                    "2.6.1",
                                    "2.7.1",
                                    "2.7.2",
                                    "2.8.1",
                                    "2.8.2",
                                    "2.9.1",
                                    "2.9.2",
                                    "null"
                                ]
                            }
                        },
                        "3.服务方式": {
                            "type": "array",
                            "items": {
                                "type": "string",
                                "enum": [
                                    "3.1.1",
                                    "3.1.2",
                                    "3.1.3",
                                    "3.1.4",
                                    "3.2.1",
                                    "3.2.2",
                                    "3.2.3",
                                    "3.2.4",
                                    "3.2.5",
                                    "3.2.6",
                                    "3.2.7",
                                    "3.2.8",
                                    "3.2.9",
                                    "3.2.10",
                                    "3.2.11",
                                    "3.2.12",
                                    "3.2.13",
                                    "3.2.14",
                                    "3.2.15",
                                    "3.3.1",
                                    "3.3.2",
                                    "3.3.3",
                                    "3.3.4",
                                    "3.3.5",
                                    "3.4.1",
                                    "3.4.2",
                                    "3.4.3",
                                    "3.4.4",
                                    "3.4.5",
                                    "3.5.1",
                                    "3.5.2",
                                    "3.5.3",
                                    "3.5.4",
                                    "3.5.5",
                                    "3.6.1",
                                    "3.6.2",
                                    "3.6.3",
                                    "3.7.1",
                                    "3.7.2",
                                    "3.7.3",
                                    "3.7.4",
                                    "3.8.1",
                                    "3.8.2",
                                    "3.8.3",
                                    "3.8.4",
                                    "3.9.1",
                                    "3.9.2",
                                    "3.10.1",
                                    "3.10.2",
                                    "3.10.3",
                                    "3.10.4",
                                    "3.10.5",
                                    "3.10.6",
                                    "3.11.1",
                                    "3.11.2",
                                    "3.11.3",
                                    "3.11.4",
                                    "3.12.1",
                                    "3.12.2",
                                    "null"
                                ]
                            }
                        },
                        "4.服务时长": {
                            "type": "string",
                            "enum": [
                                "(0-30]",
                                "(30-40]",
                                "(40-60]",
                                "(60-80]",
                                "(80-90]",
                                "(90-100]",
                                "(100-120]",
                                "(120-∞]",
                                "null"
                            ]
                        },
                        "5.适用人群": {
                            "type": "string",
                            "enum": [
                                "5.1.1",
                                "5.2.1",
                                "5.2.2",
                                "5.3.1",
                                "5.3.2",
                                "5.4",
                                "null"
                            ]
                        },
                        "6.适用日期/时段": {
                            "type": "string"
                        },
                        "7.非服务类商品": {
                            "type": "string"
                        }
                    },
                    "required": [
                        "1.服务名称",
                        "2.适用部位",
                        "3.服务方式",
                        "4.服务时长",
                        "5.适用人群",
                        "6.适用日期/时段",
                        "7.非服务类商品"
                    ],
                    "additionalProperties": false
                },
                "匹配结果": {
                    "type": "string",
                    "enum": [
                        "是",
                        "否"
                    ]
                }
            },
            "required": [
                "项目单A",
                "项目单B",
                "匹配结果"
            ],
            "additionalProperties": false
        },
        "no_required_eval_acc_keys": [
            "6.适用日期/时段"
        ],
        "model_response": "```json\n{\n    \"项目单A\": {\n        \"1.服务名称\": [\"1.1\"],\n        \"2.适用部位\": [\"2.1.1\"],\n        \"3.服务方式\": [\"3.1.1\", \"3.3.1\"],\n        \"4.服务时长\": \"(30-40]\",\n        \"5.适用人群\": \"5.4\",\n        \"6.适用日期/时段\": \"10:00-22:00\",\n        \"7.非服务类商品\": \"null\"\n    },\n    \"项目单B\": {\n        \"1.服务名称\": [\"1.1\"],\n        \"2.适用部位\": [\"2.1.1\"],\n        \"3.服务方式\": [\"3.1.1\", \"3.3.1\"],\n        \"4.服务时长\": \"(30-40]\",\n        \"5.适用人群\": \"5.4\",\n        \"6.适用日期/时段\": \"10:00-20:00\",\n        \"7.非服务类商品\": \"null\"\n    },\n    \"匹配结果\": \"否\"\n}\n```"
    },
    {
        "input": "【Background】\n【角色定义】你是一名消费者,你需要充分了解两个商家提供的生活项目并进行比较, 根据关键要素抽取规则和项目匹配规则来判断两个项目是否相同或匹配，并且以结构化数据的形式把两个项目结果展示出来。\n【Requirements】\n\n\n项目单的信息包括：商品标题、项目单详情、有效期、营业时间、适用人数、购买限制等。关键要素包括：服务名称、适用部位、服务方式、服务时长、适用人群、适用日期/时段、非服务类商品。（注意：如果有枚举值需要归类到枚举值，如果该内容在枚举值之外则默认为null；严格按照优先级，获取信息后不再考虑剩余。\"\n    \"1.服务名称，同一项目单可能包含多个项目，需要全部列举（注意：出现好评礼、会员礼所附赠的项目不计入服务名称。例如：“好评一次深层洁净60分钟”，则服务名称为“null”。优先级：商品标题 > 服务功效 > 服务流程/步骤\n     枚举值：\n     1.1深层洁净(收缩毛孔)\n     1.2补水保湿(皮肤清洁、毛孔洗澡)\n     1.3祛痘\n     1.4美白嫩肤\n     1.5淡斑祛斑\n     1.6紧致提拉\n     1.7修复护理\n     1.8脱毛\n     1.9眼部护理\n     1.10肩颈按摩\n     1.11SPA\n     1.12头疗\n     1.13养生调理\n     1.14瘦身纤体\n     1.15美胸美臀\n\n    2.适用部位：和服务名称对应。优先级：商品标题 > 服务功效 > 服务流程/步骤\n     枚举值：\n     2.1深层洁净/补水保湿/祛痘/美白嫩肤/淡斑祛斑/紧致提拉/修复护理：2.1.1面部,2.1.2部分面部,2.1.3背部 \n     2.2脱毛：2.2.1口唇,2.2.2腋下,2.2.3面部,2.2.4手臂,2.2.5腿部,2.2.6私密/比基尼\n     2.3眼部护理：2.3.1眼部 \n     2.4肩颈按摩：2.4.1肩颈,2.4.2肩颈+背 \n     2.5SPA：2.5.1全身,2.5.2肩颈+腰背,2.5.3肩颈+背部+腿部,2.5.4肩颈+腰腹+腿,2.5.5头+肩+颈+背,2.5.6背部 \n     2.6头疗：2.6.1头部\n     2.7养生调理：2.7.1全身(未指明部位),2.7.2局部(非全身，或者指明某个部位) \n     2.8瘦身纤体：2.8.1全身,2.8.2局部塑形 \n     2.9美胸美臀：2.9.1胸部,2.9.2臀部\n    \n    3.服务方式：和服务名称对应。优先级：项目单详情>商品标题\n     枚举值：（注意：1.未提到以下内容的，输出null;2.如果出现2种或者2种以上结果需要都输出）\n     3.1深层洁净：3.1.1)仪器(超微小气泡/大气泡/臭氧泡泡/魔法活氧泡泡) 3.1.2)海菲秀 3.1.3)泥膜/面膜 3.1.4)白牌产品 \n    3.2补水保湿：3.2.1)B5精华 3.2.2)修丽可 3.2.3)日式pola 3.2.4)日式晓姿 3.2.5)赫莲娜HR 3.2.6)伊芙珑evelom 3.2.7)海蓝之谜LA MER 3.2.8)瑞妍cellcosment 3.2.9)莱珀妮 LA PRAIRIE 3.2.10)迪奥DIOR 3.2.11)圣罗兰YSL 3.2.12)诚美DGR 3.2.13)法尔曼VALMONT 3.2.14)菲洛嘉FILORGA 3.2.15)白牌产品\n     3.3祛痘：3.3.1)手工针清/皮铲/护理 3.3.2)点阵激光 3.3.3)红蓝光/PDT光能/烤光 3.3.4)刷酸/果酸 3.3.5)草本 \n     3.4美白嫩肤：3.4.1)焕肤类 3.4.2)氨甲环酸 3.4.3)大牌产品(菲洛嘉) 3.4.4)普牌产品(欧诗漫) 3.4.5)白牌产品 \n     3.5紧致提拉：3.5.1)手法按摩类 3.5.2)抗糖祛黄/生物酶疗 3.5.3)木乃伊紧致 3.5.4)大牌产品(赫莲娜/日式POLA) 3.5.5)白牌产品 \n     3.6修复护理：3.6.1)酵素/乳糖酸/骨胶原/活性酶 3.6.2)大牌产品(赫莲娜/伊芙珑/海蓝之谜/瑞妍/莱珀妮/迪奥/圣罗兰诚美DGR/法尔曼/菲洛嘉) 3.6.3)白牌产品\n     3.7肩颈按摩：3.7.1)使用精油 3.7.2)不使用精油 3.7.3)热石精油 3.7.4)水疗\n     3.8全身SPA：3.8.1)使用精油 3.8.2)不使用精油 3.8.3)热石精油 3.8.4)水疗\n     3.9头疗：3.9.1)使用精油 3.9.2)不使用精油 \n     3.10养生调理：3.10.1)灸类 3.10.2)刮痧 3.10.3)罐类 3.10.4)蒸/浴类 3.10.5)经络/净排类 3.10.6)产后修复类\n     3.11瘦身纤体：3.11.1)针灸/拔罐/经络 3.11.2)刮痧 3.11.3)仪器 3.11.4)调理粉/精油\n     3.12.美胸美臀：3.12.1)使用精油 3.12.2)不使用精油\n\n    4.服务时长，总服务时长(服务项目的服务时长总和)。优先级：商品标题>项目单详情\n    需要映射到枚举值：(0-30]、(30-40]、(40-60]、(60-80]、(80-90]、(90-100]、(100-120]、(120-∞]（输出答案时需要输出具体的枚举值内容）\n\n    5.适用人群，包括性别、年龄、用户类型（出现“XX节”属于营销词，不能作为性别的判断，eg.女神节专属、母亲节，不能判断性别为女性） 优先级：购买限制>商品标题>项目单详情\n     枚举值：（注意：此项优先级：用户类型>性别>年龄，只需输出一个类别）\n     5.1用户类型：5.1.1新客价格（第一次使用该项目的用户）\n     5.2性别：5.2.1男性，5.2.2女性\n     5.3年龄：5.3.1儿童（0-12周岁）,5.3.2成人（18岁以上）\n     5.4不限通用(每人限购1份，不限年龄，性别)\n\n    6.适用日期/时段（注意：全天可用等于商家营业时间可用；闲时指的是周一到周五的下午4点前）  优先级：项目单详情>商品标题>购买须知\n    注意1：项目单详情中信息多处不符一致时，则取最小时段进行对比，eg1.A单适用日期：2025年7月1日-2025年9月1日，周一-周五10:00-19:00可用；B单适用日期2025.7.1-2025.10.1周一到周日10:00-22:00，则AB两单适用日期/时段不一致。eg2.2025年8月1日-2025年8月30日，周一-周五10:00-19:00可用；B单适用日期2025.7.1-2025.10.1周一-周天10:00-19:00可用，则AB两单适用日期/时段一致（不考虑年月日时格式）\n    注意2：适用日期/时段：从营业时间得到信息，仅看“周一-周日”、“xx月xx日-xx月xx日”、“xx:xx-xx:xx”、“xx点-xx点”等类似字眼，无需关注特殊节假日；时段：由“开始时间”和“结束时间”组成，输出具体的时间，例如“10:00-22:00” \n\n    7.非服务类商品：指的是除服务名称以外的内容，eg.“深层洁净60分钟+（含/送/赠）XX面膜2盒”，”非服务商品为“XX面膜，2盒”。如果是仅面膜、产品，零食、皮肤检测等非美容美体产品不算非服务产品，此时输出null。\n\n    8.白牌产品：指的是小厂商生产的没有牌子的商品，白牌是相对品牌而言的。\n\n\n    项目单匹配规则：根据抽取出来的要素和以下规则判断是否为同一项目单“注意：如果无法识别出来则默认为null”\n     1.服务名称：需完全一致，否则认为两个项目单不一致(不考虑顺序)。\n     2.适用部位：需完全一致，否则认为两个项目单不一致(不考虑顺序)。\n     3.服务方式：任意一方有值另一方空值，不可以视为一致。需要两侧都有值进行判断是否一致。\n     4.服务时长：如果任意一方有值另一方空值，可以视为一致。但当双方都有值时，双方时长一致才算一致。\n     5.适用人群：性别、年龄、用户类型要完全一样才算一致，如果任意一方空值则默认为“不限通用”，随后再对比出结果。\n     6.适用日期/时段：\n      1)当只有适用日期（年月日）时，日期精确到年月日相同则认为一致，eg.A单适用日期：2025年7月1日-2025年10月1日；B单适用日期2025.7.1-2025.10.1，则AB两单适用日期一致。（不考虑年月日格式）\n      2)当任意一方“适用日期”为空值，则取适用时段或者运营时间进行比较，AB两单之间起始及终止时间相差为1小时以内，可视为一致，超过1小时则为不一致。\n     7.非服务类商品：\n      1)纯非服务类商品，无需参与匹配。\n      2)若出现服务名称+非服务产品，针对服务内容按照规则匹配；非服务类商品需精准匹配，内容具体到名称+规格或者单位或者品牌。eg.“深层洁净60分钟+（含/送/赠）XX面膜2盒”，”非服务商品为“2盒XX面膜”\n    判断步骤：\n     1. 根据输入的项目单信息和规则抽取相应的要素，以及输出对应的枚举值内容\n     2. 根据抽取要素、枚举值内容和匹配规则来判断两个项目单是否匹配\n     \n     \n\n【Input】 \n6. 项目单A:{'商品标题': '【痘痘多→】全脸定制祛痘健康无痘肌', '图文详情': '', '有效期': '', '适用人数': '每张优惠券最多1人使用', '规则提醒': '不再与其他优惠同享', '购买限制': '每人限购1张，只适用于初次到店非商户会员使用', '营业时间': '周一至周日10:00-21:00', '项目单详情': [{'名称': '全脸祛痘', '分类': '皮肤管理', '二级分类': '祛痘清痘', '服务功效': '祛痘清痘', '适用部位': '全面部', '服务次数': '','适用性别': '', '服务亮点': '', '服务流程': '', '服务步骤': [{'产品': '', '说明': '痘肌360度多维检测', '名称': '皮肤检测', '设备': '', '二级名称': '皮肤检测', '时长': '10分钟', '部位': ''}, {'产品': '', '说明': '痘肌卸妆三重洁净', '名称': '卸妆洁面', '设备': '', '二级名称': '卸妆洁面', '时长': '5分钟', '部位': ''}, {'产品': '', '说明': '温感热喷舒张毛孔', '名称': '面部清洁', '设备': '', '二级名称': '毛孔舒张', '时长': '5分钟', '部位': ''}, {'产品': '', '说明': '清洁油脂', '名称': '面部清洁', '设备': '', '二级名称': '深层清洁', '时长': '3分钟', '部位': ''}, {'产品': '', '说明': '全脸指法触压定位排痘', '名称': '痘肌护理', '设备': '', '二级名称': '手工清痘', '时长': '10分钟', '部位': ''}, {'产品': '', '说明': '水氧肌底活肤喷冲', '名称': '补水保湿', '设备': '', '二级名称': '深层补水', '时长': '5分钟', '部位': ''}, {'产品': '', '说明': '祛痘精华肌底冰感注导', '名称': '修护护理', '设备': '', '二级名称': '修护护理', '时长': '5分钟', '部位': ''}, {'产品': '', '说明': '定制蓝藻膜修护', '名称': '修护护理', '设备': '', '二级名称': '修护护理', '时长': '10分钟', '部位': ''}, {'产品': '', '说明': '痘肌舒缓点霜修护', '名称': '修护护理', '设备': '', '二级名称': '修护护理', '时长': '2分钟', '部位': ''}, {'产品': '', '说明': '仪器LED动力修护', '名称': '修护护理', '设备': '', '二级名称': '修护护理', '时长': '5分钟', '部位': ''}], '服务附赠': ''}]} 项目单B:{'商品标题': '【热销】三合一黑头管理➕补水➕大气泡深层清洁毛孔{新客专享}', '营业时间': '10:00-21:00', '服务功效': '深层清洁、去黑头', '适用性别': '不限', '适用部位': '全脸部', '有效期': '有效期：购买后360天有效', '可用时间': '商家营业时间可用', '购买限制': '每人限购1份', '适用人数': '每张优惠券限1人使用', '其他规则': '单次消费最多使用1张优惠券;不与店内优惠同享;发票问题请询问商家;•不与店内优惠同享;•单次消费最多使用1张优惠券;•每张优惠券最多1人使用;1、到店体验服务需提前1小时电话预约，由于活动门店可能顾客过多，若无预约进店，门店可推后接待，请谅解！;2、全国门店通用，仅限新客，可转赠亲友，但在活动期内每人只限使用一次，限用一张，不可叠加使用;3、此套餐无隐形消费，套餐内的内容都可以使用，套餐外的消费请咨询商家;4、周末节假日适用，男女不限。 ', '项目单详情': [{'名称': '三合一黑头管理、补水、大气', '分类': '三合一护理', '部位': '', '服务流程': '皮肤检测全脸部10分钟;深层洁净全脸部5分钟;修护护理全脸部8分钟;深层洁净全脸部8分钟;修护护理全脸部5分钟;深层洁净脸颊10分钟;补水保湿全脸部10分钟;补水保湿全脸部10分钟;说明：SOR智能面部检测;说明：净颜泡泡卸妆洁面;说明：热喷打开毛孔;说明：吸附毛孔垃圾;说明：真空吸附N+清透;说明：黑头清理;说明：补水保湿全面部;说明：调制面膜修护', '附赠': '免费茶歇零食'}]}\n\n\n\n【Output Requirement】\n 你的输出必须满足以下JSON_SCHEMA{'$schema': 'http://json-schema.org/draft-07/schema#', 'type': 'object', 'properties': {'项目单A': {'type': 'object', 'properties': {'1.服务名称': {'type': 'array', 'items': {'type': 'string', 'enum': ['1.1', '1.2', '1.3', '1.4', '1.5', '1.6', '1.7', '1.8', '1.9', '1.10', '1.11', '1.12', '1.13', '1.14', '1.15', 'null']}}, '2.适用部位': {'type': 'array', 'items': {'type': 'string', 'enum': ['2.1.1', '2.1.2', '2.1.3', '2.2.1', '2.2.2', '2.2.3', '2.2.4', '2.2.5', '2.2.6', '2.3.1', '2.4.1', '2.4.2', '2.5.1', '2.5.2', '2.5.3', '2.5.4', '2.5.5', '2.5.6', '2.6.1', '2.7.1', '2.7.2', '2.8.1', '2.8.2', '2.9.1', '2.9.2', 'null']}}, '3.服务方式': {'type': 'array', 'items': {'type': 'string', 'enum': ['3.1.1', '3.1.2', '3.1.3', '3.1.4', '3.2.1', '3.2.2', '3.2.3', '3.2.4', '3.2.5', '3.2.6', '3.2.7', '3.2.8', '3.2.9', '3.2.10', '3.2.11', '3.2.12', '3.2.13', '3.2.14', '3.2.15', '3.3.1', '3.3.2', '3.3.3', '3.3.4', '3.3.5', '3.4.1', '3.4.2', '3.4.3', '3.4.4', '3.4.5', '3.5.1', '3.5.2', '3.5.3', '3.5.4', '3.5.5', '3.6.1', '3.6.2', '3.6.3', '3.7.1', '3.7.2', '3.7.3', '3.7.4', '3.8.1', '3.8.2', '3.8.3', '3.8.4', '3.9.1', '3.9.2', '3.10.1', '3.10.2', '3.10.3', '3.10.4', '3.10.5', '3.10.6', '3.11.1', '3.11.2', '3.11.3', '3.11.4', '3.12.1', '3.12.2', 'null']}}, '4.服务时长': {'type': 'string', 'enum': ['(0-30]', '(30-40]', '(40-60]', '(60-80]', '(80-90]', '(90-100]', '(100-120]', '(120-∞]', 'null']}, '5.适用人群': {'type': 'string', 'enum': ['5.1.1', '5.2.1', '5.2.2', '5.3.1', '5.3.2', '5.4', 'null']}, '6.适用日期/时段': {'type': 'string'}, '7.非服务类商品': {'type': 'string'}}, 'required': ['1.服务名称', '2.适用部位', '3.服务方式', '4.服务时长', '5.适用人群', '6.适用日期/时段', '7.非服务类商品'], 'additionalProperties': False}, '项目单B': {'type': 'object', 'properties': {'1.服务名称': {'type': 'array', 'items': {'type': 'string', 'enum': ['1.1', '1.2', '1.3', '1.4', '1.5', '1.6', '1.7', '1.8', '1.9', '1.10', '1.11', '1.12', '1.13', '1.14', '1.15', 'null']}}, '2.适用部位': {'type': 'array', 'items': {'type': 'string', 'enum': ['2.1.1', '2.1.2', '2.1.3', '2.2.1', '2.2.2', '2.2.3', '2.2.4', '2.2.5', '2.2.6', '2.3.1', '2.4.1', '2.4.2', '2.5.1', '2.5.2', '2.5.3', '2.5.4', '2.5.5', '2.5.6', '2.6.1', '2.7.1', '2.7.2', '2.8.1', '2.8.2', '2.9.1', '2.9.2', 'null']}}, '3.服务方式': {'type': 'array', 'items': {'type': 'string', 'enum': ['3.1.1', '3.1.2', '3.1.3', '3.1.4', '3.2.1', '3.2.2', '3.2.3', '3.2.4', '3.2.5', '3.2.6', '3.2.7', '3.2.8', '3.2.9', '3.2.10', '3.2.11', '3.2.12', '3.2.13', '3.2.14', '3.2.15', '3.3.1', '3.3.2', '3.3.3', '3.3.4', '3.3.5', '3.4.1', '3.4.2', '3.4.3', '3.4.4', '3.4.5', '3.5.1', '3.5.2', '3.5.3', '3.5.4', '3.5.5', '3.6.1', '3.6.2', '3.6.3', '3.7.1', '3.7.2', '3.7.3', '3.7.4', '3.8.1', '3.8.2', '3.8.3', '3.8.4', '3.9.1', '3.9.2', '3.10.1', '3.10.2', '3.10.3', '3.10.4', '3.10.5', '3.10.6', '3.11.1', '3.11.2', '3.11.3', '3.11.4', '3.12.1', '3.12.2', 'null']}}, '4.服务时长': {'type': 'string', 'enum': ['(0-30]', '(30-40]', '(40-60]', '(60-80]', '(80-90]', '(90-100]', '(100-120]', '(120-∞]', 'null']}, '5.适用人群': {'type': 'string', 'enum': ['5.1.1', '5.2.1', '5.2.2', '5.3.1', '5.3.2', '5.4', 'null']}, '6.适用日期/时段': {'type': 'string'}, '7.非服务类商品': {'type': 'string'}}, 'required': ['1.服务名称', '2.适用部位', '3.服务方式', '4.服务时长', '5.适用人群', '6.适用日期/时段', '7.非服务类商品'], 'additionalProperties': False}, '匹配结果': {'type': 'string', 'enum': ['是', '否']}}, 'required': ['项目单A', '项目单B', '匹配结果'], 'additionalProperties': False}",
        "target": {
            "项目单A": {
                "1.服务名称": [
                    "1.3"
                ],
                "2.适用部位": [
                    "2.1.1"
                ],
                "3.服务方式": [
                    "3.3.1"
                ],
                "4.服务时长": "(40-60]",
                "5.适用人群": "5.1.1",
                "6.适用日期/时段": "周一至周日10:00-21:00",
                "7.非服务类商品": "null"
            },
            "项目单B": {
                "1.服务名称": [
                    "1.1",
                    "1.2"
                ],
                "2.适用部位": [
                    "2.1.1"
                ],
                "3.服务方式": [
                    "3.1.1"
                ],
                "4.服务时长": "(60-80]",
                "5.适用人群": "5.1.1",
                "6.适用日期/时段": "10:00-21:00",
                "7.非服务类商品": "null"
            },
            "匹配结果": "否"
        },
        "json_schema": {
            "$schema": "http://json-schema.org/draft-07/schema#",
            "type": "object",
            "properties": {
                "项目单A": {
                    "type": "object",
                    "properties": {
                        "1.服务名称": {
                            "type": "array",
                            "items": {
                                "type": "string",
                                "enum": [
                                    "1.1",
                                    "1.2",
                                    "1.3",
                                    "1.4",
                                    "1.5",
                                    "1.6",
                                    "1.7",
                                    "1.8",
                                    "1.9",
                                    "1.10",
                                    "1.11",
                                    "1.12",
                                    "1.13",
                                    "1.14",
                                    "1.15",
                                    "null"
                                ]
                            }
                        },
                        "2.适用部位": {
                            "type": "array",
                            "items": {
                                "type": "string",
                                "enum": [
                                    "2.1.1",
                                    "2.1.2",
                                    "2.1.3",
                                    "2.2.1",
                                    "2.2.2",
                                    "2.2.3",
                                    "2.2.4",
                                    "2.2.5",
                                    "2.2.6",
                                    "2.3.1",
                                    "2.4.1",
                                    "2.4.2",
                                    "2.5.1",
                                    "2.5.2",
                                    "2.5.3",
                                    "2.5.4",
                                    "2.5.5",
                                    "2.5.6",
                                    "2.6.1",
                                    "2.7.1",
                                    "2.7.2",
                                    "2.8.1",
                                    "2.8.2",
                                    "2.9.1",
                                    "2.9.2",
                                    "null"
                                ]
                            }
                        },
                        "3.服务方式": {
                            "type": "array",
                            "items": {
                                "type": "string",
                                "enum": [
                                    "3.1.1",
                                    "3.1.2",
                                    "3.1.3",
                                    "3.1.4",
                                    "3.2.1",
                                    "3.2.2",
                                    "3.2.3",
                                    "3.2.4",
                                    "3.2.5",
                                    "3.2.6",
                                    "3.2.7",
                                    "3.2.8",
                                    "3.2.9",
                                    "3.2.10",
                                    "3.2.11",
                                    "3.2.12",
                                    "3.2.13",
                                    "3.2.14",
                                    "3.2.15",
                                    "3.3.1",
                                    "3.3.2",
                                    "3.3.3",
                                    "3.3.4",
                                    "3.3.5",
                                    "3.4.1",
                                    "3.4.2",
                                    "3.4.3",
                                    "3.4.4",
                                    "3.4.5",
                                    "3.5.1",
                                    "3.5.2",
                                    "3.5.3",
                                    "3.5.4",
                                    "3.5.5",
                                    "3.6.1",
                                    "3.6.2",
                                    "3.6.3",
                                    "3.7.1",
                                    "3.7.2",
                                    "3.7.3",
                                    "3.7.4",
                                    "3.8.1",
                                    "3.8.2",
                                    "3.8.3",
                                    "3.8.4",
                                    "3.9.1",
                                    "3.9.2",
                                    "3.10.1",
                                    "3.10.2",
                                    "3.10.3",
                                    "3.10.4",
                                    "3.10.5",
                                    "3.10.6",
                                    "3.11.1",
                                    "3.11.2",
                                    "3.11.3",
                                    "3.11.4",
                                    "3.12.1",
                                    "3.12.2",
                                    "null"
                                ]
                            }
                        },
                        "4.服务时长": {
                            "type": "string",
                            "enum": [
                                "(0-30]",
                                "(30-40]",
                                "(40-60]",
                                "(60-80]",
                                "(80-90]",
                                "(90-100]",
                                "(100-120]",
                                "(120-∞]",
                                "null"
                            ]
                        },
                        "5.适用人群": {
                            "type": "string",
                            "enum": [
                                "5.1.1",
                                "5.2.1",
                                "5.2.2",
                                "5.3.1",
                                "5.3.2",
                                "5.4",
                                "null"
                            ]
                        },
                        "6.适用日期/时段": {
                            "type": "string"
                        },
                        "7.非服务类商品": {
                            "type": "string"
                        }
                    },
                    "required": [
                        "1.服务名称",
                        "2.适用部位",
                        "3.服务方式",
                        "4.服务时长",
                        "5.适用人群",
                        "6.适用日期/时段",
                        "7.非服务类商品"
                    ],
                    "additionalProperties": false
                },
                "项目单B": {
                    "type": "object",
                    "properties": {
                        "1.服务名称": {
                            "type": "array",
                            "items": {
                                "type": "string",
                                "enum": [
                                    "1.1",
                                    "1.2",
                                    "1.3",
                                    "1.4",
                                    "1.5",
                                    "1.6",
                                    "1.7",
                                    "1.8",
                                    "1.9",
                                    "1.10",
                                    "1.11",
                                    "1.12",
                                    "1.13",
                                    "1.14",
                                    "1.15",
                                    "null"
                                ]
                            }
                        },
                        "2.适用部位": {
                            "type": "array",
                            "items": {
                                "type": "string",
                                "enum": [
                                    "2.1.1",
                                    "2.1.2",
                                    "2.1.3",
                                    "2.2.1",
                                    "2.2.2",
                                    "2.2.3",
                                    "2.2.4",
                                    "2.2.5",
                                    "2.2.6",
                                    "2.3.1",
                                    "2.4.1",
                                    "2.4.2",
                                    "2.5.1",
                                    "2.5.2",
                                    "2.5.3",
                                    "2.5.4",
                                    "2.5.5",
                                    "2.5.6",
                                    "2.6.1",
                                    "2.7.1",
                                    "2.7.2",
                                    "2.8.1",
                                    "2.8.2",
                                    "2.9.1",
                                    "2.9.2",
                                    "null"
                                ]
                            }
                        },
                        "3.服务方式": {
                            "type": "array",
                            "items": {
                                "type": "string",
                                "enum": [
                                    "3.1.1",
                                    "3.1.2",
                                    "3.1.3",
                                    "3.1.4",
                                    "3.2.1",
                                    "3.2.2",
                                    "3.2.3",
                                    "3.2.4",
                                    "3.2.5",
                                    "3.2.6",
                                    "3.2.7",
                                    "3.2.8",
                                    "3.2.9",
                                    "3.2.10",
                                    "3.2.11",
                                    "3.2.12",
                                    "3.2.13",
                                    "3.2.14",
                                    "3.2.15",
                                    "3.3.1",
                                    "3.3.2",
                                    "3.3.3",
                                    "3.3.4",
                                    "3.3.5",
                                    "3.4.1",
                                    "3.4.2",
                                    "3.4.3",
                                    "3.4.4",
                                    "3.4.5",
                                    "3.5.1",
                                    "3.5.2",
                                    "3.5.3",
                                    "3.5.4",
                                    "3.5.5",
                                    "3.6.1",
                                    "3.6.2",
                                    "3.6.3",
                                    "3.7.1",
                                    "3.7.2",
                                    "3.7.3",
                                    "3.7.4",
                                    "3.8.1",
                                    "3.8.2",
                                    "3.8.3",
                                    "3.8.4",
                                    "3.9.1",
                                    "3.9.2",
                                    "3.10.1",
                                    "3.10.2",
                                    "3.10.3",
                                    "3.10.4",
                                    "3.10.5",
                                    "3.10.6",
                                    "3.11.1",
                                    "3.11.2",
                                    "3.11.3",
                                    "3.11.4",
                                    "3.12.1",
                                    "3.12.2",
                                    "null"
                                ]
                            }
                        },
                        "4.服务时长": {
                            "type": "string",
                            "enum": [
                                "(0-30]",
                                "(30-40]",
                                "(40-60]",
                                "(60-80]",
                                "(80-90]",
                                "(90-100]",
                                "(100-120]",
                                "(120-∞]",
                                "null"
                            ]
                        },
                        "5.适用人群": {
                            "type": "string",
                            "enum": [
                                "5.1.1",
                                "5.2.1",
                                "5.2.2",
                                "5.3.1",
                                "5.3.2",
                                "5.4",
                                "null"
                            ]
                        },
                        "6.适用日期/时段": {
                            "type": "string"
                        },
                        "7.非服务类商品": {
                            "type": "string"
                        }
                    },
                    "required": [
                        "1.服务名称",
                        "2.适用部位",
                        "3.服务方式",
                        "4.服务时长",
                        "5.适用人群",
                        "6.适用日期/时段",
                        "7.非服务类商品"
                    ],
                    "additionalProperties": false
                },
                "匹配结果": {
                    "type": "string",
                    "enum": [
                        "是",
                        "否"
                    ]
                }
            },
            "required": [
                "项目单A",
                "项目单B",
                "匹配结果"
            ],
            "additionalProperties": false
        },
        "no_required_eval_acc_keys": [
            "6.适用日期/时段"
        ],
        "model_response": "```json\n{\n    \"项目单A\": {\n        \"1.服务名称\": [\"1.3\", \"1.2\", \"1.7\"],\n        \"2.适用部位\": [\"2.1.1\"],\n        \"3.服务方式\": [\"3.3.1\", \"3.2.15\", \"3.6.3\"],\n        \"4.服务时长\": \"(40-60]\",\n        \"5.适用人群\": \"5.1.1\",\n        \"6.适用日期/时段\": \"10:00-21:00\",\n        \"7.非服务类商品\": \"null\"\n    },\n    \"项目单B\": {\n        \"1.服务名称\": [\"1.1\", \"1.2\"],\n        \"2.适用部位\": [\"2.1.1\"],\n        \"3.服务方式\": [\"3.1.1\", \"3.2.15\"],\n        \"4.服务时长\": \"(40-60]\",\n        \"5.适用人群\": \"5.4\",\n        \"6.适用日期/时段\": \"10:00-21:00\",\n        \"7.非服务类商品\": \"null\"\n    },\n    \"匹配结果\": \"否\"\n}\n```"
    },
    {
        "input": "【Background】\n【角色定义】你是一名消费者,你需要充分了解两个商家提供的生活项目并进行比较, 根据关键要素抽取规则和项目匹配规则来判断两个项目是否相同或匹配，并且以结构化数据的形式把两个项目结果展示出来。\n【Requirements】\n\n\n项目单的信息包括：商品标题、项目单详情、有效期、营业时间、适用人数、购买限制等。关键要素包括：服务名称、适用部位、服务方式、服务时长、适用人群、适用日期/时段、非服务类商品。（注意：如果有枚举值需要归类到枚举值，如果该内容在枚举值之外则默认为null；严格按照优先级，获取信息后不再考虑剩余。\"\n    \"1.服务名称，同一项目单可能包含多个项目，需要全部列举（注意：出现好评礼、会员礼所附赠的项目不计入服务名称。例如：“好评一次深层洁净60分钟”，则服务名称为“null”。优先级：商品标题 > 服务功效 > 服务流程/步骤\n     枚举值：\n     1.1深层洁净(收缩毛孔)\n     1.2补水保湿(皮肤清洁、毛孔洗澡)\n     1.3祛痘\n     1.4美白嫩肤\n     1.5淡斑祛斑\n     1.6紧致提拉\n     1.7修复护理\n     1.8脱毛\n     1.9眼部护理\n     1.10肩颈按摩\n     1.11SPA\n     1.12头疗\n     1.13养生调理\n     1.14瘦身纤体\n     1.15美胸美臀\n\n    2.适用部位：和服务名称对应。优先级：商品标题 > 服务功效 > 服务流程/步骤\n     枚举值：\n     2.1深层洁净/补水保湿/祛痘/美白嫩肤/淡斑祛斑/紧致提拉/修复护理：2.1.1面部,2.1.2部分面部,2.1.3背部 \n     2.2脱毛：2.2.1口唇,2.2.2腋下,2.2.3面部,2.2.4手臂,2.2.5腿部,2.2.6私密/比基尼\n     2.3眼部护理：2.3.1眼部 \n     2.4肩颈按摩：2.4.1肩颈,2.4.2肩颈+背 \n     2.5SPA：2.5.1全身,2.5.2肩颈+腰背,2.5.3肩颈+背部+腿部,2.5.4肩颈+腰腹+腿,2.5.5头+肩+颈+背,2.5.6背部 \n     2.6头疗：2.6.1头部\n     2.7养生调理：2.7.1全身(未指明部位),2.7.2局部(非全身，或者指明某个部位) \n     2.8瘦身纤体：2.8.1全身,2.8.2局部塑形 \n     2.9美胸美臀：2.9.1胸部,2.9.2臀部\n    \n    3.服务方式：和服务名称对应。优先级：项目单详情>商品标题\n     枚举值：（注意：1.未提到以下内容的，输出null;2.如果出现2种或者2种以上结果需要都输出）\n     3.1深层洁净：3.1.1)仪器(超微小气泡/大气泡/臭氧泡泡/魔法活氧泡泡) 3.1.2)海菲秀 3.1.3)泥膜/面膜 3.1.4)白牌产品 \n    3.2补水保湿：3.2.1)B5精华 3.2.2)修丽可 3.2.3)日式pola 3.2.4)日式晓姿 3.2.5)赫莲娜HR 3.2.6)伊芙珑evelom 3.2.7)海蓝之谜LA MER 3.2.8)瑞妍cellcosment 3.2.9)莱珀妮 LA PRAIRIE 3.2.10)迪奥DIOR 3.2.11)圣罗兰YSL 3.2.12)诚美DGR 3.2.13)法尔曼VALMONT 3.2.14)菲洛嘉FILORGA 3.2.15)白牌产品\n     3.3祛痘：3.3.1)手工针清/皮铲/护理 3.3.2)点阵激光 3.3.3)红蓝光/PDT光能/烤光 3.3.4)刷酸/果酸 3.3.5)草本 \n     3.4美白嫩肤：3.4.1)焕肤类 3.4.2)氨甲环酸 3.4.3)大牌产品(菲洛嘉) 3.4.4)普牌产品(欧诗漫) 3.4.5)白牌产品 \n     3.5紧致提拉：3.5.1)手法按摩类 3.5.2)抗糖祛黄/生物酶疗 3.5.3)木乃伊紧致 3.5.4)大牌产品(赫莲娜/日式POLA) 3.5.5)白牌产品 \n     3.6修复护理：3.6.1)酵素/乳糖酸/骨胶原/活性酶 3.6.2)大牌产品(赫莲娜/伊芙珑/海蓝之谜/瑞妍/莱珀妮/迪奥/圣罗兰诚美DGR/法尔曼/菲洛嘉) 3.6.3)白牌产品\n     3.7肩颈按摩：3.7.1)使用精油 3.7.2)不使用精油 3.7.3)热石精油 3.7.4)水疗\n     3.8全身SPA：3.8.1)使用精油 3.8.2)不使用精油 3.8.3)热石精油 3.8.4)水疗\n     3.9头疗：3.9.1)使用精油 3.9.2)不使用精油 \n     3.10养生调理：3.10.1)灸类 3.10.2)刮痧 3.10.3)罐类 3.10.4)蒸/浴类 3.10.5)经络/净排类 3.10.6)产后修复类\n     3.11瘦身纤体：3.11.1)针灸/拔罐/经络 3.11.2)刮痧 3.11.3)仪器 3.11.4)调理粉/精油\n     3.12.美胸美臀：3.12.1)使用精油 3.12.2)不使用精油\n\n    4.服务时长，总服务时长(服务项目的服务时长总和)。优先级：商品标题>项目单详情\n    需要映射到枚举值：(0-30]、(30-40]、(40-60]、(60-80]、(80-90]、(90-100]、(100-120]、(120-∞]（输出答案时需要输出具体的枚举值内容）\n\n    5.适用人群，包括性别、年龄、用户类型（出现“XX节”属于营销词，不能作为性别的判断，eg.女神节专属、母亲节，不能判断性别为女性） 优先级：购买限制>商品标题>项目单详情\n     枚举值：（注意：此项优先级：用户类型>性别>年龄，只需输出一个类别）\n     5.1用户类型：5.1.1新客价格（第一次使用该项目的用户）\n     5.2性别：5.2.1男性，5.2.2女性\n     5.3年龄：5.3.1儿童（0-12周岁）,5.3.2成人（18岁以上）\n     5.4不限通用(每人限购1份，不限年龄，性别)\n\n    6.适用日期/时段（注意：全天可用等于商家营业时间可用；闲时指的是周一到周五的下午4点前）  优先级：项目单详情>商品标题>购买须知\n    注意1：项目单详情中信息多处不符一致时，则取最小时段进行对比，eg1.A单适用日期：2025年7月1日-2025年9月1日，周一-周五10:00-19:00可用；B单适用日期2025.7.1-2025.10.1周一到周日10:00-22:00，则AB两单适用日期/时段不一致。eg2.2025年8月1日-2025年8月30日，周一-周五10:00-19:00可用；B单适用日期2025.7.1-2025.10.1周一-周天10:00-19:00可用，则AB两单适用日期/时段一致（不考虑年月日时格式）\n    注意2：适用日期/时段：从营业时间得到信息，仅看“周一-周日”、“xx月xx日-xx月xx日”、“xx:xx-xx:xx”、“xx点-xx点”等类似字眼，无需关注特殊节假日；时段：由“开始时间”和“结束时间”组成，输出具体的时间，例如“10:00-22:00” \n\n    7.非服务类商品：指的是除服务名称以外的内容，eg.“深层洁净60分钟+（含/送/赠）XX面膜2盒”，”非服务商品为“XX面膜，2盒”。如果是仅面膜、产品，零食、皮肤检测等非美容美体产品不算非服务产品，此时输出null。\n\n    8.白牌产品：指的是小厂商生产的没有牌子的商品，白牌是相对品牌而言的。\n\n\n    项目单匹配规则：根据抽取出来的要素和以下规则判断是否为同一项目单“注意：如果无法识别出来则默认为null”\n     1.服务名称：需完全一致，否则认为两个项目单不一致(不考虑顺序)。\n     2.适用部位：需完全一致，否则认为两个项目单不一致(不考虑顺序)。\n     3.服务方式：任意一方有值另一方空值，不可以视为一致。需要两侧都有值进行判断是否一致。\n     4.服务时长：如果任意一方有值另一方空值，可以视为一致。但当双方都有值时，双方时长一致才算一致。\n     5.适用人群：性别、年龄、用户类型要完全一样才算一致，如果任意一方空值则默认为“不限通用”，随后再对比出结果。\n     6.适用日期/时段：\n      1)当只有适用日期（年月日）时，日期精确到年月日相同则认为一致，eg.A单适用日期：2025年7月1日-2025年10月1日；B单适用日期2025.7.1-2025.10.1，则AB两单适用日期一致。（不考虑年月日格式）\n      2)当任意一方“适用日期”为空值，则取适用时段或者运营时间进行比较，AB两单之间起始及终止时间相差为1小时以内，可视为一致，超过1小时则为不一致。\n     7.非服务类商品：\n      1)纯非服务类商品，无需参与匹配。\n      2)若出现服务名称+非服务产品，针对服务内容按照规则匹配；非服务类商品需精准匹配，内容具体到名称+规格或者单位或者品牌。eg.“深层洁净60分钟+（含/送/赠）XX面膜2盒”，”非服务商品为“2盒XX面膜”\n    判断步骤：\n     1. 根据输入的项目单信息和规则抽取相应的要素，以及输出对应的枚举值内容\n     2. 根据抽取要素、枚举值内容和匹配规则来判断两个项目单是否匹配\n     \n     \n\n【Input】 \n7.项目单A:{'商品标题': '嫩滑一夏·比基尼-双部位私密处脱毛初体验', '图文详情': ' ', '有效期': '', '适用人数': '每张优惠券最多1人使用', '规则提醒': '不再与其他优惠同享', '购买限制': '每人限购1张', '营业时间': '周一至周日 10:00-20:00', '项目单详情': [{'名称': '嫩滑一夏·比基尼-双部位私密处脱毛初', '分类': '脱毛', '二级分类': '', '服务功效': '', '适用部位': '比基尼V区、私密I区', '服务次数': '1次', '服务时长': '', '适用性别': '女士脱毛', '服务亮点': '单人单间、一次性耗材、一客一消毒', '服务流程': '1.清洁5分钟，2.涂胶5分钟，3.脱毛10分钟，4.镇定5分钟', '服务步骤': '', '服务附赠': ''}]} 项目单B:{'商品标题': '【热门】小腿上臂下臂单次脱毛体验三选一 钜惠男女通用', '营业时间': '10:00-21:00', '服务功效': '', '适用部位': '', '服务时长': '', '有效期': '有效期：购买后60天内有效', '可用时间': '10:00-20:00', '购买限制': '每人限购1份', '适用人数': '每张优惠券限1人使用', '其他规则': '未成年不可用，单次消费最多使用1张优惠券;不与店内优惠同享;发票问题请询问商家;三选一，不叠加部位', '项目单详情': [{'名称': '选择下手臂脱毛', '分类': '', '部位': '手臂', '时长': '30分钟', '服务流程': '', '附赠服务': ''}, {'名称': '选择小手臂脱毛', '分类': '', '部位': '手臂', '时长': '30分钟', '服务流程': '', '附赠服务': ''}, {'名称': '选择小腿脱毛', '分类': '', '部位': '腿部', '时长': '30分钟', '服务流程': '', '附赠服务': ''}]}\n\n\n\n【Output Requirement】\n 你的输出必须满足以下JSON_SCHEMA{'$schema': 'http://json-schema.org/draft-07/schema#', 'type': 'object', 'properties': {'项目单A': {'type': 'object', 'properties': {'1.服务名称': {'type': 'array', 'items': {'type': 'string', 'enum': ['1.1', '1.2', '1.3', '1.4', '1.5', '1.6', '1.7', '1.8', '1.9', '1.10', '1.11', '1.12', '1.13', '1.14', '1.15', 'null']}}, '2.适用部位': {'type': 'array', 'items': {'type': 'string', 'enum': ['2.1.1', '2.1.2', '2.1.3', '2.2.1', '2.2.2', '2.2.3', '2.2.4', '2.2.5', '2.2.6', '2.3.1', '2.4.1', '2.4.2', '2.5.1', '2.5.2', '2.5.3', '2.5.4', '2.5.5', '2.5.6', '2.6.1', '2.7.1', '2.7.2', '2.8.1', '2.8.2', '2.9.1', '2.9.2', 'null']}}, '3.服务方式': {'type': 'array', 'items': {'type': 'string', 'enum': ['3.1.1', '3.1.2', '3.1.3', '3.1.4', '3.2.1', '3.2.2', '3.2.3', '3.2.4', '3.2.5', '3.2.6', '3.2.7', '3.2.8', '3.2.9', '3.2.10', '3.2.11', '3.2.12', '3.2.13', '3.2.14', '3.2.15', '3.3.1', '3.3.2', '3.3.3', '3.3.4', '3.3.5', '3.4.1', '3.4.2', '3.4.3', '3.4.4', '3.4.5', '3.5.1', '3.5.2', '3.5.3', '3.5.4', '3.5.5', '3.6.1', '3.6.2', '3.6.3', '3.7.1', '3.7.2', '3.7.3', '3.7.4', '3.8.1', '3.8.2', '3.8.3', '3.8.4', '3.9.1', '3.9.2', '3.10.1', '3.10.2', '3.10.3', '3.10.4', '3.10.5', '3.10.6', '3.11.1', '3.11.2', '3.11.3', '3.11.4', '3.12.1', '3.12.2', 'null']}}, '4.服务时长': {'type': 'string', 'enum': ['(0-30]', '(30-40]', '(40-60]', '(60-80]', '(80-90]', '(90-100]', '(100-120]', '(120-∞]', 'null']}, '5.适用人群': {'type': 'string', 'enum': ['5.1.1', '5.2.1', '5.2.2', '5.3.1', '5.3.2', '5.4', 'null']}, '6.适用日期/时段': {'type': 'string'}, '7.非服务类商品': {'type': 'string'}}, 'required': ['1.服务名称', '2.适用部位', '3.服务方式', '4.服务时长', '5.适用人群', '6.适用日期/时段', '7.非服务类商品'], 'additionalProperties': False}, '项目单B': {'type': 'object', 'properties': {'1.服务名称': {'type': 'array', 'items': {'type': 'string', 'enum': ['1.1', '1.2', '1.3', '1.4', '1.5', '1.6', '1.7', '1.8', '1.9', '1.10', '1.11', '1.12', '1.13', '1.14', '1.15', 'null']}}, '2.适用部位': {'type': 'array', 'items': {'type': 'string', 'enum': ['2.1.1', '2.1.2', '2.1.3', '2.2.1', '2.2.2', '2.2.3', '2.2.4', '2.2.5', '2.2.6', '2.3.1', '2.4.1', '2.4.2', '2.5.1', '2.5.2', '2.5.3', '2.5.4', '2.5.5', '2.5.6', '2.6.1', '2.7.1', '2.7.2', '2.8.1', '2.8.2', '2.9.1', '2.9.2', 'null']}}, '3.服务方式': {'type': 'array', 'items': {'type': 'string', 'enum': ['3.1.1', '3.1.2', '3.1.3', '3.1.4', '3.2.1', '3.2.2', '3.2.3', '3.2.4', '3.2.5', '3.2.6', '3.2.7', '3.2.8', '3.2.9', '3.2.10', '3.2.11', '3.2.12', '3.2.13', '3.2.14', '3.2.15', '3.3.1', '3.3.2', '3.3.3', '3.3.4', '3.3.5', '3.4.1', '3.4.2', '3.4.3', '3.4.4', '3.4.5', '3.5.1', '3.5.2', '3.5.3', '3.5.4', '3.5.5', '3.6.1', '3.6.2', '3.6.3', '3.7.1', '3.7.2', '3.7.3', '3.7.4', '3.8.1', '3.8.2', '3.8.3', '3.8.4', '3.9.1', '3.9.2', '3.10.1', '3.10.2', '3.10.3', '3.10.4', '3.10.5', '3.10.6', '3.11.1', '3.11.2', '3.11.3', '3.11.4', '3.12.1', '3.12.2', 'null']}}, '4.服务时长': {'type': 'string', 'enum': ['(0-30]', '(30-40]', '(40-60]', '(60-80]', '(80-90]', '(90-100]', '(100-120]', '(120-∞]', 'null']}, '5.适用人群': {'type': 'string', 'enum': ['5.1.1', '5.2.1', '5.2.2', '5.3.1', '5.3.2', '5.4', 'null']}, '6.适用日期/时段': {'type': 'string'}, '7.非服务类商品': {'type': 'string'}}, 'required': ['1.服务名称', '2.适用部位', '3.服务方式', '4.服务时长', '5.适用人群', '6.适用日期/时段', '7.非服务类商品'], 'additionalProperties': False}, '匹配结果': {'type': 'string', 'enum': ['是', '否']}}, 'required': ['项目单A', '项目单B', '匹配结果'], 'additionalProperties': False}",
        "target": {
            "项目单A": {
                "1.服务名称": [
                    "1.8"
                ],
                "2.适用部位": [
                    "2.2.6"
                ],
                "3.服务方式": [
                    "null"
                ],
                "4.服务时长": "(0-30]",
                "5.适用人群": "5.2.2",
                "6.适用日期/时段": "周一至周日10:00-20:00",
                "7.非服务类商品": "null"
            },
            "项目单B": {
                "1.服务名称": [
                    "1.8"
                ],
                "2.适用部位": [
                    "2.2.4",
                    "2.2.5"
                ],
                "3.服务方式": [
                    "null"
                ],
                "4.服务时长": "(0-30]",
                "5.适用人群": "5.3.2",
                "6.适用日期/时段": "10:00-20:00",
                "7.非服务类商品": "null"
            },
            "匹配结果": "否"
        },
        "json_schema": {
            "$schema": "http://json-schema.org/draft-07/schema#",
            "type": "object",
            "properties": {
                "项目单A": {
                    "type": "object",
                    "properties": {
                        "1.服务名称": {
                            "type": "array",
                            "items": {
                                "type": "string",
                                "enum": [
                                    "1.1",
                                    "1.2",
                                    "1.3",
                                    "1.4",
                                    "1.5",
                                    "1.6",
                                    "1.7",
                                    "1.8",
                                    "1.9",
                                    "1.10",
                                    "1.11",
                                    "1.12",
                                    "1.13",
                                    "1.14",
                                    "1.15",
                                    "null"
                                ]
                            }
                        },
                        "2.适用部位": {
                            "type": "array",
                            "items": {
                                "type": "string",
                                "enum": [
                                    "2.1.1",
                                    "2.1.2",
                                    "2.1.3",
                                    "2.2.1",
                                    "2.2.2",
                                    "2.2.3",
                                    "2.2.4",
                                    "2.2.5",
                                    "2.2.6",
                                    "2.3.1",
                                    "2.4.1",
                                    "2.4.2",
                                    "2.5.1",
                                    "2.5.2",
                                    "2.5.3",
                                    "2.5.4",
                                    "2.5.5",
                                    "2.5.6",
                                    "2.6.1",
                                    "2.7.1",
                                    "2.7.2",
                                    "2.8.1",
                                    "2.8.2",
                                    "2.9.1",
                                    "2.9.2",
                                    "null"
                                ]
                            }
                        },
                        "3.服务方式": {
                            "type": "array",
                            "items": {
                                "type": "string",
                                "enum": [
                                    "3.1.1",
                                    "3.1.2",
                                    "3.1.3",
                                    "3.1.4",
                                    "3.2.1",
                                    "3.2.2",
                                    "3.2.3",
                                    "3.2.4",
                                    "3.2.5",
                                    "3.2.6",
                                    "3.2.7",
                                    "3.2.8",
                                    "3.2.9",
                                    "3.2.10",
                                    "3.2.11",
                                    "3.2.12",
                                    "3.2.13",
                                    "3.2.14",
                                    "3.2.15",
                                    "3.3.1",
                                    "3.3.2",
                                    "3.3.3",
                                    "3.3.4",
                                    "3.3.5",
                                    "3.4.1",
                                    "3.4.2",
                                    "3.4.3",
                                    "3.4.4",
                                    "3.4.5",
                                    "3.5.1",
                                    "3.5.2",
                                    "3.5.3",
                                    "3.5.4",
                                    "3.5.5",
                                    "3.6.1",
                                    "3.6.2",
                                    "3.6.3",
                                    "3.7.1",
                                    "3.7.2",
                                    "3.7.3",
                                    "3.7.4",
                                    "3.8.1",
                                    "3.8.2",
                                    "3.8.3",
                                    "3.8.4",
                                    "3.9.1",
                                    "3.9.2",
                                    "3.10.1",
                                    "3.10.2",
                                    "3.10.3",
                                    "3.10.4",
                                    "3.10.5",
                                    "3.10.6",
                                    "3.11.1",
                                    "3.11.2",
                                    "3.11.3",
                                    "3.11.4",
                                    "3.12.1",
                                    "3.12.2",
                                    "null"
                                ]
                            }
                        },
                        "4.服务时长": {
                            "type": "string",
                            "enum": [
                                "(0-30]",
                                "(30-40]",
                                "(40-60]",
                                "(60-80]",
                                "(80-90]",
                                "(90-100]",
                                "(100-120]",
                                "(120-∞]",
                                "null"
                            ]
                        },
                        "5.适用人群": {
                            "type": "string",
                            "enum": [
                                "5.1.1",
                                "5.2.1",
                                "5.2.2",
                                "5.3.1",
                                "5.3.2",
                                "5.4",
                                "null"
                            ]
                        },
                        "6.适用日期/时段": {
                            "type": "string"
                        },
                        "7.非服务类商品": {
                            "type": "string"
                        }
                    },
                    "required": [
                        "1.服务名称",
                        "2.适用部位",
                        "3.服务方式",
                        "4.服务时长",
                        "5.适用人群",
                        "6.适用日期/时段",
                        "7.非服务类商品"
                    ],
                    "additionalProperties": false
                },
                "项目单B": {
                    "type": "object",
                    "properties": {
                        "1.服务名称": {
                            "type": "array",
                            "items": {
                                "type": "string",
                                "enum": [
                                    "1.1",
                                    "1.2",
                                    "1.3",
                                    "1.4",
                                    "1.5",
                                    "1.6",
                                    "1.7",
                                    "1.8",
                                    "1.9",
                                    "1.10",
                                    "1.11",
                                    "1.12",
                                    "1.13",
                                    "1.14",
                                    "1.15",
                                    "null"
                                ]
                            }
                        },
                        "2.适用部位": {
                            "type": "array",
                            "items": {
                                "type": "string",
                                "enum": [
                                    "2.1.1",
                                    "2.1.2",
                                    "2.1.3",
                                    "2.2.1",
                                    "2.2.2",
                                    "2.2.3",
                                    "2.2.4",
                                    "2.2.5",
                                    "2.2.6",
                                    "2.3.1",
                                    "2.4.1",
                                    "2.4.2",
                                    "2.5.1",
                                    "2.5.2",
                                    "2.5.3",
                                    "2.5.4",
                                    "2.5.5",
                                    "2.5.6",
                                    "2.6.1",
                                    "2.7.1",
                                    "2.7.2",
                                    "2.8.1",
                                    "2.8.2",
                                    "2.9.1",
                                    "2.9.2",
                                    "null"
                                ]
                            }
                        },
                        "3.服务方式": {
                            "type": "array",
                            "items": {
                                "type": "string",
                                "enum": [
                                    "3.1.1",
                                    "3.1.2",
                                    "3.1.3",
                                    "3.1.4",
                                    "3.2.1",
                                    "3.2.2",
                                    "3.2.3",
                                    "3.2.4",
                                    "3.2.5",
                                    "3.2.6",
                                    "3.2.7",
                                    "3.2.8",
                                    "3.2.9",
                                    "3.2.10",
                                    "3.2.11",
                                    "3.2.12",
                                    "3.2.13",
                                    "3.2.14",
                                    "3.2.15",
                                    "3.3.1",
                                    "3.3.2",
                                    "3.3.3",
                                    "3.3.4",
                                    "3.3.5",
                                    "3.4.1",
                                    "3.4.2",
                                    "3.4.3",
                                    "3.4.4",
                                    "3.4.5",
                                    "3.5.1",
                                    "3.5.2",
                                    "3.5.3",
                                    "3.5.4",
                                    "3.5.5",
                                    "3.6.1",
                                    "3.6.2",
                                    "3.6.3",
                                    "3.7.1",
                                    "3.7.2",
                                    "3.7.3",
                                    "3.7.4",
                                    "3.8.1",
                                    "3.8.2",
                                    "3.8.3",
                                    "3.8.4",
                                    "3.9.1",
                                    "3.9.2",
                                    "3.10.1",
                                    "3.10.2",
                                    "3.10.3",
                                    "3.10.4",
                                    "3.10.5",
                                    "3.10.6",
                                    "3.11.1",
                                    "3.11.2",
                                    "3.11.3",
                                    "3.11.4",
                                    "3.12.1",
                                    "3.12.2",
                                    "null"
                                ]
                            }
                        },
                        "4.服务时长": {
                            "type": "string",
                            "enum": [
                                "(0-30]",
                                "(30-40]",
                                "(40-60]",
                                "(60-80]",
                                "(80-90]",
                                "(90-100]",
                                "(100-120]",
                                "(120-∞]",
                                "null"
                            ]
                        },
                        "5.适用人群": {
                            "type": "string",
                            "enum": [
                                "5.1.1",
                                "5.2.1",
                                "5.2.2",
                                "5.3.1",
                                "5.3.2",
                                "5.4",
                                "null"
                            ]
                        },
                        "6.适用日期/时段": {
                            "type": "string"
                        },
                        "7.非服务类商品": {
                            "type": "string"
                        }
                    },
                    "required": [
                        "1.服务名称",
                        "2.适用部位",
                        "3.服务方式",
                        "4.服务时长",
                        "5.适用人群",
                        "6.适用日期/时段",
                        "7.非服务类商品"
                    ],
                    "additionalProperties": false
                },
                "匹配结果": {
                    "type": "string",
                    "enum": [
                        "是",
                        "否"
                    ]
                }
            },
            "required": [
                "项目单A",
                "项目单B",
                "匹配结果"
            ],
            "additionalProperties": false
        },
        "no_required_eval_acc_keys": [
            "6.适用日期/时段"
        ],
        "model_response": "```json\n{\n  \"项目单A\": {\n    \"1.服务名称\": [\n      \"1.8\"\n    ],\n    \"2.适用部位\": [\n      \"2.2.6\"\n    ],\n    \"3.服务方式\": [\n      \"null\"\n    ],\n    \"4.服务时长\": \"(0-30]\",\n    \"5.适用人群\": \"5.2.2\",\n    \"6.适用日期/时段\": \"10:00-20:00\",\n    \"7.非服务类商品\": \"null\"\n  },\n  \"项目单B\": {\n    \"1.服务名称\": [\n      \"1.8\"\n    ],\n    \"2.适用部位\": [\n      \"2.2.4\",\n      \"2.2.5\"\n    ],\n    \"3.服务方式\": [\n      \"null\"\n    ],\n    \"4.服务时长\": \"(30-40]\",\n    \"5.适用人群\": \"5.4\",\n    \"6.适用日期/时段\": \"10:00-20:00\",\n    \"7.非服务类商品\": \"null\"\n  },\n  \"匹配结果\": \"否\"\n}\n```"
    },
    {
        "input": "【Background】\n【角色定义】你是一名消费者,你需要充分了解两个商家提供的生活项目并进行比较, 根据关键要素抽取规则和项目匹配规则来判断两个项目是否相同或匹配，并且以结构化数据的形式把两个项目结果展示出来。\n【Requirements】\n\n\n项目单的信息包括：商品标题、项目单详情、有效期、营业时间、适用人数、购买限制等。关键要素包括：服务名称、适用部位、服务方式、服务时长、适用人群、适用日期/时段、非服务类商品。（注意：如果有枚举值需要归类到枚举值，如果该内容在枚举值之外则默认为null；严格按照优先级，获取信息后不再考虑剩余。\"\n    \"1.服务名称，同一项目单可能包含多个项目，需要全部列举（注意：出现好评礼、会员礼所附赠的项目不计入服务名称。例如：“好评一次深层洁净60分钟”，则服务名称为“null”。优先级：商品标题 > 服务功效 > 服务流程/步骤\n     枚举值：\n     1.1深层洁净(收缩毛孔)\n     1.2补水保湿(皮肤清洁、毛孔洗澡)\n     1.3祛痘\n     1.4美白嫩肤\n     1.5淡斑祛斑\n     1.6紧致提拉\n     1.7修复护理\n     1.8脱毛\n     1.9眼部护理\n     1.10肩颈按摩\n     1.11SPA\n     1.12头疗\n     1.13养生调理\n     1.14瘦身纤体\n     1.15美胸美臀\n\n    2.适用部位：和服务名称对应。优先级：商品标题 > 服务功效 > 服务流程/步骤\n     枚举值：\n     2.1深层洁净/补水保湿/祛痘/美白嫩肤/淡斑祛斑/紧致提拉/修复护理：2.1.1面部,2.1.2部分面部,2.1.3背部 \n     2.2脱毛：2.2.1口唇,2.2.2腋下,2.2.3面部,2.2.4手臂,2.2.5腿部,2.2.6私密/比基尼\n     2.3眼部护理：2.3.1眼部 \n     2.4肩颈按摩：2.4.1肩颈,2.4.2肩颈+背 \n     2.5SPA：2.5.1全身,2.5.2肩颈+腰背,2.5.3肩颈+背部+腿部,2.5.4肩颈+腰腹+腿,2.5.5头+肩+颈+背,2.5.6背部 \n     2.6头疗：2.6.1头部\n     2.7养生调理：2.7.1全身(未指明部位),2.7.2局部(非全身，或者指明某个部位) \n     2.8瘦身纤体：2.8.1全身,2.8.2局部塑形 \n     2.9美胸美臀：2.9.1胸部,2.9.2臀部\n    \n    3.服务方式：和服务名称对应。优先级：项目单详情>商品标题\n     枚举值：（注意：1.未提到以下内容的，输出null;2.如果出现2种或者2种以上结果需要都输出）\n     3.1深层洁净：3.1.1)仪器(超微小气泡/大气泡/臭氧泡泡/魔法活氧泡泡) 3.1.2)海菲秀 3.1.3)泥膜/面膜 3.1.4)白牌产品 \n    3.2补水保湿：3.2.1)B5精华 3.2.2)修丽可 3.2.3)日式pola 3.2.4)日式晓姿 3.2.5)赫莲娜HR 3.2.6)伊芙珑evelom 3.2.7)海蓝之谜LA MER 3.2.8)瑞妍cellcosment 3.2.9)莱珀妮 LA PRAIRIE 3.2.10)迪奥DIOR 3.2.11)圣罗兰YSL 3.2.12)诚美DGR 3.2.13)法尔曼VALMONT 3.2.14)菲洛嘉FILORGA 3.2.15)白牌产品\n     3.3祛痘：3.3.1)手工针清/皮铲/护理 3.3.2)点阵激光 3.3.3)红蓝光/PDT光能/烤光 3.3.4)刷酸/果酸 3.3.5)草本 \n     3.4美白嫩肤：3.4.1)焕肤类 3.4.2)氨甲环酸 3.4.3)大牌产品(菲洛嘉) 3.4.4)普牌产品(欧诗漫) 3.4.5)白牌产品 \n     3.5紧致提拉：3.5.1)手法按摩类 3.5.2)抗糖祛黄/生物酶疗 3.5.3)木乃伊紧致 3.5.4)大牌产品(赫莲娜/日式POLA) 3.5.5)白牌产品 \n     3.6修复护理：3.6.1)酵素/乳糖酸/骨胶原/活性酶 3.6.2)大牌产品(赫莲娜/伊芙珑/海蓝之谜/瑞妍/莱珀妮/迪奥/圣罗兰诚美DGR/法尔曼/菲洛嘉) 3.6.3)白牌产品\n     3.7肩颈按摩：3.7.1)使用精油 3.7.2)不使用精油 3.7.3)热石精油 3.7.4)水疗\n     3.8全身SPA：3.8.1)使用精油 3.8.2)不使用精油 3.8.3)热石精油 3.8.4)水疗\n     3.9头疗：3.9.1)使用精油 3.9.2)不使用精油 \n     3.10养生调理：3.10.1)灸类 3.10.2)刮痧 3.10.3)罐类 3.10.4)蒸/浴类 3.10.5)经络/净排类 3.10.6)产后修复类\n     3.11瘦身纤体：3.11.1)针灸/拔罐/经络 3.11.2)刮痧 3.11.3)仪器 3.11.4)调理粉/精油\n     3.12.美胸美臀：3.12.1)使用精油 3.12.2)不使用精油\n\n    4.服务时长，总服务时长(服务项目的服务时长总和)。优先级：商品标题>项目单详情\n    需要映射到枚举值：(0-30]、(30-40]、(40-60]、(60-80]、(80-90]、(90-100]、(100-120]、(120-∞]（输出答案时需要输出具体的枚举值内容）\n\n    5.适用人群，包括性别、年龄、用户类型（出现“XX节”属于营销词，不能作为性别的判断，eg.女神节专属、母亲节，不能判断性别为女性） 优先级：购买限制>商品标题>项目单详情\n     枚举值：（注意：此项优先级：用户类型>性别>年龄，只需输出一个类别）\n     5.1用户类型：5.1.1新客价格（第一次使用该项目的用户）\n     5.2性别：5.2.1男性，5.2.2女性\n     5.3年龄：5.3.1儿童（0-12周岁）,5.3.2成人（18岁以上）\n     5.4不限通用(每人限购1份，不限年龄，性别)\n\n    6.适用日期/时段（注意：全天可用等于商家营业时间可用；闲时指的是周一到周五的下午4点前）  优先级：项目单详情>商品标题>购买须知\n    注意1：项目单详情中信息多处不符一致时，则取最小时段进行对比，eg1.A单适用日期：2025年7月1日-2025年9月1日，周一-周五10:00-19:00可用；B单适用日期2025.7.1-2025.10.1周一到周日10:00-22:00，则AB两单适用日期/时段不一致。eg2.2025年8月1日-2025年8月30日，周一-周五10:00-19:00可用；B单适用日期2025.7.1-2025.10.1周一-周天10:00-19:00可用，则AB两单适用日期/时段一致（不考虑年月日时格式）\n    注意2：适用日期/时段：从营业时间得到信息，仅看“周一-周日”、“xx月xx日-xx月xx日”、“xx:xx-xx:xx”、“xx点-xx点”等类似字眼，无需关注特殊节假日；时段：由“开始时间”和“结束时间”组成，输出具体的时间，例如“10:00-22:00” \n\n    7.非服务类商品：指的是除服务名称以外的内容，eg.“深层洁净60分钟+（含/送/赠）XX面膜2盒”，”非服务商品为“XX面膜，2盒”。如果是仅面膜、产品，零食、皮肤检测等非美容美体产品不算非服务产品，此时输出null。\n\n    8.白牌产品：指的是小厂商生产的没有牌子的商品，白牌是相对品牌而言的。\n\n\n    项目单匹配规则：根据抽取出来的要素和以下规则判断是否为同一项目单“注意：如果无法识别出来则默认为null”\n     1.服务名称：需完全一致，否则认为两个项目单不一致(不考虑顺序)。\n     2.适用部位：需完全一致，否则认为两个项目单不一致(不考虑顺序)。\n     3.服务方式：任意一方有值另一方空值，不可以视为一致。需要两侧都有值进行判断是否一致。\n     4.服务时长：如果任意一方有值另一方空值，可以视为一致。但当双方都有值时，双方时长一致才算一致。\n     5.适用人群：性别、年龄、用户类型要完全一样才算一致，如果任意一方空值则默认为“不限通用”，随后再对比出结果。\n     6.适用日期/时段：\n      1)当只有适用日期（年月日）时，日期精确到年月日相同则认为一致，eg.A单适用日期：2025年7月1日-2025年10月1日；B单适用日期2025.7.1-2025.10.1，则AB两单适用日期一致。（不考虑年月日格式）\n      2)当任意一方“适用日期”为空值，则取适用时段或者运营时间进行比较，AB两单之间起始及终止时间相差为1小时以内，可视为一致，超过1小时则为不一致。\n     7.非服务类商品：\n      1)纯非服务类商品，无需参与匹配。\n      2)若出现服务名称+非服务产品，针对服务内容按照规则匹配；非服务类商品需精准匹配，内容具体到名称+规格或者单位或者品牌。eg.“深层洁净60分钟+（含/送/赠）XX面膜2盒”，”非服务商品为“2盒XX面膜”\n    判断步骤：\n     1. 根据输入的项目单信息和规则抽取相应的要素，以及输出对应的枚举值内容\n     2. 根据抽取要素、枚举值内容和匹配规则来判断两个项目单是否匹配\n     \n     \n\n【Input】 \n8.项目单A:{'商品标题': '60分钟肌肤净透丨360肌底清洁+刮痧活肤+肤保湿', '图文详情': '本优惠活动新客体验价，同1顾客使用多ID重复多拍同1个项目单视为无效，门店有权拒绝接待！，温馨提示：宝子们，为保证您到店就能享受美美的护肤体验，购买优惠卷后记得拨打电话提前预约哦！优惠券的服务项目和详情仅供参考，具体以实物为准，因为店长会根据您的皮肤状态做对应的调整，更贴合您的护理需求哦！繁忙时候，同行多人到店可能会遇上位置不够的情况，请您多担待等候一下下哦！', '有效期': '', '适用人数': '每张优惠券最多1人使用', '规则提醒': '不再与其他优惠同享', '购买限制': '只适用于初次到店非商户会员使用', '营业时间': '周一至周日10:00-21:00', '项目单详情': [{'名称': '360 肌底清洁+细胞水氧', '分类': '皮肤管理', '二级分类': '其他深层清洁', '服务功效': '补水保湿、深层清洁', '适用部位': '全面部', '服务次数': '', '服务时长': '60', '适用性别': '男女不限', '服务亮点': '', '服务流程': '', '服务步骤': [{'产品': '', '说明': '多维度检测皮肤 油脂 水分 皮下肌肤问题', '名称': '皮肤检测', '设备': '智能定向检测', '二级名称': '皮肤检测', '时长': '10', '部位': '全面部'}, {'产品': '植物萃取卸妆水平衡洁面乳氨基酸', '说明': '温和卸妆，微米绵密气泡深层洁净', '名称': '卸妆洁面', '设备': '', '二级名称': '卸妆洁面', '时长': '5', '部位': '全面部'}, {'产品': '湿敷清透嫩肤精华液', '说明': '热胀冷缩原理 舒张毛孔 软化顽固黑头及油脂', '名称': '面部清洁', '设备': '纳米离子仪热喷', '二级名称': '毛孔舒张', '时长': '5', '部位': 'T区、鼻部'}, {'产品': '', '说明': '利用负压吸力吸附肌肤深处堵塞物及油脂', '名称': '面部清洁', '设备': '毛孔透析仪', '二级名称': '深层清洁', '时长': '5', '部位': 'T区、鼻部'}, {'产品': '清透水润靓肤膜', '说明': '加速面部微循环 疏通毛孔 舒缓放松面部', '名称': '面部清洁', '设备': '刮痧板', '二级名称': '深层清洁', '时长': '8', '部位': '全面部'}, {'产品': '清透细肤精华液', '说明': '收缩毛孔 舒缓镇静', '名称': '面部清洁', '设备': '海蓝之星 冰导仪', '二级名称': '收缩毛孔', '时长': '5', '部位': '全面部'}, {'产品': '郑一生精华', '说明': '雾化分子量 深层灌溉肌肤 水汪汪肌肤', '名称': '补水保湿', '设备': '海蓝之星注氧仪', '二级名称': '水氧活肤', '时长': '3', '部位': '全面部'}, {'产品': '补水面膜', '说明': '敷补水面膜 促进精华液吸收 补水保湿', '名称': '补水保湿', '设备': '', '二级名称': '深层补水', '时长': '14', '部位': '全面部'}, {'产品': '郑一生水 精华 乳 霜全套护肤', '说明': '保湿锁水 防晒 加强防护', '名称': '收尾步骤', '设备': '', '二级名称': '保湿防晒', '时长': '5', '部位': '全面部'}], '店铺福利': '茶水、甜品'}]} 项目单B:{'商品标题': '【夏日宠粉】超润沁透啵啵肌 沁透补水（60分钟专享）', '营业时间': '10:00-21:00', '服务功效': '补水保湿', '适用性别': '不限', '适用部位': '全脸部', '服务时长': '60分钟', '有效期': '购买后180天有效', '可用时间': '商家营业时间可用', '购买限制': '每人限购3份', '适用人数': '每张优惠券限1人使用', '其他规则': '单次消费最多使用1张优惠券;不与店内优惠同享;发票问题请询问商家;单次消费最多使用1张优惠券；;为避免到店等待，购买后请及时提前致电客服预约确认到店时间；;因为每个人的情况不一样，具体的操作流程可能会和门店有所出入；;预约时间：9:00~21:00；', '项目单详情': [{'名称': '超润沁透啵啵肌', '分类': '超润沁透啵啵肌', '部位': '', '时长': '60分钟', '服务流程': '皮肤检测全脸部;微米绵密气泡洁净全脸部;离子仪热喷全脸部;水动力轻氧全脸部;焕颜柔肤护理全脸部;0°舒缓护理全脸部;小水库水分灌注全脸部;水润面膜护理全脸部;基础护肤全脸部', '附赠服务': ''}]}\n\n\n\n【Output Requirement】\n 你的输出必须满足以下JSON_SCHEMA{'$schema': 'http://json-schema.org/draft-07/schema#', 'type': 'object', 'properties': {'项目单A': {'type': 'object', 'properties': {'1.服务名称': {'type': 'array', 'items': {'type': 'string', 'enum': ['1.1', '1.2', '1.3', '1.4', '1.5', '1.6', '1.7', '1.8', '1.9', '1.10', '1.11', '1.12', '1.13', '1.14', '1.15', 'null']}}, '2.适用部位': {'type': 'array', 'items': {'type': 'string', 'enum': ['2.1.1', '2.1.2', '2.1.3', '2.2.1', '2.2.2', '2.2.3', '2.2.4', '2.2.5', '2.2.6', '2.3.1', '2.4.1', '2.4.2', '2.5.1', '2.5.2', '2.5.3', '2.5.4', '2.5.5', '2.5.6', '2.6.1', '2.7.1', '2.7.2', '2.8.1', '2.8.2', '2.9.1', '2.9.2', 'null']}}, '3.服务方式': {'type': 'array', 'items': {'type': 'string', 'enum': ['3.1.1', '3.1.2', '3.1.3', '3.1.4', '3.2.1', '3.2.2', '3.2.3', '3.2.4', '3.2.5', '3.2.6', '3.2.7', '3.2.8', '3.2.9', '3.2.10', '3.2.11', '3.2.12', '3.2.13', '3.2.14', '3.2.15', '3.3.1', '3.3.2', '3.3.3', '3.3.4', '3.3.5', '3.4.1', '3.4.2', '3.4.3', '3.4.4', '3.4.5', '3.5.1', '3.5.2', '3.5.3', '3.5.4', '3.5.5', '3.6.1', '3.6.2', '3.6.3', '3.7.1', '3.7.2', '3.7.3', '3.7.4', '3.8.1', '3.8.2', '3.8.3', '3.8.4', '3.9.1', '3.9.2', '3.10.1', '3.10.2', '3.10.3', '3.10.4', '3.10.5', '3.10.6', '3.11.1', '3.11.2', '3.11.3', '3.11.4', '3.12.1', '3.12.2', 'null']}}, '4.服务时长': {'type': 'string', 'enum': ['(0-30]', '(30-40]', '(40-60]', '(60-80]', '(80-90]', '(90-100]', '(100-120]', '(120-∞]', 'null']}, '5.适用人群': {'type': 'string', 'enum': ['5.1.1', '5.2.1', '5.2.2', '5.3.1', '5.3.2', '5.4', 'null']}, '6.适用日期/时段': {'type': 'string'}, '7.非服务类商品': {'type': 'string'}}, 'required': ['1.服务名称', '2.适用部位', '3.服务方式', '4.服务时长', '5.适用人群', '6.适用日期/时段', '7.非服务类商品'], 'additionalProperties': False}, '项目单B': {'type': 'object', 'properties': {'1.服务名称': {'type': 'array', 'items': {'type': 'string', 'enum': ['1.1', '1.2', '1.3', '1.4', '1.5', '1.6', '1.7', '1.8', '1.9', '1.10', '1.11', '1.12', '1.13', '1.14', '1.15', 'null']}}, '2.适用部位': {'type': 'array', 'items': {'type': 'string', 'enum': ['2.1.1', '2.1.2', '2.1.3', '2.2.1', '2.2.2', '2.2.3', '2.2.4', '2.2.5', '2.2.6', '2.3.1', '2.4.1', '2.4.2', '2.5.1', '2.5.2', '2.5.3', '2.5.4', '2.5.5', '2.5.6', '2.6.1', '2.7.1', '2.7.2', '2.8.1', '2.8.2', '2.9.1', '2.9.2', 'null']}}, '3.服务方式': {'type': 'array', 'items': {'type': 'string', 'enum': ['3.1.1', '3.1.2', '3.1.3', '3.1.4', '3.2.1', '3.2.2', '3.2.3', '3.2.4', '3.2.5', '3.2.6', '3.2.7', '3.2.8', '3.2.9', '3.2.10', '3.2.11', '3.2.12', '3.2.13', '3.2.14', '3.2.15', '3.3.1', '3.3.2', '3.3.3', '3.3.4', '3.3.5', '3.4.1', '3.4.2', '3.4.3', '3.4.4', '3.4.5', '3.5.1', '3.5.2', '3.5.3', '3.5.4', '3.5.5', '3.6.1', '3.6.2', '3.6.3', '3.7.1', '3.7.2', '3.7.3', '3.7.4', '3.8.1', '3.8.2', '3.8.3', '3.8.4', '3.9.1', '3.9.2', '3.10.1', '3.10.2', '3.10.3', '3.10.4', '3.10.5', '3.10.6', '3.11.1', '3.11.2', '3.11.3', '3.11.4', '3.12.1', '3.12.2', 'null']}}, '4.服务时长': {'type': 'string', 'enum': ['(0-30]', '(30-40]', '(40-60]', '(60-80]', '(80-90]', '(90-100]', '(100-120]', '(120-∞]', 'null']}, '5.适用人群': {'type': 'string', 'enum': ['5.1.1', '5.2.1', '5.2.2', '5.3.1', '5.3.2', '5.4', 'null']}, '6.适用日期/时段': {'type': 'string'}, '7.非服务类商品': {'type': 'string'}}, 'required': ['1.服务名称', '2.适用部位', '3.服务方式', '4.服务时长', '5.适用人群', '6.适用日期/时段', '7.非服务类商品'], 'additionalProperties': False}, '匹配结果': {'type': 'string', 'enum': ['是', '否']}}, 'required': ['项目单A', '项目单B', '匹配结果'], 'additionalProperties': False}",
        "target": {
            "项目单A": {
                "1.服务名称": [
                    "1.1",
                    "1.2"
                ],
                "2.适用部位": [
                    "2.1.1"
                ],
                "3.服务方式": [
                    "3.1.1",
                    "3.1.3",
                    "3.2.15"
                ],
                "4.服务时长": "(40-60]",
                "5.适用人群": "5.1.1",
                "6.适用日期/时段": "周一至周日10:00-21:00",
                "7.非服务类商品": "null"
            },
            "项目单B": {
                "1.服务名称": [
                    "1.2"
                ],
                "2.适用部位": [
                    "2.1.1"
                ],
                "3.服务方式": [
                    "3.2.15"
                ],
                "4.服务时长": "(40-60]",
                "5.适用人群": "5.4",
                "6.适用日期/时段": "10:00-21:00",
                "7.非服务类商品": "null"
            },
            "匹配结果": "否"
        },
        "json_schema": {
            "$schema": "http://json-schema.org/draft-07/schema#",
            "type": "object",
            "properties": {
                "项目单A": {
                    "type": "object",
                    "properties": {
                        "1.服务名称": {
                            "type": "array",
                            "items": {
                                "type": "string",
                                "enum": [
                                    "1.1",
                                    "1.2",
                                    "1.3",
                                    "1.4",
                                    "1.5",
                                    "1.6",
                                    "1.7",
                                    "1.8",
                                    "1.9",
                                    "1.10",
                                    "1.11",
                                    "1.12",
                                    "1.13",
                                    "1.14",
                                    "1.15",
                                    "null"
                                ]
                            }
                        },
                        "2.适用部位": {
                            "type": "array",
                            "items": {
                                "type": "string",
                                "enum": [
                                    "2.1.1",
                                    "2.1.2",
                                    "2.1.3",
                                    "2.2.1",
                                    "2.2.2",
                                    "2.2.3",
                                    "2.2.4",
                                    "2.2.5",
                                    "2.2.6",
                                    "2.3.1",
                                    "2.4.1",
                                    "2.4.2",
                                    "2.5.1",
                                    "2.5.2",
                                    "2.5.3",
                                    "2.5.4",
                                    "2.5.5",
                                    "2.5.6",
                                    "2.6.1",
                                    "2.7.1",
                                    "2.7.2",
                                    "2.8.1",
                                    "2.8.2",
                                    "2.9.1",
                                    "2.9.2",
                                    "null"
                                ]
                            }
                        },
                        "3.服务方式": {
                            "type": "array",
                            "items": {
                                "type": "string",
                                "enum": [
                                    "3.1.1",
                                    "3.1.2",
                                    "3.1.3",
                                    "3.1.4",
                                    "3.2.1",
                                    "3.2.2",
                                    "3.2.3",
                                    "3.2.4",
                                    "3.2.5",
                                    "3.2.6",
                                    "3.2.7",
                                    "3.2.8",
                                    "3.2.9",
                                    "3.2.10",
                                    "3.2.11",
                                    "3.2.12",
                                    "3.2.13",
                                    "3.2.14",
                                    "3.2.15",
                                    "3.3.1",
                                    "3.3.2",
                                    "3.3.3",
                                    "3.3.4",
                                    "3.3.5",
                                    "3.4.1",
                                    "3.4.2",
                                    "3.4.3",
                                    "3.4.4",
                                    "3.4.5",
                                    "3.5.1",
                                    "3.5.2",
                                    "3.5.3",
                                    "3.5.4",
                                    "3.5.5",
                                    "3.6.1",
                                    "3.6.2",
                                    "3.6.3",
                                    "3.7.1",
                                    "3.7.2",
                                    "3.7.3",
                                    "3.7.4",
                                    "3.8.1",
                                    "3.8.2",
                                    "3.8.3",
                                    "3.8.4",
                                    "3.9.1",
                                    "3.9.2",
                                    "3.10.1",
                                    "3.10.2",
                                    "3.10.3",
                                    "3.10.4",
                                    "3.10.5",
                                    "3.10.6",
                                    "3.11.1",
                                    "3.11.2",
                                    "3.11.3",
                                    "3.11.4",
                                    "3.12.1",
                                    "3.12.2",
                                    "null"
                                ]
                            }
                        },
                        "4.服务时长": {
                            "type": "string",
                            "enum": [
                                "(0-30]",
                                "(30-40]",
                                "(40-60]",
                                "(60-80]",
                                "(80-90]",
                                "(90-100]",
                                "(100-120]",
                                "(120-∞]",
                                "null"
                            ]
                        },
                        "5.适用人群": {
                            "type": "string",
                            "enum": [
                                "5.1.1",
                                "5.2.1",
                                "5.2.2",
                                "5.3.1",
                                "5.3.2",
                                "5.4",
                                "null"
                            ]
                        },
                        "6.适用日期/时段": {
                            "type": "string"
                        },
                        "7.非服务类商品": {
                            "type": "string"
                        }
                    },
                    "required": [
                        "1.服务名称",
                        "2.适用部位",
                        "3.服务方式",
                        "4.服务时长",
                        "5.适用人群",
                        "6.适用日期/时段",
                        "7.非服务类商品"
                    ],
                    "additionalProperties": false
                },
                "项目单B": {
                    "type": "object",
                    "properties": {
                        "1.服务名称": {
                            "type": "array",
                            "items": {
                                "type": "string",
                                "enum": [
                                    "1.1",
                                    "1.2",
                                    "1.3",
                                    "1.4",
                                    "1.5",
                                    "1.6",
                                    "1.7",
                                    "1.8",
                                    "1.9",
                                    "1.10",
                                    "1.11",
                                    "1.12",
                                    "1.13",
                                    "1.14",
                                    "1.15",
                                    "null"
                                ]
                            }
                        },
                        "2.适用部位": {
                            "type": "array",
                            "items": {
                                "type": "string",
                                "enum": [
                                    "2.1.1",
                                    "2.1.2",
                                    "2.1.3",
                                    "2.2.1",
                                    "2.2.2",
                                    "2.2.3",
                                    "2.2.4",
                                    "2.2.5",
                                    "2.2.6",
                                    "2.3.1",
                                    "2.4.1",
                                    "2.4.2",
                                    "2.5.1",
                                    "2.5.2",
                                    "2.5.3",
                                    "2.5.4",
                                    "2.5.5",
                                    "2.5.6",
                                    "2.6.1",
                                    "2.7.1",
                                    "2.7.2",
                                    "2.8.1",
                                    "2.8.2",
                                    "2.9.1",
                                    "2.9.2",
                                    "null"
                                ]
                            }
                        },
                        "3.服务方式": {
                            "type": "array",
                            "items": {
                                "type": "string",
                                "enum": [
                                    "3.1.1",
                                    "3.1.2",
                                    "3.1.3",
                                    "3.1.4",
                                    "3.2.1",
                                    "3.2.2",
                                    "3.2.3",
                                    "3.2.4",
                                    "3.2.5",
                                    "3.2.6",
                                    "3.2.7",
                                    "3.2.8",
                                    "3.2.9",
                                    "3.2.10",
                                    "3.2.11",
                                    "3.2.12",
                                    "3.2.13",
                                    "3.2.14",
                                    "3.2.15",
                                    "3.3.1",
                                    "3.3.2",
                                    "3.3.3",
                                    "3.3.4",
                                    "3.3.5",
                                    "3.4.1",
                                    "3.4.2",
                                    "3.4.3",
                                    "3.4.4",
                                    "3.4.5",
                                    "3.5.1",
                                    "3.5.2",
                                    "3.5.3",
                                    "3.5.4",
                                    "3.5.5",
                                    "3.6.1",
                                    "3.6.2",
                                    "3.6.3",
                                    "3.7.1",
                                    "3.7.2",
                                    "3.7.3",
                                    "3.7.4",
                                    "3.8.1",
                                    "3.8.2",
                                    "3.8.3",
                                    "3.8.4",
                                    "3.9.1",
                                    "3.9.2",
                                    "3.10.1",
                                    "3.10.2",
                                    "3.10.3",
                                    "3.10.4",
                                    "3.10.5",
                                    "3.10.6",
                                    "3.11.1",
                                    "3.11.2",
                                    "3.11.3",
                                    "3.11.4",
                                    "3.12.1",
                                    "3.12.2",
                                    "null"
                                ]
                            }
                        },
                        "4.服务时长": {
                            "type": "string",
                            "enum": [
                                "(0-30]",
                                "(30-40]",
                                "(40-60]",
                                "(60-80]",
                                "(80-90]",
                                "(90-100]",
                                "(100-120]",
                                "(120-∞]",
                                "null"
                            ]
                        },
                        "5.适用人群": {
                            "type": "string",
                            "enum": [
                                "5.1.1",
                                "5.2.1",
                                "5.2.2",
                                "5.3.1",
                                "5.3.2",
                                "5.4",
                                "null"
                            ]
                        },
                        "6.适用日期/时段": {
                            "type": "string"
                        },
                        "7.非服务类商品": {
                            "type": "string"
                        }
                    },
                    "required": [
                        "1.服务名称",
                        "2.适用部位",
                        "3.服务方式",
                        "4.服务时长",
                        "5.适用人群",
                        "6.适用日期/时段",
                        "7.非服务类商品"
                    ],
                    "additionalProperties": false
                },
                "匹配结果": {
                    "type": "string",
                    "enum": [
                        "是",
                        "否"
                    ]
                }
            },
            "required": [
                "项目单A",
                "项目单B",
                "匹配结果"
            ],
            "additionalProperties": false
        },
        "no_required_eval_acc_keys": [
            "6.适用日期/时段"
        ],
        "model_response": "```json\n{\n    \"项目单A\": {\n        \"1.服务名称\": [\"1.1\", \"1.2\"],\n        \"2.适用部位\": [\"2.1.1\"],\n        \"3.服务方式\": [\"3.1.1\", \"3.2.15\"],\n        \"4.服务时长\": \"(60-80]\",\n        \"5.适用人群\": \"5.1.1\",\n        \"6.适用日期/时段\": \"10:00-21:00\",\n        \"7.非服务类商品\": \"null\"\n    },\n    \"项目单B\": {\n        \"1.服务名称\": [\"1.2\"],\n        \"2.适用部位\": [\"2.1.1\"],\n        \"3.服务方式\": [\"3.1.1\"],\n        \"4.服务时长\": \"(60-80]\",\n        \"5.适用人群\": \"5.4\",\n        \"6.适用日期/时段\": \"10:00-21:00\",\n        \"7.非服务类商品\": \"null\"\n    },\n    \"匹配结果\": \"否\"\n}\n```"
    },
    {
        "input": "【Background】\n【角色定义】你是一名消费者,你需要充分了解两个商家提供的生活项目并进行比较, 根据关键要素抽取规则和项目匹配规则来判断两个项目是否相同或匹配，并且以结构化数据的形式把两个项目结果展示出来。\n【Requirements】\n\n\n项目单的信息包括：商品标题、项目单详情、有效期、营业时间、适用人数、购买限制等。关键要素包括：服务名称、适用部位、服务方式、服务时长、适用人群、适用日期/时段、非服务类商品。（注意：如果有枚举值需要归类到枚举值，如果该内容在枚举值之外则默认为null；严格按照优先级，获取信息后不再考虑剩余。\"\n    \"1.服务名称，同一项目单可能包含多个项目，需要全部列举（注意：出现好评礼、会员礼所附赠的项目不计入服务名称。例如：“好评一次深层洁净60分钟”，则服务名称为“null”。优先级：商品标题 > 服务功效 > 服务流程/步骤\n     枚举值：\n     1.1深层洁净(收缩毛孔)\n     1.2补水保湿(皮肤清洁、毛孔洗澡)\n     1.3祛痘\n     1.4美白嫩肤\n     1.5淡斑祛斑\n     1.6紧致提拉\n     1.7修复护理\n     1.8脱毛\n     1.9眼部护理\n     1.10肩颈按摩\n     1.11SPA\n     1.12头疗\n     1.13养生调理\n     1.14瘦身纤体\n     1.15美胸美臀\n\n    2.适用部位：和服务名称对应。优先级：商品标题 > 服务功效 > 服务流程/步骤\n     枚举值：\n     2.1深层洁净/补水保湿/祛痘/美白嫩肤/淡斑祛斑/紧致提拉/修复护理：2.1.1面部,2.1.2部分面部,2.1.3背部 \n     2.2脱毛：2.2.1口唇,2.2.2腋下,2.2.3面部,2.2.4手臂,2.2.5腿部,2.2.6私密/比基尼\n     2.3眼部护理：2.3.1眼部 \n     2.4肩颈按摩：2.4.1肩颈,2.4.2肩颈+背 \n     2.5SPA：2.5.1全身,2.5.2肩颈+腰背,2.5.3肩颈+背部+腿部,2.5.4肩颈+腰腹+腿,2.5.5头+肩+颈+背,2.5.6背部 \n     2.6头疗：2.6.1头部\n     2.7养生调理：2.7.1全身(未指明部位),2.7.2局部(非全身，或者指明某个部位) \n     2.8瘦身纤体：2.8.1全身,2.8.2局部塑形 \n     2.9美胸美臀：2.9.1胸部,2.9.2臀部\n    \n    3.服务方式：和服务名称对应。优先级：项目单详情>商品标题\n     枚举值：（注意：1.未提到以下内容的，输出null;2.如果出现2种或者2种以上结果需要都输出）\n     3.1深层洁净：3.1.1)仪器(超微小气泡/大气泡/臭氧泡泡/魔法活氧泡泡) 3.1.2)海菲秀 3.1.3)泥膜/面膜 3.1.4)白牌产品 \n    3.2补水保湿：3.2.1)B5精华 3.2.2)修丽可 3.2.3)日式pola 3.2.4)日式晓姿 3.2.5)赫莲娜HR 3.2.6)伊芙珑evelom 3.2.7)海蓝之谜LA MER 3.2.8)瑞妍cellcosment 3.2.9)莱珀妮 LA PRAIRIE 3.2.10)迪奥DIOR 3.2.11)圣罗兰YSL 3.2.12)诚美DGR 3.2.13)法尔曼VALMONT 3.2.14)菲洛嘉FILORGA 3.2.15)白牌产品\n     3.3祛痘：3.3.1)手工针清/皮铲/护理 3.3.2)点阵激光 3.3.3)红蓝光/PDT光能/烤光 3.3.4)刷酸/果酸 3.3.5)草本 \n     3.4美白嫩肤：3.4.1)焕肤类 3.4.2)氨甲环酸 3.4.3)大牌产品(菲洛嘉) 3.4.4)普牌产品(欧诗漫) 3.4.5)白牌产品 \n     3.5紧致提拉：3.5.1)手法按摩类 3.5.2)抗糖祛黄/生物酶疗 3.5.3)木乃伊紧致 3.5.4)大牌产品(赫莲娜/日式POLA) 3.5.5)白牌产品 \n     3.6修复护理：3.6.1)酵素/乳糖酸/骨胶原/活性酶 3.6.2)大牌产品(赫莲娜/伊芙珑/海蓝之谜/瑞妍/莱珀妮/迪奥/圣罗兰诚美DGR/法尔曼/菲洛嘉) 3.6.3)白牌产品\n     3.7肩颈按摩：3.7.1)使用精油 3.7.2)不使用精油 3.7.3)热石精油 3.7.4)水疗\n     3.8全身SPA：3.8.1)使用精油 3.8.2)不使用精油 3.8.3)热石精油 3.8.4)水疗\n     3.9头疗：3.9.1)使用精油 3.9.2)不使用精油 \n     3.10养生调理：3.10.1)灸类 3.10.2)刮痧 3.10.3)罐类 3.10.4)蒸/浴类 3.10.5)经络/净排类 3.10.6)产后修复类\n     3.11瘦身纤体：3.11.1)针灸/拔罐/经络 3.11.2)刮痧 3.11.3)仪器 3.11.4)调理粉/精油\n     3.12.美胸美臀：3.12.1)使用精油 3.12.2)不使用精油\n\n    4.服务时长，总服务时长(服务项目的服务时长总和)。优先级：商品标题>项目单详情\n    需要映射到枚举值：(0-30]、(30-40]、(40-60]、(60-80]、(80-90]、(90-100]、(100-120]、(120-∞]（输出答案时需要输出具体的枚举值内容）\n\n    5.适用人群，包括性别、年龄、用户类型（出现“XX节”属于营销词，不能作为性别的判断，eg.女神节专属、母亲节，不能判断性别为女性） 优先级：购买限制>商品标题>项目单详情\n     枚举值：（注意：此项优先级：用户类型>性别>年龄，只需输出一个类别）\n     5.1用户类型：5.1.1新客价格（第一次使用该项目的用户）\n     5.2性别：5.2.1男性，5.2.2女性\n     5.3年龄：5.3.1儿童（0-12周岁）,5.3.2成人（18岁以上）\n     5.4不限通用(每人限购1份，不限年龄，性别)\n\n    6.适用日期/时段（注意：全天可用等于商家营业时间可用；闲时指的是周一到周五的下午4点前）  优先级：项目单详情>商品标题>购买须知\n    注意1：项目单详情中信息多处不符一致时，则取最小时段进行对比，eg1.A单适用日期：2025年7月1日-2025年9月1日，周一-周五10:00-19:00可用；B单适用日期2025.7.1-2025.10.1周一到周日10:00-22:00，则AB两单适用日期/时段不一致。eg2.2025年8月1日-2025年8月30日，周一-周五10:00-19:00可用；B单适用日期2025.7.1-2025.10.1周一-周天10:00-19:00可用，则AB两单适用日期/时段一致（不考虑年月日时格式）\n    注意2：适用日期/时段：从营业时间得到信息，仅看“周一-周日”、“xx月xx日-xx月xx日”、“xx:xx-xx:xx”、“xx点-xx点”等类似字眼，无需关注特殊节假日；时段：由“开始时间”和“结束时间”组成，输出具体的时间，例如“10:00-22:00” \n\n    7.非服务类商品：指的是除服务名称以外的内容，eg.“深层洁净60分钟+（含/送/赠）XX面膜2盒”，”非服务商品为“XX面膜，2盒”。如果是仅面膜、产品，零食、皮肤检测等非美容美体产品不算非服务产品，此时输出null。\n\n    8.白牌产品：指的是小厂商生产的没有牌子的商品，白牌是相对品牌而言的。\n\n\n    项目单匹配规则：根据抽取出来的要素和以下规则判断是否为同一项目单“注意：如果无法识别出来则默认为null”\n     1.服务名称：需完全一致，否则认为两个项目单不一致(不考虑顺序)。\n     2.适用部位：需完全一致，否则认为两个项目单不一致(不考虑顺序)。\n     3.服务方式：任意一方有值另一方空值，不可以视为一致。需要两侧都有值进行判断是否一致。\n     4.服务时长：如果任意一方有值另一方空值，可以视为一致。但当双方都有值时，双方时长一致才算一致。\n     5.适用人群：性别、年龄、用户类型要完全一样才算一致，如果任意一方空值则默认为“不限通用”，随后再对比出结果。\n     6.适用日期/时段：\n      1)当只有适用日期（年月日）时，日期精确到年月日相同则认为一致，eg.A单适用日期：2025年7月1日-2025年10月1日；B单适用日期2025.7.1-2025.10.1，则AB两单适用日期一致。（不考虑年月日格式）\n      2)当任意一方“适用日期”为空值，则取适用时段或者运营时间进行比较，AB两单之间起始及终止时间相差为1小时以内，可视为一致，超过1小时则为不一致。\n     7.非服务类商品：\n      1)纯非服务类商品，无需参与匹配。\n      2)若出现服务名称+非服务产品，针对服务内容按照规则匹配；非服务类商品需精准匹配，内容具体到名称+规格或者单位或者品牌。eg.“深层洁净60分钟+（含/送/赠）XX面膜2盒”，”非服务商品为“2盒XX面膜”\n    判断步骤：\n     1. 根据输入的项目单信息和规则抽取相应的要素，以及输出对应的枚举值内容\n     2. 根据抽取要素、枚举值内容和匹配规则来判断两个项目单是否匹配\n     \n     \n\n【Input】 \n9.项目单A:{'商品标题': '【只做肚子】平坦小肚子深度养护套餐', '图文详情': '平坦小肚子深度养护套餐', '有效期': '购买之日起30天内有效，随时退，过期退', '适用人数': '每张优惠券最多1人使用', '规则提醒': '可与其他优惠同享', '购买限制': '每人不限购买次数，不限会员使用', '营业时间': '周一至周六09:00-21:00', '项目单详情': [{'名称': '【只做肚子】', '分类': '瘦身塑形', '二级分类': '', '服务功效': '', '适用部位': '腹部', '服务次数': '1', '服务时长': '', '适用性别': '女', '服务亮点': '', '服务流程': '', '服务步骤': [{'产品': '', '类型': '定制方案', '名称': '1对1身材分析', '时长': '5min', '设备': ''}, {'产品': '', '类型': '瘦身塑形', '名称': '专业手法+腹部热敷膏', '时长': '30min', '设备': ''}, {'产品': '', '类型': '其他', '名称': '腹部热敷膏4盒', '时长': '0min', '设备': ''}], '服务附赠': ''}]} 项目单B:{'商品标题': '【只做背] 】迷人美背深度养护套餐', '营业时间': '09:00-21:00', '服务功效': '改善厚背，变美人背', '适用性别': 'null', '适用部位': '背部', '有效期': '购买后360天内有效', '可用时间': '商家营业时间可用', '购买限制': '每单最多买1份', '适用人数': '可与店内部分优惠同享，详询商家;每张次卡最多1人使用;每次到店最多使用1次;发票问题请询问商家;温馨提示：由于行业特殊，暂不接待男士。该项目单总共4盒，分两次核销。 ', '项目单详情': [{'名称': '美背热敷膏4盒', '分类': '', '部位': '背部专用', '时长': '0', '服务流程': '', '附赠服务': ''}, {'名称': '1对1身材咨询', '分类': '', '部位': '', '时长': '10分钟', '服务流程': '', '附赠服务': ''}, {'名称': '迷人美背深度养护套餐', '分类': '', '部位': '', '时长': '0', '服务流程': '', '附赠服务': ''}]}\n\n\n\n【Output Requirement】\n 你的输出必须满足以下JSON_SCHEMA{'$schema': 'http://json-schema.org/draft-07/schema#', 'type': 'object', 'properties': {'项目单A': {'type': 'object', 'properties': {'1.服务名称': {'type': 'array', 'items': {'type': 'string', 'enum': ['1.1', '1.2', '1.3', '1.4', '1.5', '1.6', '1.7', '1.8', '1.9', '1.10', '1.11', '1.12', '1.13', '1.14', '1.15', 'null']}}, '2.适用部位': {'type': 'array', 'items': {'type': 'string', 'enum': ['2.1.1', '2.1.2', '2.1.3', '2.2.1', '2.2.2', '2.2.3', '2.2.4', '2.2.5', '2.2.6', '2.3.1', '2.4.1', '2.4.2', '2.5.1', '2.5.2', '2.5.3', '2.5.4', '2.5.5', '2.5.6', '2.6.1', '2.7.1', '2.7.2', '2.8.1', '2.8.2', '2.9.1', '2.9.2', 'null']}}, '3.服务方式': {'type': 'array', 'items': {'type': 'string', 'enum': ['3.1.1', '3.1.2', '3.1.3', '3.1.4', '3.2.1', '3.2.2', '3.2.3', '3.2.4', '3.2.5', '3.2.6', '3.2.7', '3.2.8', '3.2.9', '3.2.10', '3.2.11', '3.2.12', '3.2.13', '3.2.14', '3.2.15', '3.3.1', '3.3.2', '3.3.3', '3.3.4', '3.3.5', '3.4.1', '3.4.2', '3.4.3', '3.4.4', '3.4.5', '3.5.1', '3.5.2', '3.5.3', '3.5.4', '3.5.5', '3.6.1', '3.6.2', '3.6.3', '3.7.1', '3.7.2', '3.7.3', '3.7.4', '3.8.1', '3.8.2', '3.8.3', '3.8.4', '3.9.1', '3.9.2', '3.10.1', '3.10.2', '3.10.3', '3.10.4', '3.10.5', '3.10.6', '3.11.1', '3.11.2', '3.11.3', '3.11.4', '3.12.1', '3.12.2', 'null']}}, '4.服务时长': {'type': 'string', 'enum': ['(0-30]', '(30-40]', '(40-60]', '(60-80]', '(80-90]', '(90-100]', '(100-120]', '(120-∞]', 'null']}, '5.适用人群': {'type': 'string', 'enum': ['5.1.1', '5.2.1', '5.2.2', '5.3.1', '5.3.2', '5.4', 'null']}, '6.适用日期/时段': {'type': 'string'}, '7.非服务类商品': {'type': 'string'}}, 'required': ['1.服务名称', '2.适用部位', '3.服务方式', '4.服务时长', '5.适用人群', '6.适用日期/时段', '7.非服务类商品'], 'additionalProperties': False}, '项目单B': {'type': 'object', 'properties': {'1.服务名称': {'type': 'array', 'items': {'type': 'string', 'enum': ['1.1', '1.2', '1.3', '1.4', '1.5', '1.6', '1.7', '1.8', '1.9', '1.10', '1.11', '1.12', '1.13', '1.14', '1.15', 'null']}}, '2.适用部位': {'type': 'array', 'items': {'type': 'string', 'enum': ['2.1.1', '2.1.2', '2.1.3', '2.2.1', '2.2.2', '2.2.3', '2.2.4', '2.2.5', '2.2.6', '2.3.1', '2.4.1', '2.4.2', '2.5.1', '2.5.2', '2.5.3', '2.5.4', '2.5.5', '2.5.6', '2.6.1', '2.7.1', '2.7.2', '2.8.1', '2.8.2', '2.9.1', '2.9.2', 'null']}}, '3.服务方式': {'type': 'array', 'items': {'type': 'string', 'enum': ['3.1.1', '3.1.2', '3.1.3', '3.1.4', '3.2.1', '3.2.2', '3.2.3', '3.2.4', '3.2.5', '3.2.6', '3.2.7', '3.2.8', '3.2.9', '3.2.10', '3.2.11', '3.2.12', '3.2.13', '3.2.14', '3.2.15', '3.3.1', '3.3.2', '3.3.3', '3.3.4', '3.3.5', '3.4.1', '3.4.2', '3.4.3', '3.4.4', '3.4.5', '3.5.1', '3.5.2', '3.5.3', '3.5.4', '3.5.5', '3.6.1', '3.6.2', '3.6.3', '3.7.1', '3.7.2', '3.7.3', '3.7.4', '3.8.1', '3.8.2', '3.8.3', '3.8.4', '3.9.1', '3.9.2', '3.10.1', '3.10.2', '3.10.3', '3.10.4', '3.10.5', '3.10.6', '3.11.1', '3.11.2', '3.11.3', '3.11.4', '3.12.1', '3.12.2', 'null']}}, '4.服务时长': {'type': 'string', 'enum': ['(0-30]', '(30-40]', '(40-60]', '(60-80]', '(80-90]', '(90-100]', '(100-120]', '(120-∞]', 'null']}, '5.适用人群': {'type': 'string', 'enum': ['5.1.1', '5.2.1', '5.2.2', '5.3.1', '5.3.2', '5.4', 'null']}, '6.适用日期/时段': {'type': 'string'}, '7.非服务类商品': {'type': 'string'}}, 'required': ['1.服务名称', '2.适用部位', '3.服务方式', '4.服务时长', '5.适用人群', '6.适用日期/时段', '7.非服务类商品'], 'additionalProperties': False}, '匹配结果': {'type': 'string', 'enum': ['是', '否']}}, 'required': ['项目单A', '项目单B', '匹配结果'], 'additionalProperties': False}",
        "target": {
            "项目单A": {
                "1.服务名称": [
                    "1.14"
                ],
                "2.适用部位": [
                    "2.8.2"
                ],
                "3.服务方式": [
                    "null"
                ],
                "4.服务时长": " (30-40]",
                "5.适用人群": "5.2.2",
                "6.适用日期/时段": "周一至周六09:00-21:00",
                "7.非服务类商品": "腹部热敷膏4盒"
            },
            "项目单B": {
                "1.服务名称": [
                    "1.14"
                ],
                "2.适用部位": [
                    "2.8.2"
                ],
                "3.服务方式": [
                    "null"
                ],
                "4.服务时长": "(0-30]",
                "5.适用人群": "5.2.2",
                "6.适用日期/时段": "09:00-21:00",
                "7.非服务类商品": "美背热敷膏4盒"
            },
            "匹配结果": "否"
        },
        "json_schema": {
            "$schema": "http://json-schema.org/draft-07/schema#",
            "type": "object",
            "properties": {
                "项目单A": {
                    "type": "object",
                    "properties": {
                        "1.服务名称": {
                            "type": "array",
                            "items": {
                                "type": "string",
                                "enum": [
                                    "1.1",
                                    "1.2",
                                    "1.3",
                                    "1.4",
                                    "1.5",
                                    "1.6",
                                    "1.7",
                                    "1.8",
                                    "1.9",
                                    "1.10",
                                    "1.11",
                                    "1.12",
                                    "1.13",
                                    "1.14",
                                    "1.15",
                                    "null"
                                ]
                            }
                        },
                        "2.适用部位": {
                            "type": "array",
                            "items": {
                                "type": "string",
                                "enum": [
                                    "2.1.1",
                                    "2.1.2",
                                    "2.1.3",
                                    "2.2.1",
                                    "2.2.2",
                                    "2.2.3",
                                    "2.2.4",
                                    "2.2.5",
                                    "2.2.6",
                                    "2.3.1",
                                    "2.4.1",
                                    "2.4.2",
                                    "2.5.1",
                                    "2.5.2",
                                    "2.5.3",
                                    "2.5.4",
                                    "2.5.5",
                                    "2.5.6",
                                    "2.6.1",
                                    "2.7.1",
                                    "2.7.2",
                                    "2.8.1",
                                    "2.8.2",
                                    "2.9.1",
                                    "2.9.2",
                                    "null"
                                ]
                            }
                        },
                        "3.服务方式": {
                            "type": "array",
                            "items": {
                                "type": "string",
                                "enum": [
                                    "3.1.1",
                                    "3.1.2",
                                    "3.1.3",
                                    "3.1.4",
                                    "3.2.1",
                                    "3.2.2",
                                    "3.2.3",
                                    "3.2.4",
                                    "3.2.5",
                                    "3.2.6",
                                    "3.2.7",
                                    "3.2.8",
                                    "3.2.9",
                                    "3.2.10",
                                    "3.2.11",
                                    "3.2.12",
                                    "3.2.13",
                                    "3.2.14",
                                    "3.2.15",
                                    "3.3.1",
                                    "3.3.2",
                                    "3.3.3",
                                    "3.3.4",
                                    "3.3.5",
                                    "3.4.1",
                                    "3.4.2",
                                    "3.4.3",
                                    "3.4.4",
                                    "3.4.5",
                                    "3.5.1",
                                    "3.5.2",
                                    "3.5.3",
                                    "3.5.4",
                                    "3.5.5",
                                    "3.6.1",
                                    "3.6.2",
                                    "3.6.3",
                                    "3.7.1",
                                    "3.7.2",
                                    "3.7.3",
                                    "3.7.4",
                                    "3.8.1",
                                    "3.8.2",
                                    "3.8.3",
                                    "3.8.4",
                                    "3.9.1",
                                    "3.9.2",
                                    "3.10.1",
                                    "3.10.2",
                                    "3.10.3",
                                    "3.10.4",
                                    "3.10.5",
                                    "3.10.6",
                                    "3.11.1",
                                    "3.11.2",
                                    "3.11.3",
                                    "3.11.4",
                                    "3.12.1",
                                    "3.12.2",
                                    "null"
                                ]
                            }
                        },
                        "4.服务时长": {
                            "type": "string",
                            "enum": [
                                "(0-30]",
                                "(30-40]",
                                "(40-60]",
                                "(60-80]",
                                "(80-90]",
                                "(90-100]",
                                "(100-120]",
                                "(120-∞]",
                                "null"
                            ]
                        },
                        "5.适用人群": {
                            "type": "string",
                            "enum": [
                                "5.1.1",
                                "5.2.1",
                                "5.2.2",
                                "5.3.1",
                                "5.3.2",
                                "5.4",
                                "null"
                            ]
                        },
                        "6.适用日期/时段": {
                            "type": "string"
                        },
                        "7.非服务类商品": {
                            "type": "string"
                        }
                    },
                    "required": [
                        "1.服务名称",
                        "2.适用部位",
                        "3.服务方式",
                        "4.服务时长",
                        "5.适用人群",
                        "6.适用日期/时段",
                        "7.非服务类商品"
                    ],
                    "additionalProperties": false
                },
                "项目单B": {
                    "type": "object",
                    "properties": {
                        "1.服务名称": {
                            "type": "array",
                            "items": {
                                "type": "string",
                                "enum": [
                                    "1.1",
                                    "1.2",
                                    "1.3",
                                    "1.4",
                                    "1.5",
                                    "1.6",
                                    "1.7",
                                    "1.8",
                                    "1.9",
                                    "1.10",
                                    "1.11",
                                    "1.12",
                                    "1.13",
                                    "1.14",
                                    "1.15",
                                    "null"
                                ]
                            }
                        },
                        "2.适用部位": {
                            "type": "array",
                            "items": {
                                "type": "string",
                                "enum": [
                                    "2.1.1",
                                    "2.1.2",
                                    "2.1.3",
                                    "2.2.1",
                                    "2.2.2",
                                    "2.2.3",
                                    "2.2.4",
                                    "2.2.5",
                                    "2.2.6",
                                    "2.3.1",
                                    "2.4.1",
                                    "2.4.2",
                                    "2.5.1",
                                    "2.5.2",
                                    "2.5.3",
                                    "2.5.4",
                                    "2.5.5",
                                    "2.5.6",
                                    "2.6.1",
                                    "2.7.1",
                                    "2.7.2",
                                    "2.8.1",
                                    "2.8.2",
                                    "2.9.1",
                                    "2.9.2",
                                    "null"
                                ]
                            }
                        },
                        "3.服务方式": {
                            "type": "array",
                            "items": {
                                "type": "string",
                                "enum": [
                                    "3.1.1",
                                    "3.1.2",
                                    "3.1.3",
                                    "3.1.4",
                                    "3.2.1",
                                    "3.2.2",
                                    "3.2.3",
                                    "3.2.4",
                                    "3.2.5",
                                    "3.2.6",
                                    "3.2.7",
                                    "3.2.8",
                                    "3.2.9",
                                    "3.2.10",
                                    "3.2.11",
                                    "3.2.12",
                                    "3.2.13",
                                    "3.2.14",
                                    "3.2.15",
                                    "3.3.1",
                                    "3.3.2",
                                    "3.3.3",
                                    "3.3.4",
                                    "3.3.5",
                                    "3.4.1",
                                    "3.4.2",
                                    "3.4.3",
                                    "3.4.4",
                                    "3.4.5",
                                    "3.5.1",
                                    "3.5.2",
                                    "3.5.3",
                                    "3.5.4",
                                    "3.5.5",
                                    "3.6.1",
                                    "3.6.2",
                                    "3.6.3",
                                    "3.7.1",
                                    "3.7.2",
                                    "3.7.3",
                                    "3.7.4",
                                    "3.8.1",
                                    "3.8.2",
                                    "3.8.3",
                                    "3.8.4",
                                    "3.9.1",
                                    "3.9.2",
                                    "3.10.1",
                                    "3.10.2",
                                    "3.10.3",
                                    "3.10.4",
                                    "3.10.5",
                                    "3.10.6",
                                    "3.11.1",
                                    "3.11.2",
                                    "3.11.3",
                                    "3.11.4",
                                    "3.12.1",
                                    "3.12.2",
                                    "null"
                                ]
                            }
                        },
                        "4.服务时长": {
                            "type": "string",
                            "enum": [
                                "(0-30]",
                                "(30-40]",
                                "(40-60]",
                                "(60-80]",
                                "(80-90]",
                                "(90-100]",
                                "(100-120]",
                                "(120-∞]",
                                "null"
                            ]
                        },
                        "5.适用人群": {
                            "type": "string",
                            "enum": [
                                "5.1.1",
                                "5.2.1",
                                "5.2.2",
                                "5.3.1",
                                "5.3.2",
                                "5.4",
                                "null"
                            ]
                        },
                        "6.适用日期/时段": {
                            "type": "string"
                        },
                        "7.非服务类商品": {
                            "type": "string"
                        }
                    },
                    "required": [
                        "1.服务名称",
                        "2.适用部位",
                        "3.服务方式",
                        "4.服务时长",
                        "5.适用人群",
                        "6.适用日期/时段",
                        "7.非服务类商品"
                    ],
                    "additionalProperties": false
                },
                "匹配结果": {
                    "type": "string",
                    "enum": [
                        "是",
                        "否"
                    ]
                }
            },
            "required": [
                "项目单A",
                "项目单B",
                "匹配结果"
            ],
            "additionalProperties": false
        },
        "no_required_eval_acc_keys": [
            "6.适用日期/时段"
        ],
        "model_response": "```json\n{\n  \"项目单A\": {\n    \"1.服务名称\": [\n      \"1.14\"\n    ],\n    \"2.适用部位\": [\n      \"2.8.2\"\n    ],\n    \"3.服务方式\": [\n      \"3.11.4\"\n    ],\n    \"4.服务时长\": \"(30-40]\",\n    \"5.适用人群\": \"5.2.2\",\n    \"6.适用日期/时段\": \"09:00-21:00\",\n    \"7.非服务类商品\": \"腹部热敷膏, 4盒\"\n  },\n  \"项目单B\": {\n    \"1.服务名称\": [\n      \"null\"\n    ],\n    \"2.适用部位\": [\n      \"2.1.3\"\n    ],\n    \"3.服务方式\": [\n      \"null\"\n    ],\n    \"4.服务时长\": \"(0-30]\",\n    \"5.适用人群\": \"5.4\",\n    \"6.适用日期/时段\": \"09:00-21:00\",\n    \"7.非服务类商品\": \"美背热敷膏, 4盒\"\n  },\n  \"匹配结果\": \"否\"\n}\n```"
    },
    {
        "input": "【Background】\n【角色定义】你是一名消费者,你需要充分了解两个商家提供的生活项目并进行比较, 根据关键要素抽取规则和项目匹配规则来判断两个项目是否相同或匹配，并且以结构化数据的形式把两个项目结果展示出来。\n【Requirements】\n\n\n项目单的信息包括：商品标题、项目单详情、有效期、营业时间、适用人数、购买限制等。关键要素包括：服务名称、适用部位、服务方式、服务时长、适用人群、适用日期/时段、非服务类商品。（注意：如果有枚举值需要归类到枚举值，如果该内容在枚举值之外则默认为null；严格按照优先级，获取信息后不再考虑剩余。\"\n    \"1.服务名称，同一项目单可能包含多个项目，需要全部列举（注意：出现好评礼、会员礼所附赠的项目不计入服务名称。例如：“好评一次深层洁净60分钟”，则服务名称为“null”。优先级：商品标题 > 服务功效 > 服务流程/步骤\n     枚举值：\n     1.1深层洁净(收缩毛孔)\n     1.2补水保湿(皮肤清洁、毛孔洗澡)\n     1.3祛痘\n     1.4美白嫩肤\n     1.5淡斑祛斑\n     1.6紧致提拉\n     1.7修复护理\n     1.8脱毛\n     1.9眼部护理\n     1.10肩颈按摩\n     1.11SPA\n     1.12头疗\n     1.13养生调理\n     1.14瘦身纤体\n     1.15美胸美臀\n\n    2.适用部位：和服务名称对应。优先级：商品标题 > 服务功效 > 服务流程/步骤\n     枚举值：\n     2.1深层洁净/补水保湿/祛痘/美白嫩肤/淡斑祛斑/紧致提拉/修复护理：2.1.1面部,2.1.2部分面部,2.1.3背部 \n     2.2脱毛：2.2.1口唇,2.2.2腋下,2.2.3面部,2.2.4手臂,2.2.5腿部,2.2.6私密/比基尼\n     2.3眼部护理：2.3.1眼部 \n     2.4肩颈按摩：2.4.1肩颈,2.4.2肩颈+背 \n     2.5SPA：2.5.1全身,2.5.2肩颈+腰背,2.5.3肩颈+背部+腿部,2.5.4肩颈+腰腹+腿,2.5.5头+肩+颈+背,2.5.6背部 \n     2.6头疗：2.6.1头部\n     2.7养生调理：2.7.1全身(未指明部位),2.7.2局部(非全身，或者指明某个部位) \n     2.8瘦身纤体：2.8.1全身,2.8.2局部塑形 \n     2.9美胸美臀：2.9.1胸部,2.9.2臀部\n    \n    3.服务方式：和服务名称对应。优先级：项目单详情>商品标题\n     枚举值：（注意：1.未提到以下内容的，输出null;2.如果出现2种或者2种以上结果需要都输出）\n     3.1深层洁净：3.1.1)仪器(超微小气泡/大气泡/臭氧泡泡/魔法活氧泡泡) 3.1.2)海菲秀 3.1.3)泥膜/面膜 3.1.4)白牌产品 \n    3.2补水保湿：3.2.1)B5精华 3.2.2)修丽可 3.2.3)日式pola 3.2.4)日式晓姿 3.2.5)赫莲娜HR 3.2.6)伊芙珑evelom 3.2.7)海蓝之谜LA MER 3.2.8)瑞妍cellcosment 3.2.9)莱珀妮 LA PRAIRIE 3.2.10)迪奥DIOR 3.2.11)圣罗兰YSL 3.2.12)诚美DGR 3.2.13)法尔曼VALMONT 3.2.14)菲洛嘉FILORGA 3.2.15)白牌产品\n     3.3祛痘：3.3.1)手工针清/皮铲/护理 3.3.2)点阵激光 3.3.3)红蓝光/PDT光能/烤光 3.3.4)刷酸/果酸 3.3.5)草本 \n     3.4美白嫩肤：3.4.1)焕肤类 3.4.2)氨甲环酸 3.4.3)大牌产品(菲洛嘉) 3.4.4)普牌产品(欧诗漫) 3.4.5)白牌产品 \n     3.5紧致提拉：3.5.1)手法按摩类 3.5.2)抗糖祛黄/生物酶疗 3.5.3)木乃伊紧致 3.5.4)大牌产品(赫莲娜/日式POLA) 3.5.5)白牌产品 \n     3.6修复护理：3.6.1)酵素/乳糖酸/骨胶原/活性酶 3.6.2)大牌产品(赫莲娜/伊芙珑/海蓝之谜/瑞妍/莱珀妮/迪奥/圣罗兰诚美DGR/法尔曼/菲洛嘉) 3.6.3)白牌产品\n     3.7肩颈按摩：3.7.1)使用精油 3.7.2)不使用精油 3.7.3)热石精油 3.7.4)水疗\n     3.8全身SPA：3.8.1)使用精油 3.8.2)不使用精油 3.8.3)热石精油 3.8.4)水疗\n     3.9头疗：3.9.1)使用精油 3.9.2)不使用精油 \n     3.10养生调理：3.10.1)灸类 3.10.2)刮痧 3.10.3)罐类 3.10.4)蒸/浴类 3.10.5)经络/净排类 3.10.6)产后修复类\n     3.11瘦身纤体：3.11.1)针灸/拔罐/经络 3.11.2)刮痧 3.11.3)仪器 3.11.4)调理粉/精油\n     3.12.美胸美臀：3.12.1)使用精油 3.12.2)不使用精油\n\n    4.服务时长，总服务时长(服务项目的服务时长总和)。优先级：商品标题>项目单详情\n    需要映射到枚举值：(0-30]、(30-40]、(40-60]、(60-80]、(80-90]、(90-100]、(100-120]、(120-∞]（输出答案时需要输出具体的枚举值内容）\n\n    5.适用人群，包括性别、年龄、用户类型（出现“XX节”属于营销词，不能作为性别的判断，eg.女神节专属、母亲节，不能判断性别为女性） 优先级：购买限制>商品标题>项目单详情\n     枚举值：（注意：此项优先级：用户类型>性别>年龄，只需输出一个类别）\n     5.1用户类型：5.1.1新客价格（第一次使用该项目的用户）\n     5.2性别：5.2.1男性，5.2.2女性\n     5.3年龄：5.3.1儿童（0-12周岁）,5.3.2成人（18岁以上）\n     5.4不限通用(每人限购1份，不限年龄，性别)\n\n    6.适用日期/时段（注意：全天可用等于商家营业时间可用；闲时指的是周一到周五的下午4点前）  优先级：项目单详情>商品标题>购买须知\n    注意1：项目单详情中信息多处不符一致时，则取最小时段进行对比，eg1.A单适用日期：2025年7月1日-2025年9月1日，周一-周五10:00-19:00可用；B单适用日期2025.7.1-2025.10.1周一到周日10:00-22:00，则AB两单适用日期/时段不一致。eg2.2025年8月1日-2025年8月30日，周一-周五10:00-19:00可用；B单适用日期2025.7.1-2025.10.1周一-周天10:00-19:00可用，则AB两单适用日期/时段一致（不考虑年月日时格式）\n    注意2：适用日期/时段：从营业时间得到信息，仅看“周一-周日”、“xx月xx日-xx月xx日”、“xx:xx-xx:xx”、“xx点-xx点”等类似字眼，无需关注特殊节假日；时段：由“开始时间”和“结束时间”组成，输出具体的时间，例如“10:00-22:00” \n\n    7.非服务类商品：指的是除服务名称以外的内容，eg.“深层洁净60分钟+（含/送/赠）XX面膜2盒”，”非服务商品为“XX面膜，2盒”。如果是仅面膜、产品，零食、皮肤检测等非美容美体产品不算非服务产品，此时输出null。\n\n    8.白牌产品：指的是小厂商生产的没有牌子的商品，白牌是相对品牌而言的。\n\n\n    项目单匹配规则：根据抽取出来的要素和以下规则判断是否为同一项目单“注意：如果无法识别出来则默认为null”\n     1.服务名称：需完全一致，否则认为两个项目单不一致(不考虑顺序)。\n     2.适用部位：需完全一致，否则认为两个项目单不一致(不考虑顺序)。\n     3.服务方式：任意一方有值另一方空值，不可以视为一致。需要两侧都有值进行判断是否一致。\n     4.服务时长：如果任意一方有值另一方空值，可以视为一致。但当双方都有值时，双方时长一致才算一致。\n     5.适用人群：性别、年龄、用户类型要完全一样才算一致，如果任意一方空值则默认为“不限通用”，随后再对比出结果。\n     6.适用日期/时段：\n      1)当只有适用日期（年月日）时，日期精确到年月日相同则认为一致，eg.A单适用日期：2025年7月1日-2025年10月1日；B单适用日期2025.7.1-2025.10.1，则AB两单适用日期一致。（不考虑年月日格式）\n      2)当任意一方“适用日期”为空值，则取适用时段或者运营时间进行比较，AB两单之间起始及终止时间相差为1小时以内，可视为一致，超过1小时则为不一致。\n     7.非服务类商品：\n      1)纯非服务类商品，无需参与匹配。\n      2)若出现服务名称+非服务产品，针对服务内容按照规则匹配；非服务类商品需精准匹配，内容具体到名称+规格或者单位或者品牌。eg.“深层洁净60分钟+（含/送/赠）XX面膜2盒”，”非服务商品为“2盒XX面膜”\n    判断步骤：\n     1. 根据输入的项目单信息和规则抽取相应的要素，以及输出对应的枚举值内容\n     2. 根据抽取要素、枚举值内容和匹配规则来判断两个项目单是否匹配\n     \n     \n\n【Input】 \n10.项目单A:{'商品标题': '360深层毛孔净化管理', '适用人数': '每张优惠券最多1人使用', '规则提醒': '可与其他优惠同享', '购买限制': '每人限购1张', '营业时间': '周一至周日10:00-22:00', '项目单详情': [{'名称': '360深层毛孔净化管理', '分类': '皮肤管理', '二级分类': '大气泡', '服务功效': '补水保湿、深层清洁', '适用部位': '全面部', '服务流程': '', '服务步骤': [{'产品': '', '说明': '', '名称': '卸妆洁面', '设备': '', '二级名称': '卸妆洁面', '时长': '10min', '部位': '全面部'}, {'产品': '黑头导出液', '说明': '', '名称': '面部清洁', '设备': '热喷', '二级名称': '毛孔舒张', '时长': '10 min ', '部位': '全面部'}, {'产品': '纯净水', '说明': '', '名称': '面部清洁', '设备': '大气泡', '二级名称': '小气泡清洁', '时长': '10 min ', '部位': '全面部'}, {'产品': '茶树退红底膜', '说明': '', '名称': '修护护理', '设备': '照灯', '二级名称': '修护护理', '时长': '10 min ', '部位': '全面部'}, {'产品': '补水精华', '说明': '', '名称': '修护护理', '设备': '冷导', '二级名称': '冷喷镇静', '时长': '5 min ', '部位': '全面部'}, {'产品': '敷补水面膜', '说明': '', '名称': '补水保湿', '设备': '', '二级名称': '深层补水', '时长': '15 min ', '部位': '全面部'}], '服务附赠': '化妆用具1套'}]} 项目单B:{'商品': '深层肌底毛孔净化管理', '营业时间': '10:00-22:00', '服务功效': '深层清洁', '适用性别': '不限', '适用部位': '全脸部', '有效期': '有效期：购买后60天有效', '可用时间': '商家营业时间可用', '购买限制': '', '适用人数': '每张优惠券限1人使用', '其他规则': '单次消费最多使用1张优惠券;可与店内部分优惠同享，详询商家;发票问题请询问商家;购买两单以后即可赠送雨伞一把;24小时内联系客服核销送好礼', '项目单详情': [{'名称': '功能面部舒缓', '分类': '舒缓', '部位': '', '时长': '5分钟', '服务流程': '深层洁净全脸部5分钟', '附赠服务': '无'}, {'名称': '水光仪深层清洁黑头', '分类': '清洁', '部位': '', '时长': '15分钟', '服务流程': '深层洁净全脸部15分钟', '附赠服务': '无'}, {'名称': '热喷仪疏通毛孔', '分类': '热喷仪', '部位': '', '时长': '10分钟', '服务流程': '深层洁净全脸部10分钟', '附赠服务': '无'}, {'名称': '面部泡泡清洁', '分类': '面部泡泡', '部位': '', '时长': '5分钟', '服务流程': '深层洁净全脸部5分钟', '附赠服务': '无'}, {'名称': '光动力毛孔修复', '分类': '修复', '部位': '', '时长': '15分钟', '服务流程': '深层洁净全脸部15分钟', '附赠服务': '无'}, {'名称': '深层补水面膜', '分类': '补水', '部位': '', '时长': '5分钟', '服务流程': '深层洁净全脸部5分钟', '附赠服务': '无'}, {'名称': '肩颈舒缓放松', '分类': '放松', '部位': '', '时长': '5分钟', '服务流程': '深层洁净颈部5分钟', '附赠服务': '无'}]}\n\n\n\n【Output Requirement】\n 你的输出必须满足以下JSON_SCHEMA{'$schema': 'http://json-schema.org/draft-07/schema#', 'type': 'object', 'properties': {'项目单A': {'type': 'object', 'properties': {'1.服务名称': {'type': 'array', 'items': {'type': 'string', 'enum': ['1.1', '1.2', '1.3', '1.4', '1.5', '1.6', '1.7', '1.8', '1.9', '1.10', '1.11', '1.12', '1.13', '1.14', '1.15', 'null']}}, '2.适用部位': {'type': 'array', 'items': {'type': 'string', 'enum': ['2.1.1', '2.1.2', '2.1.3', '2.2.1', '2.2.2', '2.2.3', '2.2.4', '2.2.5', '2.2.6', '2.3.1', '2.4.1', '2.4.2', '2.5.1', '2.5.2', '2.5.3', '2.5.4', '2.5.5', '2.5.6', '2.6.1', '2.7.1', '2.7.2', '2.8.1', '2.8.2', '2.9.1', '2.9.2', 'null']}}, '3.服务方式': {'type': 'array', 'items': {'type': 'string', 'enum': ['3.1.1', '3.1.2', '3.1.3', '3.1.4', '3.2.1', '3.2.2', '3.2.3', '3.2.4', '3.2.5', '3.2.6', '3.2.7', '3.2.8', '3.2.9', '3.2.10', '3.2.11', '3.2.12', '3.2.13', '3.2.14', '3.2.15', '3.3.1', '3.3.2', '3.3.3', '3.3.4', '3.3.5', '3.4.1', '3.4.2', '3.4.3', '3.4.4', '3.4.5', '3.5.1', '3.5.2', '3.5.3', '3.5.4', '3.5.5', '3.6.1', '3.6.2', '3.6.3', '3.7.1', '3.7.2', '3.7.3', '3.7.4', '3.8.1', '3.8.2', '3.8.3', '3.8.4', '3.9.1', '3.9.2', '3.10.1', '3.10.2', '3.10.3', '3.10.4', '3.10.5', '3.10.6', '3.11.1', '3.11.2', '3.11.3', '3.11.4', '3.12.1', '3.12.2', 'null']}}, '4.服务时长': {'type': 'string', 'enum': ['(0-30]', '(30-40]', '(40-60]', '(60-80]', '(80-90]', '(90-100]', '(100-120]', '(120-∞]', 'null']}, '5.适用人群': {'type': 'string', 'enum': ['5.1.1', '5.2.1', '5.2.2', '5.3.1', '5.3.2', '5.4', 'null']}, '6.适用日期/时段': {'type': 'string'}, '7.非服务类商品': {'type': 'string'}}, 'required': ['1.服务名称', '2.适用部位', '3.服务方式', '4.服务时长', '5.适用人群', '6.适用日期/时段', '7.非服务类商品'], 'additionalProperties': False}, '项目单B': {'type': 'object', 'properties': {'1.服务名称': {'type': 'array', 'items': {'type': 'string', 'enum': ['1.1', '1.2', '1.3', '1.4', '1.5', '1.6', '1.7', '1.8', '1.9', '1.10', '1.11', '1.12', '1.13', '1.14', '1.15', 'null']}}, '2.适用部位': {'type': 'array', 'items': {'type': 'string', 'enum': ['2.1.1', '2.1.2', '2.1.3', '2.2.1', '2.2.2', '2.2.3', '2.2.4', '2.2.5', '2.2.6', '2.3.1', '2.4.1', '2.4.2', '2.5.1', '2.5.2', '2.5.3', '2.5.4', '2.5.5', '2.5.6', '2.6.1', '2.7.1', '2.7.2', '2.8.1', '2.8.2', '2.9.1', '2.9.2', 'null']}}, '3.服务方式': {'type': 'array', 'items': {'type': 'string', 'enum': ['3.1.1', '3.1.2', '3.1.3', '3.1.4', '3.2.1', '3.2.2', '3.2.3', '3.2.4', '3.2.5', '3.2.6', '3.2.7', '3.2.8', '3.2.9', '3.2.10', '3.2.11', '3.2.12', '3.2.13', '3.2.14', '3.2.15', '3.3.1', '3.3.2', '3.3.3', '3.3.4', '3.3.5', '3.4.1', '3.4.2', '3.4.3', '3.4.4', '3.4.5', '3.5.1', '3.5.2', '3.5.3', '3.5.4', '3.5.5', '3.6.1', '3.6.2', '3.6.3', '3.7.1', '3.7.2', '3.7.3', '3.7.4', '3.8.1', '3.8.2', '3.8.3', '3.8.4', '3.9.1', '3.9.2', '3.10.1', '3.10.2', '3.10.3', '3.10.4', '3.10.5', '3.10.6', '3.11.1', '3.11.2', '3.11.3', '3.11.4', '3.12.1', '3.12.2', 'null']}}, '4.服务时长': {'type': 'string', 'enum': ['(0-30]', '(30-40]', '(40-60]', '(60-80]', '(80-90]', '(90-100]', '(100-120]', '(120-∞]', 'null']}, '5.适用人群': {'type': 'string', 'enum': ['5.1.1', '5.2.1', '5.2.2', '5.3.1', '5.3.2', '5.4', 'null']}, '6.适用日期/时段': {'type': 'string'}, '7.非服务类商品': {'type': 'string'}}, 'required': ['1.服务名称', '2.适用部位', '3.服务方式', '4.服务时长', '5.适用人群', '6.适用日期/时段', '7.非服务类商品'], 'additionalProperties': False}, '匹配结果': {'type': 'string', 'enum': ['是', '否']}}, 'required': ['项目单A', '项目单B', '匹配结果'], 'additionalProperties': False}",
        "target": {
            "项目单A": {
                "1.服务名称": [
                    "1.1"
                ],
                "2.适用部位": [
                    "2.1.1"
                ],
                "3.服务方式": [
                    "3.1.1",
                    "3.1.3"
                ],
                "4.服务时长": "(40-60]",
                "5.适用人群": "5.4",
                "6.适用日期/时段": "周一至周日10:00-22:00",
                "7.非服务类商品": "化妆用具1套"
            },
            "项目单B": {
                "1.服务名称": [
                    "1.1"
                ],
                "2.适用部位": [
                    "2.1.1"
                ],
                "3.服务方式": [
                    "3.1.1",
                    "3.1.3"
                ],
                "4.服务时长": "(100-120]",
                "5.适用人群": "5.4",
                "6.适用日期/时段": "10:00-22:00",
                "7.非服务类商品": "null"
            },
            "匹配结果": "否"
        },
        "json_schema": {
            "$schema": "http://json-schema.org/draft-07/schema#",
            "type": "object",
            "properties": {
                "项目单A": {
                    "type": "object",
                    "properties": {
                        "1.服务名称": {
                            "type": "array",
                            "items": {
                                "type": "string",
                                "enum": [
                                    "1.1",
                                    "1.2",
                                    "1.3",
                                    "1.4",
                                    "1.5",
                                    "1.6",
                                    "1.7",
                                    "1.8",
                                    "1.9",
                                    "1.10",
                                    "1.11",
                                    "1.12",
                                    "1.13",
                                    "1.14",
                                    "1.15",
                                    "null"
                                ]
                            }
                        },
                        "2.适用部位": {
                            "type": "array",
                            "items": {
                                "type": "string",
                                "enum": [
                                    "2.1.1",
                                    "2.1.2",
                                    "2.1.3",
                                    "2.2.1",
                                    "2.2.2",
                                    "2.2.3",
                                    "2.2.4",
                                    "2.2.5",
                                    "2.2.6",
                                    "2.3.1",
                                    "2.4.1",
                                    "2.4.2",
                                    "2.5.1",
                                    "2.5.2",
                                    "2.5.3",
                                    "2.5.4",
                                    "2.5.5",
                                    "2.5.6",
                                    "2.6.1",
                                    "2.7.1",
                                    "2.7.2",
                                    "2.8.1",
                                    "2.8.2",
                                    "2.9.1",
                                    "2.9.2",
                                    "null"
                                ]
                            }
                        },
                        "3.服务方式": {
                            "type": "array",
                            "items": {
                                "type": "string",
                                "enum": [
                                    "3.1.1",
                                    "3.1.2",
                                    "3.1.3",
                                    "3.1.4",
                                    "3.2.1",
                                    "3.2.2",
                                    "3.2.3",
                                    "3.2.4",
                                    "3.2.5",
                                    "3.2.6",
                                    "3.2.7",
                                    "3.2.8",
                                    "3.2.9",
                                    "3.2.10",
                                    "3.2.11",
                                    "3.2.12",
                                    "3.2.13",
                                    "3.2.14",
                                    "3.2.15",
                                    "3.3.1",
                                    "3.3.2",
                                    "3.3.3",
                                    "3.3.4",
                                    "3.3.5",
                                    "3.4.1",
                                    "3.4.2",
                                    "3.4.3",
                                    "3.4.4",
                                    "3.4.5",
                                    "3.5.1",
                                    "3.5.2",
                                    "3.5.3",
                                    "3.5.4",
                                    "3.5.5",
                                    "3.6.1",
                                    "3.6.2",
                                    "3.6.3",
                                    "3.7.1",
                                    "3.7.2",
                                    "3.7.3",
                                    "3.7.4",
                                    "3.8.1",
                                    "3.8.2",
                                    "3.8.3",
                                    "3.8.4",
                                    "3.9.1",
                                    "3.9.2",
                                    "3.10.1",
                                    "3.10.2",
                                    "3.10.3",
                                    "3.10.4",
                                    "3.10.5",
                                    "3.10.6",
                                    "3.11.1",
                                    "3.11.2",
                                    "3.11.3",
                                    "3.11.4",
                                    "3.12.1",
                                    "3.12.2",
                                    "null"
                                ]
                            }
                        },
                        "4.服务时长": {
                            "type": "string",
                            "enum": [
                                "(0-30]",
                                "(30-40]",
                                "(40-60]",
                                "(60-80]",
                                "(80-90]",
                                "(90-100]",
                                "(100-120]",
                                "(120-∞]",
                                "null"
                            ]
                        },
                        "5.适用人群": {
                            "type": "string",
                            "enum": [
                                "5.1.1",
                                "5.2.1",
                                "5.2.2",
                                "5.3.1",
                                "5.3.2",
                                "5.4",
                                "null"
                            ]
                        },
                        "6.适用日期/时段": {
                            "type": "string"
                        },
                        "7.非服务类商品": {
                            "type": "string"
                        }
                    },
                    "required": [
                        "1.服务名称",
                        "2.适用部位",
                        "3.服务方式",
                        "4.服务时长",
                        "5.适用人群",
                        "6.适用日期/时段",
                        "7.非服务类商品"
                    ],
                    "additionalProperties": false
                },
                "项目单B": {
                    "type": "object",
                    "properties": {
                        "1.服务名称": {
                            "type": "array",
                            "items": {
                                "type": "string",
                                "enum": [
                                    "1.1",
                                    "1.2",
                                    "1.3",
                                    "1.4",
                                    "1.5",
                                    "1.6",
                                    "1.7",
                                    "1.8",
                                    "1.9",
                                    "1.10",
                                    "1.11",
                                    "1.12",
                                    "1.13",
                                    "1.14",
                                    "1.15",
                                    "null"
                                ]
                            }
                        },
                        "2.适用部位": {
                            "type": "array",
                            "items": {
                                "type": "string",
                                "enum": [
                                    "2.1.1",
                                    "2.1.2",
                                    "2.1.3",
                                    "2.2.1",
                                    "2.2.2",
                                    "2.2.3",
                                    "2.2.4",
                                    "2.2.5",
                                    "2.2.6",
                                    "2.3.1",
                                    "2.4.1",
                                    "2.4.2",
                                    "2.5.1",
                                    "2.5.2",
                                    "2.5.3",
                                    "2.5.4",
                                    "2.5.5",
                                    "2.5.6",
                                    "2.6.1",
                                    "2.7.1",
                                    "2.7.2",
                                    "2.8.1",
                                    "2.8.2",
                                    "2.9.1",
                                    "2.9.2",
                                    "null"
                                ]
                            }
                        },
                        "3.服务方式": {
                            "type": "array",
                            "items": {
                                "type": "string",
                                "enum": [
                                    "3.1.1",
                                    "3.1.2",
                                    "3.1.3",
                                    "3.1.4",
                                    "3.2.1",
                                    "3.2.2",
                                    "3.2.3",
                                    "3.2.4",
                                    "3.2.5",
                                    "3.2.6",
                                    "3.2.7",
                                    "3.2.8",
                                    "3.2.9",
                                    "3.2.10",
                                    "3.2.11",
                                    "3.2.12",
                                    "3.2.13",
                                    "3.2.14",
                                    "3.2.15",
                                    "3.3.1",
                                    "3.3.2",
                                    "3.3.3",
                                    "3.3.4",
                                    "3.3.5",
                                    "3.4.1",
                                    "3.4.2",
                                    "3.4.3",
                                    "3.4.4",
                                    "3.4.5",
                                    "3.5.1",
                                    "3.5.2",
                                    "3.5.3",
                                    "3.5.4",
                                    "3.5.5",
                                    "3.6.1",
                                    "3.6.2",
                                    "3.6.3",
                                    "3.7.1",
                                    "3.7.2",
                                    "3.7.3",
                                    "3.7.4",
                                    "3.8.1",
                                    "3.8.2",
                                    "3.8.3",
                                    "3.8.4",
                                    "3.9.1",
                                    "3.9.2",
                                    "3.10.1",
                                    "3.10.2",
                                    "3.10.3",
                                    "3.10.4",
                                    "3.10.5",
                                    "3.10.6",
                                    "3.11.1",
                                    "3.11.2",
                                    "3.11.3",
                                    "3.11.4",
                                    "3.12.1",
                                    "3.12.2",
                                    "null"
                                ]
                            }
                        },
                        "4.服务时长": {
                            "type": "string",
                            "enum": [
                                "(0-30]",
                                "(30-40]",
                                "(40-60]",
                                "(60-80]",
                                "(80-90]",
                                "(90-100]",
                                "(100-120]",
                                "(120-∞]",
                                "null"
                            ]
                        },
                        "5.适用人群": {
                            "type": "string",
                            "enum": [
                                "5.1.1",
                                "5.2.1",
                                "5.2.2",
                                "5.3.1",
                                "5.3.2",
                                "5.4",
                                "null"
                            ]
                        },
                        "6.适用日期/时段": {
                            "type": "string"
                        },
                        "7.非服务类商品": {
                            "type": "string"
                        }
                    },
                    "required": [
                        "1.服务名称",
                        "2.适用部位",
                        "3.服务方式",
                        "4.服务时长",
                        "5.适用人群",
                        "6.适用日期/时段",
                        "7.非服务类商品"
                    ],
                    "additionalProperties": false
                },
                "匹配结果": {
                    "type": "string",
                    "enum": [
                        "是",
                        "否"
                    ]
                }
            },
            "required": [
                "项目单A",
                "项目单B",
                "匹配结果"
            ],
            "additionalProperties": false
        },
        "no_required_eval_acc_keys": [
            "6.适用日期/时段"
        ],
        "model_response": "```json\n{\n    \"项目单A\": {\n        \"1.服务名称\": [\"1.1\", \"1.2\", \"1.7\"],\n        \"2.适用部位\": [\"2.1.1\"],\n        \"3.服务方式\": [\"3.1.1\", \"3.1.3\", \"3.2.15\"],\n        \"4.服务时长\": \"(40-60]\",\n        \"5.适用人群\": \"5.4\",\n        \"6.适用日期/时段\": \"10:00-22:00\",\n        \"7.非服务类商品\": \"化妆用具1套\"\n    },\n    \"项目单B\": {\n        \"1.服务名称\": [\"1.1\", \"1.2\", \"1.7\"],\n        \"2.适用部位\": [\"2.1.1\"],\n        \"3.服务方式\": [\"3.1.1\", \"3.1.3\"],\n        \"4.服务时长\": \"(40-60]\",\n        \"5.适用人群\": \"5.4\",\n        \"6.适用日期/时段\": \"10:00-22:00\",\n        \"7.非服务类商品\": \"雨伞一把\"\n    },\n    \"匹配结果\": \"否\"\n}\n```"
    },
    {
        "input": "【Background】\n【角色定义】你是一名消费者,你需要充分了解两个商家提供的生活项目并进行比较, 根据关键要素抽取规则和项目匹配规则来判断两个项目是否相同或匹配，并且以结构化数据的形式把两个项目结果展示出来。\n【Requirements】\n\n\n项目单的信息包括：商品标题、项目单详情、有效期、营业时间、适用人数、购买限制等。关键要素包括：服务名称、适用部位、服务方式、服务时长、适用人群、适用日期/时段、非服务类商品。（注意：如果有枚举值需要归类到枚举值，如果该内容在枚举值之外则默认为null；严格按照优先级，获取信息后不再考虑剩余。\"\n    \"1.服务名称，同一项目单可能包含多个项目，需要全部列举（注意：出现好评礼、会员礼所附赠的项目不计入服务名称。例如：“好评一次深层洁净60分钟”，则服务名称为“null”。优先级：商品标题 > 服务功效 > 服务流程/步骤\n     枚举值：\n     1.1深层洁净(收缩毛孔)\n     1.2补水保湿(皮肤清洁、毛孔洗澡)\n     1.3祛痘\n     1.4美白嫩肤\n     1.5淡斑祛斑\n     1.6紧致提拉\n     1.7修复护理\n     1.8脱毛\n     1.9眼部护理\n     1.10肩颈按摩\n     1.11SPA\n     1.12头疗\n     1.13养生调理\n     1.14瘦身纤体\n     1.15美胸美臀\n\n    2.适用部位：和服务名称对应。优先级：商品标题 > 服务功效 > 服务流程/步骤\n     枚举值：\n     2.1深层洁净/补水保湿/祛痘/美白嫩肤/淡斑祛斑/紧致提拉/修复护理：2.1.1面部,2.1.2部分面部,2.1.3背部 \n     2.2脱毛：2.2.1口唇,2.2.2腋下,2.2.3面部,2.2.4手臂,2.2.5腿部,2.2.6私密/比基尼\n     2.3眼部护理：2.3.1眼部 \n     2.4肩颈按摩：2.4.1肩颈,2.4.2肩颈+背 \n     2.5SPA：2.5.1全身,2.5.2肩颈+腰背,2.5.3肩颈+背部+腿部,2.5.4肩颈+腰腹+腿,2.5.5头+肩+颈+背,2.5.6背部 \n     2.6头疗：2.6.1头部\n     2.7养生调理：2.7.1全身(未指明部位),2.7.2局部(非全身，或者指明某个部位) \n     2.8瘦身纤体：2.8.1全身,2.8.2局部塑形 \n     2.9美胸美臀：2.9.1胸部,2.9.2臀部\n    \n    3.服务方式：和服务名称对应。优先级：项目单详情>商品标题\n     枚举值：（注意：1.未提到以下内容的，输出null;2.如果出现2种或者2种以上结果需要都输出）\n     3.1深层洁净：3.1.1)仪器(超微小气泡/大气泡/臭氧泡泡/魔法活氧泡泡) 3.1.2)海菲秀 3.1.3)泥膜/面膜 3.1.4)白牌产品 \n    3.2补水保湿：3.2.1)B5精华 3.2.2)修丽可 3.2.3)日式pola 3.2.4)日式晓姿 3.2.5)赫莲娜HR 3.2.6)伊芙珑evelom 3.2.7)海蓝之谜LA MER 3.2.8)瑞妍cellcosment 3.2.9)莱珀妮 LA PRAIRIE 3.2.10)迪奥DIOR 3.2.11)圣罗兰YSL 3.2.12)诚美DGR 3.2.13)法尔曼VALMONT 3.2.14)菲洛嘉FILORGA 3.2.15)白牌产品\n     3.3祛痘：3.3.1)手工针清/皮铲/护理 3.3.2)点阵激光 3.3.3)红蓝光/PDT光能/烤光 3.3.4)刷酸/果酸 3.3.5)草本 \n     3.4美白嫩肤：3.4.1)焕肤类 3.4.2)氨甲环酸 3.4.3)大牌产品(菲洛嘉) 3.4.4)普牌产品(欧诗漫) 3.4.5)白牌产品 \n     3.5紧致提拉：3.5.1)手法按摩类 3.5.2)抗糖祛黄/生物酶疗 3.5.3)木乃伊紧致 3.5.4)大牌产品(赫莲娜/日式POLA) 3.5.5)白牌产品 \n     3.6修复护理：3.6.1)酵素/乳糖酸/骨胶原/活性酶 3.6.2)大牌产品(赫莲娜/伊芙珑/海蓝之谜/瑞妍/莱珀妮/迪奥/圣罗兰诚美DGR/法尔曼/菲洛嘉) 3.6.3)白牌产品\n     3.7肩颈按摩：3.7.1)使用精油 3.7.2)不使用精油 3.7.3)热石精油 3.7.4)水疗\n     3.8全身SPA：3.8.1)使用精油 3.8.2)不使用精油 3.8.3)热石精油 3.8.4)水疗\n     3.9头疗：3.9.1)使用精油 3.9.2)不使用精油 \n     3.10养生调理：3.10.1)灸类 3.10.2)刮痧 3.10.3)罐类 3.10.4)蒸/浴类 3.10.5)经络/净排类 3.10.6)产后修复类\n     3.11瘦身纤体：3.11.1)针灸/拔罐/经络 3.11.2)刮痧 3.11.3)仪器 3.11.4)调理粉/精油\n     3.12.美胸美臀：3.12.1)使用精油 3.12.2)不使用精油\n\n    4.服务时长，总服务时长(服务项目的服务时长总和)。优先级：商品标题>项目单详情\n    需要映射到枚举值：(0-30]、(30-40]、(40-60]、(60-80]、(80-90]、(90-100]、(100-120]、(120-∞]（输出答案时需要输出具体的枚举值内容）\n\n    5.适用人群，包括性别、年龄、用户类型（出现“XX节”属于营销词，不能作为性别的判断，eg.女神节专属、母亲节，不能判断性别为女性） 优先级：购买限制>商品标题>项目单详情\n     枚举值：（注意：此项优先级：用户类型>性别>年龄，只需输出一个类别）\n     5.1用户类型：5.1.1新客价格（第一次使用该项目的用户）\n     5.2性别：5.2.1男性，5.2.2女性\n     5.3年龄：5.3.1儿童（0-12周岁）,5.3.2成人（18岁以上）\n     5.4不限通用(每人限购1份，不限年龄，性别)\n\n    6.适用日期/时段（注意：全天可用等于商家营业时间可用；闲时指的是周一到周五的下午4点前）  优先级：项目单详情>商品标题>购买须知\n    注意1：项目单详情中信息多处不符一致时，则取最小时段进行对比，eg1.A单适用日期：2025年7月1日-2025年9月1日，周一-周五10:00-19:00可用；B单适用日期2025.7.1-2025.10.1周一到周日10:00-22:00，则AB两单适用日期/时段不一致。eg2.2025年8月1日-2025年8月30日，周一-周五10:00-19:00可用；B单适用日期2025.7.1-2025.10.1周一-周天10:00-19:00可用，则AB两单适用日期/时段一致（不考虑年月日时格式）\n    注意2：适用日期/时段：从营业时间得到信息，仅看“周一-周日”、“xx月xx日-xx月xx日”、“xx:xx-xx:xx”、“xx点-xx点”等类似字眼，无需关注特殊节假日；时段：由“开始时间”和“结束时间”组成，输出具体的时间，例如“10:00-22:00” \n\n    7.非服务类商品：指的是除服务名称以外的内容，eg.“深层洁净60分钟+（含/送/赠）XX面膜2盒”，”非服务商品为“XX面膜，2盒”。如果是仅面膜、产品，零食、皮肤检测等非美容美体产品不算非服务产品，此时输出null。\n\n    8.白牌产品：指的是小厂商生产的没有牌子的商品，白牌是相对品牌而言的。\n\n\n    项目单匹配规则：根据抽取出来的要素和以下规则判断是否为同一项目单“注意：如果无法识别出来则默认为null”\n     1.服务名称：需完全一致，否则认为两个项目单不一致(不考虑顺序)。\n     2.适用部位：需完全一致，否则认为两个项目单不一致(不考虑顺序)。\n     3.服务方式：任意一方有值另一方空值，不可以视为一致。需要两侧都有值进行判断是否一致。\n     4.服务时长：如果任意一方有值另一方空值，可以视为一致。但当双方都有值时，双方时长一致才算一致。\n     5.适用人群：性别、年龄、用户类型要完全一样才算一致，如果任意一方空值则默认为“不限通用”，随后再对比出结果。\n     6.适用日期/时段：\n      1)当只有适用日期（年月日）时，日期精确到年月日相同则认为一致，eg.A单适用日期：2025年7月1日-2025年10月1日；B单适用日期2025.7.1-2025.10.1，则AB两单适用日期一致。（不考虑年月日格式）\n      2)当任意一方“适用日期”为空值，则取适用时段或者运营时间进行比较，AB两单之间起始及终止时间相差为1小时以内，可视为一致，超过1小时则为不一致。\n     7.非服务类商品：\n      1)纯非服务类商品，无需参与匹配。\n      2)若出现服务名称+非服务产品，针对服务内容按照规则匹配；非服务类商品需精准匹配，内容具体到名称+规格或者单位或者品牌。eg.“深层洁净60分钟+（含/送/赠）XX面膜2盒”，”非服务商品为“2盒XX面膜”\n    判断步骤：\n     1. 根据输入的项目单信息和规则抽取相应的要素，以及输出对应的枚举值内容\n     2. 根据抽取要素、枚举值内容和匹配规则来判断两个项目单是否匹配\n     \n     \n\n【Input】 \n11.项目单A:{'商品标题': '【品牌主打】名医堂特色五纬肩颈调理', '图文详情': '名医堂陈氏379年传承沉淀13代医者智慧结晶 陈氏太乙72绝技手法行云流水注意：店面的健康调理师，均为持证上岗', '有效期': '购买之日起30天内有效', '适用人数': '每张优惠券最多1人使用', '规则提醒': '不再与其他优惠同享', '购买限制': '每人限购1张', '营业时间': '周一至周日09:00-18:00', '项目单详情': [{'名称': '名医堂特色五纬肩颈', '分类': 'SPA按摩', '二级分类': '', '服务功效': '疏通经络、缓解疲劳、通畅血脉', '适用部位': '肩颈', '适用性别': '男女通用', '服务流程':服务步骤': [{'说明': '专业健康师咨询分析', '名称': '咨询分析', '时长': '5min', '部位': '肩颈'}, {'说明': '一、疏通：特色肩颈疏通', '名称': '经络疏通', '时长': '20 min ', '部位': '肩颈'}, {'说明': '二、特调：陈氏太乙肩颈特调技法', '名称': '经络疏通', '时长': '25 min ', '部位': '肩颈'}, {'说明': '三、热敷：特调膜热敷', '名称': '身体护理', '时长': '10 min ', '部位': '肩颈'}], '服务附赠': '无'温馨提示：提前半小时预约。}]} 项目单B:{'商品标题': '【匠人手工】五维肩颈特调', '营业时间': '09:00-18:00', '服务功效': '缓解疲劳、舒筋活络、放松肌肉', '适用性别': '不限', '适用部位': '肩颈','有效期': '有效期：购买后360天有效', '可用时间': '商家营业时间可用', '购买限制': '每人限购1份', '适用人数': '每张优惠券限1人使用', '其他规则': '单次消费最多使用1张优惠券;不与店内优惠同享;发票问题请询问商家', '项目单详情': [{'名称': '一疏通（特色草本肩颈疏通）', '分类': '指压按摩、肩颈按摩', '部位': '肩颈', '时长': '20分钟', '服务流程': '按摩放松(不使用精油)20分钟', '附赠服务': '无'}, {'名称': '三热敷（特色草本膜肩颈热敷）', '分类': '指压按摩、肩颈按摩', '部位': '肩颈', '时长': '25分钟', '服务流程': '热敷25分钟', '附赠服务': '无'}, {'名称': '二特调（陈氏太乙肩颈特调技法）', '分类': '肩颈按摩、指压按摩', '部位': '肩颈', '时长': '10分钟', '服务流程': '按摩放松(不使用精油)10分钟', '附赠服务': '无'}, {'名称': '资深调理师咨询','时长': '5分钟', '服务流程': '咨询分析5分钟', '附赠服务': '无'}]}\n\n\n\n【Output Requirement】\n 你的输出必须满足以下JSON_SCHEMA{'$schema': 'http://json-schema.org/draft-07/schema#', 'type': 'object', 'properties': {'项目单A': {'type': 'object', 'properties': {'1.服务名称': {'type': 'array', 'items': {'type': 'string', 'enum': ['1.1', '1.2', '1.3', '1.4', '1.5', '1.6', '1.7', '1.8', '1.9', '1.10', '1.11', '1.12', '1.13', '1.14', '1.15', 'null']}}, '2.适用部位': {'type': 'array', 'items': {'type': 'string', 'enum': ['2.1.1', '2.1.2', '2.1.3', '2.2.1', '2.2.2', '2.2.3', '2.2.4', '2.2.5', '2.2.6', '2.3.1', '2.4.1', '2.4.2', '2.5.1', '2.5.2', '2.5.3', '2.5.4', '2.5.5', '2.5.6', '2.6.1', '2.7.1', '2.7.2', '2.8.1', '2.8.2', '2.9.1', '2.9.2', 'null']}}, '3.服务方式': {'type': 'array', 'items': {'type': 'string', 'enum': ['3.1.1', '3.1.2', '3.1.3', '3.1.4', '3.2.1', '3.2.2', '3.2.3', '3.2.4', '3.2.5', '3.2.6', '3.2.7', '3.2.8', '3.2.9', '3.2.10', '3.2.11', '3.2.12', '3.2.13', '3.2.14', '3.2.15', '3.3.1', '3.3.2', '3.3.3', '3.3.4', '3.3.5', '3.4.1', '3.4.2', '3.4.3', '3.4.4', '3.4.5', '3.5.1', '3.5.2', '3.5.3', '3.5.4', '3.5.5', '3.6.1', '3.6.2', '3.6.3', '3.7.1', '3.7.2', '3.7.3', '3.7.4', '3.8.1', '3.8.2', '3.8.3', '3.8.4', '3.9.1', '3.9.2', '3.10.1', '3.10.2', '3.10.3', '3.10.4', '3.10.5', '3.10.6', '3.11.1', '3.11.2', '3.11.3', '3.11.4', '3.12.1', '3.12.2', 'null']}}, '4.服务时长': {'type': 'string', 'enum': ['(0-30]', '(30-40]', '(40-60]', '(60-80]', '(80-90]', '(90-100]', '(100-120]', '(120-∞]', 'null']}, '5.适用人群': {'type': 'string', 'enum': ['5.1.1', '5.2.1', '5.2.2', '5.3.1', '5.3.2', '5.4', 'null']}, '6.适用日期/时段': {'type': 'string'}, '7.非服务类商品': {'type': 'string'}}, 'required': ['1.服务名称', '2.适用部位', '3.服务方式', '4.服务时长', '5.适用人群', '6.适用日期/时段', '7.非服务类商品'], 'additionalProperties': False}, '项目单B': {'type': 'object', 'properties': {'1.服务名称': {'type': 'array', 'items': {'type': 'string', 'enum': ['1.1', '1.2', '1.3', '1.4', '1.5', '1.6', '1.7', '1.8', '1.9', '1.10', '1.11', '1.12', '1.13', '1.14', '1.15', 'null']}}, '2.适用部位': {'type': 'array', 'items': {'type': 'string', 'enum': ['2.1.1', '2.1.2', '2.1.3', '2.2.1', '2.2.2', '2.2.3', '2.2.4', '2.2.5', '2.2.6', '2.3.1', '2.4.1', '2.4.2', '2.5.1', '2.5.2', '2.5.3', '2.5.4', '2.5.5', '2.5.6', '2.6.1', '2.7.1', '2.7.2', '2.8.1', '2.8.2', '2.9.1', '2.9.2', 'null']}}, '3.服务方式': {'type': 'array', 'items': {'type': 'string', 'enum': ['3.1.1', '3.1.2', '3.1.3', '3.1.4', '3.2.1', '3.2.2', '3.2.3', '3.2.4', '3.2.5', '3.2.6', '3.2.7', '3.2.8', '3.2.9', '3.2.10', '3.2.11', '3.2.12', '3.2.13', '3.2.14', '3.2.15', '3.3.1', '3.3.2', '3.3.3', '3.3.4', '3.3.5', '3.4.1', '3.4.2', '3.4.3', '3.4.4', '3.4.5', '3.5.1', '3.5.2', '3.5.3', '3.5.4', '3.5.5', '3.6.1', '3.6.2', '3.6.3', '3.7.1', '3.7.2', '3.7.3', '3.7.4', '3.8.1', '3.8.2', '3.8.3', '3.8.4', '3.9.1', '3.9.2', '3.10.1', '3.10.2', '3.10.3', '3.10.4', '3.10.5', '3.10.6', '3.11.1', '3.11.2', '3.11.3', '3.11.4', '3.12.1', '3.12.2', 'null']}}, '4.服务时长': {'type': 'string', 'enum': ['(0-30]', '(30-40]', '(40-60]', '(60-80]', '(80-90]', '(90-100]', '(100-120]', '(120-∞]', 'null']}, '5.适用人群': {'type': 'string', 'enum': ['5.1.1', '5.2.1', '5.2.2', '5.3.1', '5.3.2', '5.4', 'null']}, '6.适用日期/时段': {'type': 'string'}, '7.非服务类商品': {'type': 'string'}}, 'required': ['1.服务名称', '2.适用部位', '3.服务方式', '4.服务时长', '5.适用人群', '6.适用日期/时段', '7.非服务类商品'], 'additionalProperties': False}, '匹配结果': {'type': 'string', 'enum': ['是', '否']}}, 'required': ['项目单A', '项目单B', '匹配结果'], 'additionalProperties': False}",
        "target": {
            "项目单A": {
                "1.服务名称": [
                    "1.10"
                ],
                "2.适用部位": [
                    "2.4.1"
                ],
                "3.服务方式": [
                    "3.7.2"
                ],
                "4.服务时长": "(40-60]",
                "5.适用人群": "5.4",
                "6.适用日期/时段": "周一至周日09:00-18:00",
                "7.非服务类商品": "null"
            },
            "项目单B": {
                "1.服务名称": [
                    "1.10"
                ],
                "2.适用部位": [
                    "2.4.1"
                ],
                "3.服务方式": [
                    "3.7.2"
                ],
                "4.服务时长": "(40-60]",
                "5.适用人群": "5.4",
                "6.适用日期/时段": "09:00-18:00",
                "7.非服务类商品": "null"
            },
            "匹配结果": "是"
        },
        "json_schema": {
            "$schema": "http://json-schema.org/draft-07/schema#",
            "type": "object",
            "properties": {
                "项目单A": {
                    "type": "object",
                    "properties": {
                        "1.服务名称": {
                            "type": "array",
                            "items": {
                                "type": "string",
                                "enum": [
                                    "1.1",
                                    "1.2",
                                    "1.3",
                                    "1.4",
                                    "1.5",
                                    "1.6",
                                    "1.7",
                                    "1.8",
                                    "1.9",
                                    "1.10",
                                    "1.11",
                                    "1.12",
                                    "1.13",
                                    "1.14",
                                    "1.15",
                                    "null"
                                ]
                            }
                        },
                        "2.适用部位": {
                            "type": "array",
                            "items": {
                                "type": "string",
                                "enum": [
                                    "2.1.1",
                                    "2.1.2",
                                    "2.1.3",
                                    "2.2.1",
                                    "2.2.2",
                                    "2.2.3",
                                    "2.2.4",
                                    "2.2.5",
                                    "2.2.6",
                                    "2.3.1",
                                    "2.4.1",
                                    "2.4.2",
                                    "2.5.1",
                                    "2.5.2",
                                    "2.5.3",
                                    "2.5.4",
                                    "2.5.5",
                                    "2.5.6",
                                    "2.6.1",
                                    "2.7.1",
                                    "2.7.2",
                                    "2.8.1",
                                    "2.8.2",
                                    "2.9.1",
                                    "2.9.2",
                                    "null"
                                ]
                            }
                        },
                        "3.服务方式": {
                            "type": "array",
                            "items": {
                                "type": "string",
                                "enum": [
                                    "3.1.1",
                                    "3.1.2",
                                    "3.1.3",
                                    "3.1.4",
                                    "3.2.1",
                                    "3.2.2",
                                    "3.2.3",
                                    "3.2.4",
                                    "3.2.5",
                                    "3.2.6",
                                    "3.2.7",
                                    "3.2.8",
                                    "3.2.9",
                                    "3.2.10",
                                    "3.2.11",
                                    "3.2.12",
                                    "3.2.13",
                                    "3.2.14",
                                    "3.2.15",
                                    "3.3.1",
                                    "3.3.2",
                                    "3.3.3",
                                    "3.3.4",
                                    "3.3.5",
                                    "3.4.1",
                                    "3.4.2",
                                    "3.4.3",
                                    "3.4.4",
                                    "3.4.5",
                                    "3.5.1",
                                    "3.5.2",
                                    "3.5.3",
                                    "3.5.4",
                                    "3.5.5",
                                    "3.6.1",
                                    "3.6.2",
                                    "3.6.3",
                                    "3.7.1",
                                    "3.7.2",
                                    "3.7.3",
                                    "3.7.4",
                                    "3.8.1",
                                    "3.8.2",
                                    "3.8.3",
                                    "3.8.4",
                                    "3.9.1",
                                    "3.9.2",
                                    "3.10.1",
                                    "3.10.2",
                                    "3.10.3",
                                    "3.10.4",
                                    "3.10.5",
                                    "3.10.6",
                                    "3.11.1",
                                    "3.11.2",
                                    "3.11.3",
                                    "3.11.4",
                                    "3.12.1",
                                    "3.12.2",
                                    "null"
                                ]
                            }
                        },
                        "4.服务时长": {
                            "type": "string",
                            "enum": [
                                "(0-30]",
                                "(30-40]",
                                "(40-60]",
                                "(60-80]",
                                "(80-90]",
                                "(90-100]",
                                "(100-120]",
                                "(120-∞]",
                                "null"
                            ]
                        },
                        "5.适用人群": {
                            "type": "string",
                            "enum": [
                                "5.1.1",
                                "5.2.1",
                                "5.2.2",
                                "5.3.1",
                                "5.3.2",
                                "5.4",
                                "null"
                            ]
                        },
                        "6.适用日期/时段": {
                            "type": "string"
                        },
                        "7.非服务类商品": {
                            "type": "string"
                        }
                    },
                    "required": [
                        "1.服务名称",
                        "2.适用部位",
                        "3.服务方式",
                        "4.服务时长",
                        "5.适用人群",
                        "6.适用日期/时段",
                        "7.非服务类商品"
                    ],
                    "additionalProperties": false
                },
                "项目单B": {
                    "type": "object",
                    "properties": {
                        "1.服务名称": {
                            "type": "array",
                            "items": {
                                "type": "string",
                                "enum": [
                                    "1.1",
                                    "1.2",
                                    "1.3",
                                    "1.4",
                                    "1.5",
                                    "1.6",
                                    "1.7",
                                    "1.8",
                                    "1.9",
                                    "1.10",
                                    "1.11",
                                    "1.12",
                                    "1.13",
                                    "1.14",
                                    "1.15",
                                    "null"
                                ]
                            }
                        },
                        "2.适用部位": {
                            "type": "array",
                            "items": {
                                "type": "string",
                                "enum": [
                                    "2.1.1",
                                    "2.1.2",
                                    "2.1.3",
                                    "2.2.1",
                                    "2.2.2",
                                    "2.2.3",
                                    "2.2.4",
                                    "2.2.5",
                                    "2.2.6",
                                    "2.3.1",
                                    "2.4.1",
                                    "2.4.2",
                                    "2.5.1",
                                    "2.5.2",
                                    "2.5.3",
                                    "2.5.4",
                                    "2.5.5",
                                    "2.5.6",
                                    "2.6.1",
                                    "2.7.1",
                                    "2.7.2",
                                    "2.8.1",
                                    "2.8.2",
                                    "2.9.1",
                                    "2.9.2",
                                    "null"
                                ]
                            }
                        },
                        "3.服务方式": {
                            "type": "array",
                            "items": {
                                "type": "string",
                                "enum": [
                                    "3.1.1",
                                    "3.1.2",
                                    "3.1.3",
                                    "3.1.4",
                                    "3.2.1",
                                    "3.2.2",
                                    "3.2.3",
                                    "3.2.4",
                                    "3.2.5",
                                    "3.2.6",
                                    "3.2.7",
                                    "3.2.8",
                                    "3.2.9",
                                    "3.2.10",
                                    "3.2.11",
                                    "3.2.12",
                                    "3.2.13",
                                    "3.2.14",
                                    "3.2.15",
                                    "3.3.1",
                                    "3.3.2",
                                    "3.3.3",
                                    "3.3.4",
                                    "3.3.5",
                                    "3.4.1",
                                    "3.4.2",
                                    "3.4.3",
                                    "3.4.4",
                                    "3.4.5",
                                    "3.5.1",
                                    "3.5.2",
                                    "3.5.3",
                                    "3.5.4",
                                    "3.5.5",
                                    "3.6.1",
                                    "3.6.2",
                                    "3.6.3",
                                    "3.7.1",
                                    "3.7.2",
                                    "3.7.3",
                                    "3.7.4",
                                    "3.8.1",
                                    "3.8.2",
                                    "3.8.3",
                                    "3.8.4",
                                    "3.9.1",
                                    "3.9.2",
                                    "3.10.1",
                                    "3.10.2",
                                    "3.10.3",
                                    "3.10.4",
                                    "3.10.5",
                                    "3.10.6",
                                    "3.11.1",
                                    "3.11.2",
                                    "3.11.3",
                                    "3.11.4",
                                    "3.12.1",
                                    "3.12.2",
                                    "null"
                                ]
                            }
                        },
                        "4.服务时长": {
                            "type": "string",
                            "enum": [
                                "(0-30]",
                                "(30-40]",
                                "(40-60]",
                                "(60-80]",
                                "(80-90]",
                                "(90-100]",
                                "(100-120]",
                                "(120-∞]",
                                "null"
                            ]
                        },
                        "5.适用人群": {
                            "type": "string",
                            "enum": [
                                "5.1.1",
                                "5.2.1",
                                "5.2.2",
                                "5.3.1",
                                "5.3.2",
                                "5.4",
                                "null"
                            ]
                        },
                        "6.适用日期/时段": {
                            "type": "string"
                        },
                        "7.非服务类商品": {
                            "type": "string"
                        }
                    },
                    "required": [
                        "1.服务名称",
                        "2.适用部位",
                        "3.服务方式",
                        "4.服务时长",
                        "5.适用人群",
                        "6.适用日期/时段",
                        "7.非服务类商品"
                    ],
                    "additionalProperties": false
                },
                "匹配结果": {
                    "type": "string",
                    "enum": [
                        "是",
                        "否"
                    ]
                }
            },
            "required": [
                "项目单A",
                "项目单B",
                "匹配结果"
            ],
            "additionalProperties": false
        },
        "no_required_eval_acc_keys": [
            "6.适用日期/时段"
        ],
        "model_response": "```json\n{\n  \"项目单A\": {\n    \"1.服务名称\": [\n      \"1.10\"\n    ],\n    \"2.适用部位\": [\n      \"2.4.1\"\n    ],\n    \"3.服务方式\": [\n      \"3.7.2\"\n    ],\n    \"4.服务时长\": \"(60-80]\",\n    \"5.适用人群\": \"5.4\",\n    \"6.适用日期/时段\": \"09:00-18:00\",\n    \"7.非服务类商品\": \"null\"\n  },\n  \"项目单B\": {\n    \"1.服务名称\": [\n      \"1.10\"\n    ],\n    \"2.适用部位\": [\n      \"2.4.1\"\n    ],\n    \"3.服务方式\": [\n      \"3.7.2\"\n    ],\n    \"4.服务时长\": \"(60-80]\",\n    \"5.适用人群\": \"5.4\",\n    \"6.适用日期/时段\": \"09:00-18:00\",\n    \"7.非服务类商品\": \"null\"\n  },\n  \"匹配结果\": \"是\"\n}\n```"
    },
    {
        "input": "【Background】\n【角色定义】你是一名消费者,你需要充分了解两个商家提供的生活项目并进行比较, 根据关键要素抽取规则和项目匹配规则来判断两个项目是否相同或匹配，并且以结构化数据的形式把两个项目结果展示出来。\n【Requirements】\n\n\n项目单的信息包括：商品标题、项目单详情、有效期、营业时间、适用人数、购买限制等。关键要素包括：服务名称、适用部位、服务方式、服务时长、适用人群、适用日期/时段、非服务类商品。（注意：如果有枚举值需要归类到枚举值，如果该内容在枚举值之外则默认为null；严格按照优先级，获取信息后不再考虑剩余。\"\n    \"1.服务名称，同一项目单可能包含多个项目，需要全部列举（注意：出现好评礼、会员礼所附赠的项目不计入服务名称。例如：“好评一次深层洁净60分钟”，则服务名称为“null”。优先级：商品标题 > 服务功效 > 服务流程/步骤\n     枚举值：\n     1.1深层洁净(收缩毛孔)\n     1.2补水保湿(皮肤清洁、毛孔洗澡)\n     1.3祛痘\n     1.4美白嫩肤\n     1.5淡斑祛斑\n     1.6紧致提拉\n     1.7修复护理\n     1.8脱毛\n     1.9眼部护理\n     1.10肩颈按摩\n     1.11SPA\n     1.12头疗\n     1.13养生调理\n     1.14瘦身纤体\n     1.15美胸美臀\n\n    2.适用部位：和服务名称对应。优先级：商品标题 > 服务功效 > 服务流程/步骤\n     枚举值：\n     2.1深层洁净/补水保湿/祛痘/美白嫩肤/淡斑祛斑/紧致提拉/修复护理：2.1.1面部,2.1.2部分面部,2.1.3背部 \n     2.2脱毛：2.2.1口唇,2.2.2腋下,2.2.3面部,2.2.4手臂,2.2.5腿部,2.2.6私密/比基尼\n     2.3眼部护理：2.3.1眼部 \n     2.4肩颈按摩：2.4.1肩颈,2.4.2肩颈+背 \n     2.5SPA：2.5.1全身,2.5.2肩颈+腰背,2.5.3肩颈+背部+腿部,2.5.4肩颈+腰腹+腿,2.5.5头+肩+颈+背,2.5.6背部 \n     2.6头疗：2.6.1头部\n     2.7养生调理：2.7.1全身(未指明部位),2.7.2局部(非全身，或者指明某个部位) \n     2.8瘦身纤体：2.8.1全身,2.8.2局部塑形 \n     2.9美胸美臀：2.9.1胸部,2.9.2臀部\n    \n    3.服务方式：和服务名称对应。优先级：项目单详情>商品标题\n     枚举值：（注意：1.未提到以下内容的，输出null;2.如果出现2种或者2种以上结果需要都输出）\n     3.1深层洁净：3.1.1)仪器(超微小气泡/大气泡/臭氧泡泡/魔法活氧泡泡) 3.1.2)海菲秀 3.1.3)泥膜/面膜 3.1.4)白牌产品 \n    3.2补水保湿：3.2.1)B5精华 3.2.2)修丽可 3.2.3)日式pola 3.2.4)日式晓姿 3.2.5)赫莲娜HR 3.2.6)伊芙珑evelom 3.2.7)海蓝之谜LA MER 3.2.8)瑞妍cellcosment 3.2.9)莱珀妮 LA PRAIRIE 3.2.10)迪奥DIOR 3.2.11)圣罗兰YSL 3.2.12)诚美DGR 3.2.13)法尔曼VALMONT 3.2.14)菲洛嘉FILORGA 3.2.15)白牌产品\n     3.3祛痘：3.3.1)手工针清/皮铲/护理 3.3.2)点阵激光 3.3.3)红蓝光/PDT光能/烤光 3.3.4)刷酸/果酸 3.3.5)草本 \n     3.4美白嫩肤：3.4.1)焕肤类 3.4.2)氨甲环酸 3.4.3)大牌产品(菲洛嘉) 3.4.4)普牌产品(欧诗漫) 3.4.5)白牌产品 \n     3.5紧致提拉：3.5.1)手法按摩类 3.5.2)抗糖祛黄/生物酶疗 3.5.3)木乃伊紧致 3.5.4)大牌产品(赫莲娜/日式POLA) 3.5.5)白牌产品 \n     3.6修复护理：3.6.1)酵素/乳糖酸/骨胶原/活性酶 3.6.2)大牌产品(赫莲娜/伊芙珑/海蓝之谜/瑞妍/莱珀妮/迪奥/圣罗兰诚美DGR/法尔曼/菲洛嘉) 3.6.3)白牌产品\n     3.7肩颈按摩：3.7.1)使用精油 3.7.2)不使用精油 3.7.3)热石精油 3.7.4)水疗\n     3.8全身SPA：3.8.1)使用精油 3.8.2)不使用精油 3.8.3)热石精油 3.8.4)水疗\n     3.9头疗：3.9.1)使用精油 3.9.2)不使用精油 \n     3.10养生调理：3.10.1)灸类 3.10.2)刮痧 3.10.3)罐类 3.10.4)蒸/浴类 3.10.5)经络/净排类 3.10.6)产后修复类\n     3.11瘦身纤体：3.11.1)针灸/拔罐/经络 3.11.2)刮痧 3.11.3)仪器 3.11.4)调理粉/精油\n     3.12.美胸美臀：3.12.1)使用精油 3.12.2)不使用精油\n\n    4.服务时长，总服务时长(服务项目的服务时长总和)。优先级：商品标题>项目单详情\n    需要映射到枚举值：(0-30]、(30-40]、(40-60]、(60-80]、(80-90]、(90-100]、(100-120]、(120-∞]（输出答案时需要输出具体的枚举值内容）\n\n    5.适用人群，包括性别、年龄、用户类型（出现“XX节”属于营销词，不能作为性别的判断，eg.女神节专属、母亲节，不能判断性别为女性） 优先级：购买限制>商品标题>项目单详情\n     枚举值：（注意：此项优先级：用户类型>性别>年龄，只需输出一个类别）\n     5.1用户类型：5.1.1新客价格（第一次使用该项目的用户）\n     5.2性别：5.2.1男性，5.2.2女性\n     5.3年龄：5.3.1儿童（0-12周岁）,5.3.2成人（18岁以上）\n     5.4不限通用(每人限购1份，不限年龄，性别)\n\n    6.适用日期/时段（注意：全天可用等于商家营业时间可用；闲时指的是周一到周五的下午4点前）  优先级：项目单详情>商品标题>购买须知\n    注意1：项目单详情中信息多处不符一致时，则取最小时段进行对比，eg1.A单适用日期：2025年7月1日-2025年9月1日，周一-周五10:00-19:00可用；B单适用日期2025.7.1-2025.10.1周一到周日10:00-22:00，则AB两单适用日期/时段不一致。eg2.2025年8月1日-2025年8月30日，周一-周五10:00-19:00可用；B单适用日期2025.7.1-2025.10.1周一-周天10:00-19:00可用，则AB两单适用日期/时段一致（不考虑年月日时格式）\n    注意2：适用日期/时段：从营业时间得到信息，仅看“周一-周日”、“xx月xx日-xx月xx日”、“xx:xx-xx:xx”、“xx点-xx点”等类似字眼，无需关注特殊节假日；时段：由“开始时间”和“结束时间”组成，输出具体的时间，例如“10:00-22:00” \n\n    7.非服务类商品：指的是除服务名称以外的内容，eg.“深层洁净60分钟+（含/送/赠）XX面膜2盒”，”非服务商品为“XX面膜，2盒”。如果是仅面膜、产品，零食、皮肤检测等非美容美体产品不算非服务产品，此时输出null。\n\n    8.白牌产品：指的是小厂商生产的没有牌子的商品，白牌是相对品牌而言的。\n\n\n    项目单匹配规则：根据抽取出来的要素和以下规则判断是否为同一项目单“注意：如果无法识别出来则默认为null”\n     1.服务名称：需完全一致，否则认为两个项目单不一致(不考虑顺序)。\n     2.适用部位：需完全一致，否则认为两个项目单不一致(不考虑顺序)。\n     3.服务方式：任意一方有值另一方空值，不可以视为一致。需要两侧都有值进行判断是否一致。\n     4.服务时长：如果任意一方有值另一方空值，可以视为一致。但当双方都有值时，双方时长一致才算一致。\n     5.适用人群：性别、年龄、用户类型要完全一样才算一致，如果任意一方空值则默认为“不限通用”，随后再对比出结果。\n     6.适用日期/时段：\n      1)当只有适用日期（年月日）时，日期精确到年月日相同则认为一致，eg.A单适用日期：2025年7月1日-2025年10月1日；B单适用日期2025.7.1-2025.10.1，则AB两单适用日期一致。（不考虑年月日格式）\n      2)当任意一方“适用日期”为空值，则取适用时段或者运营时间进行比较，AB两单之间起始及终止时间相差为1小时以内，可视为一致，超过1小时则为不一致。\n     7.非服务类商品：\n      1)纯非服务类商品，无需参与匹配。\n      2)若出现服务名称+非服务产品，针对服务内容按照规则匹配；非服务类商品需精准匹配，内容具体到名称+规格或者单位或者品牌。eg.“深层洁净60分钟+（含/送/赠）XX面膜2盒”，”非服务商品为“2盒XX面膜”\n    判断步骤：\n     1. 根据输入的项目单信息和规则抽取相应的要素，以及输出对应的枚举值内容\n     2. 根据抽取要素、枚举值内容和匹配规则来判断两个项目单是否匹配\n     \n     \n\n【Input】 \n12.项目单A:{'商品标题': '【头皮深层清洁】头皮大扫除 头皮屑头油有异味瘙痒', '图文详情': '头疗清洁养护步骤 t1、头皮深层清洁,瓦解毛囊油脂清洁老废角质调节水油平衡,改善头皮环境 t2、根据不同发质，用专项洗护套装，清洗头发2次； t3、深层的水疗养护，让头发更柔顺； t4、手工放松按摩头部，水疗仪按摩头皮；t5、洗一次头可以放松休息一小时，养出健康秀发；'适用人数': '每张优惠券最多1人使用', '规则提醒': '不再与其他优惠同享', '购买限制': '每人限购1张', '营业时间': '周一至周日 10:00-21:00', '项目单详情': [{'名称': '护理', '分类': '护理', '二级分类': '', '服务功效': '清洁控油补水，缓解压力', '适用部位': '头发，头', '服务流程': '仪器检测：头皮检测仪、头皮护理仪，约10分钟；清洁头皮20分钟；深度护理10分钟',温馨提示：购买后90天内有效，可用时间：11:00-20:30，请您提前2小时进行预约。}]} 项目单B:{'商品标题': '【活肤水疗】保湿+深层补水', '营业时间': '10:00-21:00', '服务功效': '补水保湿、美白嫩肤、敏感修复', '适用性别': '女士', '适用部位': '全脸部', '服务时长': '35分钟', '有效期': '有效期：购买后360天有效', '可用时间': '商家营业时间可用', '购买限制': '每人限购1份', '适用人数': '每张优惠券限1人使用', '其他规则': '单次消费不限制使用张数;不与店内优惠同享;发票问题请询问商家', '项目单详情': [{'名称': '活肤水疗', '分类': '水氧活肤', '部位': '', '时长': '35分钟', '服务流程': '补水保湿全脸部35分钟', '到店即享 ': '免费茶歇零食、提供补妆用品、提供补妆服务'}]}\n\n\n\n【Output Requirement】\n 你的输出必须满足以下JSON_SCHEMA{'$schema': 'http://json-schema.org/draft-07/schema#', 'type': 'object', 'properties': {'项目单A': {'type': 'object', 'properties': {'1.服务名称': {'type': 'array', 'items': {'type': 'string', 'enum': ['1.1', '1.2', '1.3', '1.4', '1.5', '1.6', '1.7', '1.8', '1.9', '1.10', '1.11', '1.12', '1.13', '1.14', '1.15', 'null']}}, '2.适用部位': {'type': 'array', 'items': {'type': 'string', 'enum': ['2.1.1', '2.1.2', '2.1.3', '2.2.1', '2.2.2', '2.2.3', '2.2.4', '2.2.5', '2.2.6', '2.3.1', '2.4.1', '2.4.2', '2.5.1', '2.5.2', '2.5.3', '2.5.4', '2.5.5', '2.5.6', '2.6.1', '2.7.1', '2.7.2', '2.8.1', '2.8.2', '2.9.1', '2.9.2', 'null']}}, '3.服务方式': {'type': 'array', 'items': {'type': 'string', 'enum': ['3.1.1', '3.1.2', '3.1.3', '3.1.4', '3.2.1', '3.2.2', '3.2.3', '3.2.4', '3.2.5', '3.2.6', '3.2.7', '3.2.8', '3.2.9', '3.2.10', '3.2.11', '3.2.12', '3.2.13', '3.2.14', '3.2.15', '3.3.1', '3.3.2', '3.3.3', '3.3.4', '3.3.5', '3.4.1', '3.4.2', '3.4.3', '3.4.4', '3.4.5', '3.5.1', '3.5.2', '3.5.3', '3.5.4', '3.5.5', '3.6.1', '3.6.2', '3.6.3', '3.7.1', '3.7.2', '3.7.3', '3.7.4', '3.8.1', '3.8.2', '3.8.3', '3.8.4', '3.9.1', '3.9.2', '3.10.1', '3.10.2', '3.10.3', '3.10.4', '3.10.5', '3.10.6', '3.11.1', '3.11.2', '3.11.3', '3.11.4', '3.12.1', '3.12.2', 'null']}}, '4.服务时长': {'type': 'string', 'enum': ['(0-30]', '(30-40]', '(40-60]', '(60-80]', '(80-90]', '(90-100]', '(100-120]', '(120-∞]', 'null']}, '5.适用人群': {'type': 'string', 'enum': ['5.1.1', '5.2.1', '5.2.2', '5.3.1', '5.3.2', '5.4', 'null']}, '6.适用日期/时段': {'type': 'string'}, '7.非服务类商品': {'type': 'string'}}, 'required': ['1.服务名称', '2.适用部位', '3.服务方式', '4.服务时长', '5.适用人群', '6.适用日期/时段', '7.非服务类商品'], 'additionalProperties': False}, '项目单B': {'type': 'object', 'properties': {'1.服务名称': {'type': 'array', 'items': {'type': 'string', 'enum': ['1.1', '1.2', '1.3', '1.4', '1.5', '1.6', '1.7', '1.8', '1.9', '1.10', '1.11', '1.12', '1.13', '1.14', '1.15', 'null']}}, '2.适用部位': {'type': 'array', 'items': {'type': 'string', 'enum': ['2.1.1', '2.1.2', '2.1.3', '2.2.1', '2.2.2', '2.2.3', '2.2.4', '2.2.5', '2.2.6', '2.3.1', '2.4.1', '2.4.2', '2.5.1', '2.5.2', '2.5.3', '2.5.4', '2.5.5', '2.5.6', '2.6.1', '2.7.1', '2.7.2', '2.8.1', '2.8.2', '2.9.1', '2.9.2', 'null']}}, '3.服务方式': {'type': 'array', 'items': {'type': 'string', 'enum': ['3.1.1', '3.1.2', '3.1.3', '3.1.4', '3.2.1', '3.2.2', '3.2.3', '3.2.4', '3.2.5', '3.2.6', '3.2.7', '3.2.8', '3.2.9', '3.2.10', '3.2.11', '3.2.12', '3.2.13', '3.2.14', '3.2.15', '3.3.1', '3.3.2', '3.3.3', '3.3.4', '3.3.5', '3.4.1', '3.4.2', '3.4.3', '3.4.4', '3.4.5', '3.5.1', '3.5.2', '3.5.3', '3.5.4', '3.5.5', '3.6.1', '3.6.2', '3.6.3', '3.7.1', '3.7.2', '3.7.3', '3.7.4', '3.8.1', '3.8.2', '3.8.3', '3.8.4', '3.9.1', '3.9.2', '3.10.1', '3.10.2', '3.10.3', '3.10.4', '3.10.5', '3.10.6', '3.11.1', '3.11.2', '3.11.3', '3.11.4', '3.12.1', '3.12.2', 'null']}}, '4.服务时长': {'type': 'string', 'enum': ['(0-30]', '(30-40]', '(40-60]', '(60-80]', '(80-90]', '(90-100]', '(100-120]', '(120-∞]', 'null']}, '5.适用人群': {'type': 'string', 'enum': ['5.1.1', '5.2.1', '5.2.2', '5.3.1', '5.3.2', '5.4', 'null']}, '6.适用日期/时段': {'type': 'string'}, '7.非服务类商品': {'type': 'string'}}, 'required': ['1.服务名称', '2.适用部位', '3.服务方式', '4.服务时长', '5.适用人群', '6.适用日期/时段', '7.非服务类商品'], 'additionalProperties': False}, '匹配结果': {'type': 'string', 'enum': ['是', '否']}}, 'required': ['项目单A', '项目单B', '匹配结果'], 'additionalProperties': False}",
        "target": {
            "项目单A": {
                "1.服务名称": [
                    "1.12"
                ],
                "2.适用部位": [
                    "2.6.1"
                ],
                "3.服务方式": [
                    "3.9.2"
                ],
                "4.服务时长": "(30-40]",
                "5.适用人群": "5.4",
                "6.适用日期/时段": "11:00-20:30",
                "7.非服务类商品": "null"
            },
            "项目单B": {
                "1.服务名称": [
                    "1.2"
                ],
                "2.适用部位": [
                    "2.1.1"
                ],
                "3.服务方式": [
                    "3.2.15"
                ],
                "4.服务时长": "(30-40]",
                "5.适用人群": "5.2.2",
                "6.适用日期/时段": "10:00-21:00",
                "7.非服务类商品": "null"
            },
            "匹配结果": "否"
        },
        "json_schema": {
            "$schema": "http://json-schema.org/draft-07/schema#",
            "type": "object",
            "properties": {
                "项目单A": {
                    "type": "object",
                    "properties": {
                        "1.服务名称": {
                            "type": "array",
                            "items": {
                                "type": "string",
                                "enum": [
                                    "1.1",
                                    "1.2",
                                    "1.3",
                                    "1.4",
                                    "1.5",
                                    "1.6",
                                    "1.7",
                                    "1.8",
                                    "1.9",
                                    "1.10",
                                    "1.11",
                                    "1.12",
                                    "1.13",
                                    "1.14",
                                    "1.15",
                                    "null"
                                ]
                            }
                        },
                        "2.适用部位": {
                            "type": "array",
                            "items": {
                                "type": "string",
                                "enum": [
                                    "2.1.1",
                                    "2.1.2",
                                    "2.1.3",
                                    "2.2.1",
                                    "2.2.2",
                                    "2.2.3",
                                    "2.2.4",
                                    "2.2.5",
                                    "2.2.6",
                                    "2.3.1",
                                    "2.4.1",
                                    "2.4.2",
                                    "2.5.1",
                                    "2.5.2",
                                    "2.5.3",
                                    "2.5.4",
                                    "2.5.5",
                                    "2.5.6",
                                    "2.6.1",
                                    "2.7.1",
                                    "2.7.2",
                                    "2.8.1",
                                    "2.8.2",
                                    "2.9.1",
                                    "2.9.2",
                                    "null"
                                ]
                            }
                        },
                        "3.服务方式": {
                            "type": "array",
                            "items": {
                                "type": "string",
                                "enum": [
                                    "3.1.1",
                                    "3.1.2",
                                    "3.1.3",
                                    "3.1.4",
                                    "3.2.1",
                                    "3.2.2",
                                    "3.2.3",
                                    "3.2.4",
                                    "3.2.5",
                                    "3.2.6",
                                    "3.2.7",
                                    "3.2.8",
                                    "3.2.9",
                                    "3.2.10",
                                    "3.2.11",
                                    "3.2.12",
                                    "3.2.13",
                                    "3.2.14",
                                    "3.2.15",
                                    "3.3.1",
                                    "3.3.2",
                                    "3.3.3",
                                    "3.3.4",
                                    "3.3.5",
                                    "3.4.1",
                                    "3.4.2",
                                    "3.4.3",
                                    "3.4.4",
                                    "3.4.5",
                                    "3.5.1",
                                    "3.5.2",
                                    "3.5.3",
                                    "3.5.4",
                                    "3.5.5",
                                    "3.6.1",
                                    "3.6.2",
                                    "3.6.3",
                                    "3.7.1",
                                    "3.7.2",
                                    "3.7.3",
                                    "3.7.4",
                                    "3.8.1",
                                    "3.8.2",
                                    "3.8.3",
                                    "3.8.4",
                                    "3.9.1",
                                    "3.9.2",
                                    "3.10.1",
                                    "3.10.2",
                                    "3.10.3",
                                    "3.10.4",
                                    "3.10.5",
                                    "3.10.6",
                                    "3.11.1",
                                    "3.11.2",
                                    "3.11.3",
                                    "3.11.4",
                                    "3.12.1",
                                    "3.12.2",
                                    "null"
                                ]
                            }
                        },
                        "4.服务时长": {
                            "type": "string",
                            "enum": [
                                "(0-30]",
                                "(30-40]",
                                "(40-60]",
                                "(60-80]",
                                "(80-90]",
                                "(90-100]",
                                "(100-120]",
                                "(120-∞]",
                                "null"
                            ]
                        },
                        "5.适用人群": {
                            "type": "string",
                            "enum": [
                                "5.1.1",
                                "5.2.1",
                                "5.2.2",
                                "5.3.1",
                                "5.3.2",
                                "5.4",
                                "null"
                            ]
                        },
                        "6.适用日期/时段": {
                            "type": "string"
                        },
                        "7.非服务类商品": {
                            "type": "string"
                        }
                    },
                    "required": [
                        "1.服务名称",
                        "2.适用部位",
                        "3.服务方式",
                        "4.服务时长",
                        "5.适用人群",
                        "6.适用日期/时段",
                        "7.非服务类商品"
                    ],
                    "additionalProperties": false
                },
                "项目单B": {
                    "type": "object",
                    "properties": {
                        "1.服务名称": {
                            "type": "array",
                            "items": {
                                "type": "string",
                                "enum": [
                                    "1.1",
                                    "1.2",
                                    "1.3",
                                    "1.4",
                                    "1.5",
                                    "1.6",
                                    "1.7",
                                    "1.8",
                                    "1.9",
                                    "1.10",
                                    "1.11",
                                    "1.12",
                                    "1.13",
                                    "1.14",
                                    "1.15",
                                    "null"
                                ]
                            }
                        },
                        "2.适用部位": {
                            "type": "array",
                            "items": {
                                "type": "string",
                                "enum": [
                                    "2.1.1",
                                    "2.1.2",
                                    "2.1.3",
                                    "2.2.1",
                                    "2.2.2",
                                    "2.2.3",
                                    "2.2.4",
                                    "2.2.5",
                                    "2.2.6",
                                    "2.3.1",
                                    "2.4.1",
                                    "2.4.2",
                                    "2.5.1",
                                    "2.5.2",
                                    "2.5.3",
                                    "2.5.4",
                                    "2.5.5",
                                    "2.5.6",
                                    "2.6.1",
                                    "2.7.1",
                                    "2.7.2",
                                    "2.8.1",
                                    "2.8.2",
                                    "2.9.1",
                                    "2.9.2",
                                    "null"
                                ]
                            }
                        },
                        "3.服务方式": {
                            "type": "array",
                            "items": {
                                "type": "string",
                                "enum": [
                                    "3.1.1",
                                    "3.1.2",
                                    "3.1.3",
                                    "3.1.4",
                                    "3.2.1",
                                    "3.2.2",
                                    "3.2.3",
                                    "3.2.4",
                                    "3.2.5",
                                    "3.2.6",
                                    "3.2.7",
                                    "3.2.8",
                                    "3.2.9",
                                    "3.2.10",
                                    "3.2.11",
                                    "3.2.12",
                                    "3.2.13",
                                    "3.2.14",
                                    "3.2.15",
                                    "3.3.1",
                                    "3.3.2",
                                    "3.3.3",
                                    "3.3.4",
                                    "3.3.5",
                                    "3.4.1",
                                    "3.4.2",
                                    "3.4.3",
                                    "3.4.4",
                                    "3.4.5",
                                    "3.5.1",
                                    "3.5.2",
                                    "3.5.3",
                                    "3.5.4",
                                    "3.5.5",
                                    "3.6.1",
                                    "3.6.2",
                                    "3.6.3",
                                    "3.7.1",
                                    "3.7.2",
                                    "3.7.3",
                                    "3.7.4",
                                    "3.8.1",
                                    "3.8.2",
                                    "3.8.3",
                                    "3.8.4",
                                    "3.9.1",
                                    "3.9.2",
                                    "3.10.1",
                                    "3.10.2",
                                    "3.10.3",
                                    "3.10.4",
                                    "3.10.5",
                                    "3.10.6",
                                    "3.11.1",
                                    "3.11.2",
                                    "3.11.3",
                                    "3.11.4",
                                    "3.12.1",
                                    "3.12.2",
                                    "null"
                                ]
                            }
                        },
                        "4.服务时长": {
                            "type": "string",
                            "enum": [
                                "(0-30]",
                                "(30-40]",
                                "(40-60]",
                                "(60-80]",
                                "(80-90]",
                                "(90-100]",
                                "(100-120]",
                                "(120-∞]",
                                "null"
                            ]
                        },
                        "5.适用人群": {
                            "type": "string",
                            "enum": [
                                "5.1.1",
                                "5.2.1",
                                "5.2.2",
                                "5.3.1",
                                "5.3.2",
                                "5.4",
                                "null"
                            ]
                        },
                        "6.适用日期/时段": {
                            "type": "string"
                        },
                        "7.非服务类商品": {
                            "type": "string"
                        }
                    },
                    "required": [
                        "1.服务名称",
                        "2.适用部位",
                        "3.服务方式",
                        "4.服务时长",
                        "5.适用人群",
                        "6.适用日期/时段",
                        "7.非服务类商品"
                    ],
                    "additionalProperties": false
                },
                "匹配结果": {
                    "type": "string",
                    "enum": [
                        "是",
                        "否"
                    ]
                }
            },
            "required": [
                "项目单A",
                "项目单B",
                "匹配结果"
            ],
            "additionalProperties": false
        },
        "no_required_eval_acc_keys": [
            "6.适用日期/时段"
        ],
        "model_response": "```json\n{\n    \"项目单A\": {\n        \"1.服务名称\": [\"1.12\"],\n        \"2.适用部位\": [\"2.6.1\"],\n        \"3.服务方式\": [\"3.9.1\"],\n        \"4.服务时长\": \"(30-40]\",\n        \"5.适用人群\": \"5.4\",\n        \"6.适用日期/时段\": \"11:00-20:30\",\n        \"7.非服务类商品\": \"null\"\n    },\n    \"项目单B\": {\n        \"1.服务名称\": [\"1.2\"],\n        \"2.适用部位\": [\"2.1.1\"],\n        \"3.服务方式\": [\"3.2.15\"],\n        \"4.服务时长\": \"(30-40]\",\n        \"5.适用人群\": \"5.2.2\",\n        \"6.适用日期/时段\": \"10:00-21:00\",\n        \"7.非服务类商品\": \"null\"\n    },\n    \"匹配结果\": \"否\"\n}\n```"
    }
]